Workbook
Name \C: #REF!
Name \D: #REF!
Name _1_5digit: #REF!
Name _Q09: #REF!
Name a: [6]ISICrev3.1!$E:$F
Name AA: #REF!
Name aaa: #REF!
Name AAAAAA: #REF!
Name B: #REF!
Name Base: '[7]LCO - Inputs'!$A$70
Name bvdp: #REF!
Name bvdpin: #REF!
Name Calculated_Relationship_HS12___HS07: '[8]Correlation HS2012-HS2007'!#REF!
Name ccc: #REF!
Name com_desc: [9]com_desc!$A$1:$B$96
Name consol: #REF!
Name consolID: #REF!
Name desc: #REF!
Name desc_frm180: [10]desc_frm180!$A$2:$C$181
Name desc_frm92: [11]desc_frm92!$A$2:$B$94
Name ER: #REF!
Name export_prt: #REF!
Name f: #REF!
Name FRAMEIND: #REF!
Name FRAMEIND2: #REF!
Name frm: #REF!
Name frm_com: #REF!
Name frm_ind: #REF!
Name frm180_desc: [10]desc_frm180!$B$2:$C$181
Name frm92_nita: [13]MSIC!$A$1:$C$10782
Name G_prt: #REF!
Name GDPIO: #REF!
Name GDPUPDT: #REF!
Name GFCF_prt: #REF!
Name gg: #REF!
Name go_level_top1: OFFSET('[14]35-sector'!$E$36,MATCH(#REF!,'[14]35-sector'!$E$37:$E$71,0),2,1,8)
Name govt: [15]frmind92!$C$178:$D$235
Name hh: #REF!
Name HH_prt: #REF!
Name HS: '[16]HS02_CPC1.1_SITC3_ISIC3.1 (2)'!#REF!
Name ID_prt: #REF!
Name in: #REF!
Name ind: #REF!
Name INP: [17]MSIC!$A$1:$C$10782
Name input: #REF!
Name io: #REF!
Name IO_Code: #REF!
Name IO_Code2: #REF!
Name iocom: #REF!
Name kol: #REF!
Name Large: '[7]LCO - Inputs'!$A$71
Name M1_stone: '[14]2000'!$E$1382:$BV$1451
Name M2_stone: '[14]2000'!$E$1524:$BV$1593
Name M3_stone: '[14]2000'!$E$1737:$BV$1806
Name makebv: #REF!
Name makect: #REF!
Name makeout: #REF!
Name Malaysia_curr_pub: #REF!
Name Malaysia_FD_Source_Curr: #REF!
Name Matrix1: #REF!

Sheet COVER
B7: SAF & CORSIA DEMAND PROJECTION MODEL
B8: ="Model Name: "&MID(CELL("filename"),FIND("[",CELL("filename"))+1,FIND("]",CELL("filename"))-FIND("[",CELL("filename"))-1) -> Model Name: SAF_CORSIA_Demand_Model_v2.3.xlsx | G8: =TODAY() -> 46191
B9: Purpose | C9: Bottom-up demand modelling and scenario building for jet fuel and SAF from different regions
B10: Version | C10: 2.3
B11: Developed by | C11: Hammad Ainuddin
B12: Reviewed by | C12: David Toh
B13: Approved by
B16: Description
B17: This model provides a route-level, bottom-up analysis of jet fuel demand, CO₂ emissions, SAF (Sustainable Aviation Fuel) mandate obligations, and CORSIA carbon offset requirements for 1,274 international routes operated by 160 airlines across all major world regions. Six SAF demand scenarios (A&M Base, A&M Policy-Driven, A&M Climate Push, IATA Reference, Top-Down Policy, Top-Down Accelerated) are projected from 2025 to 2050. All parameters are centralised in the INPUTS (including SCENARIOS) sheet and propagate automatically to calculation and summary sheets.
B26: Document control
B28: Version | C28: Revision notes | D28: Revision date | E28: Authors
B29: v2.3 | C29: Refine scenario parameters, UN Stats country value and mapping misalignments in the Routes sheet | D29: 46189 | E29: HA
B30: v2.2 | C30: Develop A&M Scenarios, refine spreadsheet flow-structure and remove redundant tabs | D30: 46183 | E30: HA
B31: v2.1 | C31: Detailed review on routes and aligment with UN Stats (International Aviation Bunker) | D31: 46177 | E31: HA
B32: v2 | C32: Expansion of routes to include missing airlines and routes (from 64 to ~1274 routes) | D32: 46176 | E32: HA
B33: v1 | C33: Initial draft prepared | D33: 46157 | E33: HA
B36: MODEL SCOPE
B37: 1260 | C37: Flight Routes | D37: International trunk routes across 6 world regions, operated by major carriers in all scenarios
B38: 160 | C38: Operators | D38: 135 passenger airlines, 13 freighter airlines, 2 cargo integrators, 5 ACMI/charter, 5 other
B39: 14 | C39: Aircraft Types | D39: Narrowbody, widebody, large widebody and freighter variants
B40: 40 | C40: Data Sources | D40: ICAO, IATA, OAG, IEA, Airbus, Boeing, regulatory texts
B41: 4 | C41: A&M SAF Scenarios | D41: A&M Base, A&M Policy-Driven, A&M Climate Push, IATA Reference
B42: 2 | C42: Top-down SAF Scenarios | D42: Policy (mandates), Accelerated (1.5°C)
B43: 2025–2050 | C43: Projection Horizon | D43: Annual granularity 2025–2030; milestone years to 2050
B45: WORKBOOK STRUCTURE
B46: Type | C46: Sheet Name | D46: Description
B47: COVER | C47: COVER | D47: This sheet — model description, structure, and legend
B48: INPUT | C48: ▌ INPUT ▌ | D48: Divider — all sheets below are input / reference data
B49: INPUT | C49: INPUTS | D49: All model parameters: constants, growth rates, SAF mandates, scenarios
B50: INPUT | C50: OPERATORS | D50: Airline and cargo operator registry (160 operators)
B51: INPUT | C51: AIRCRAFT | D51: Aircraft performance lookup table (14 types)
B52: CALC | C52: ▌ CALC ▌ | D52: Divider — all sheets below are calculation sheets
B53: CALC | C53: ROUTES | D53: Route-level fuel, CO₂ and SAF calculations (1274 routes)
B54: CALC | C54: SUMMARY | D54: Comparison between different SAF% blend scenarios (2025–2040)
B57: CELL COLOUR LEGEND
B58: Colour | C58: Name | D58: Colour Name | E58: Description
B59: ■ | C59: INPUT cell | D59: Yellow | E59: User-editable parameter. Safe to modify. Located primarily in INPUTS sheet.
B60: ■ | C60: CALC cell | D60: Blue | E60: Formula-driven calculation. Do NOT edit manually — will be overwritten.
B61: ■ | C61: OUTPUT cell | D61: Green | E61: Final result or derived metric. Reads from CALC sheets.
B62: ■ | C62: LINK cell | D62: Peach | E62: Cross-sheet reference (=SheetName!CellRef). Formula-derived; do not edit.
B63: ■ | C63: HEADER / LABEL | D63: Navy | E63: Section header or row/column label. Not data.
B64: ■ | C64: SUB-HEADER | D64: Blue | E64: Sub-section header. Not data.
B65: ■ | C65: Alternating row | D65: Lt. Blue | E65: Zebra-stripe for readability. No semantic meaning.

Sheet ▌ INPUT ▌
A1: INPUT

Sheet INPUTS
A1: INPUTS — All Model Parameters & Lookup Tables | Yellow = user-editable | Blue = formula-derived
A2: Editing values in this sheet automatically updates ROUTES, REGIONAL, CORSIA, SAF_DEMAND, and SUMMARY. Do NOT edit cells coloured blue (formula-derived). All monetary values in USD.
A4: A AVIATION CONSTANTS
A5: Parameter | B5: Value | C5: Unit | D5: Source | E5: Notes
A6: CO₂ Emission Factor — Jet A-1 | B6: 3.16 | C6: t CO₂ / t fuel | D6: IPCC AR6 / ICAO Annex 16 | E6: Standard factor; used in all route CO₂ calcs
A7: Jet A-1 Fuel Density | B7: 0.8 | C7: kg/L (t/m³) | D7: ASTM D1655 | E7: Used to convert mass (t) → volume (kL)
A8: Average Pax Load Factor | B8: 0.82 | C8: fraction | D8: IATA 2024 Annual Review | E8: Used for seat-based fuel benchmarking
A9: Average Cargo Mass Load Factor | B9: 0.72 | C9: fraction | D9: IATA/Boeing WACF 2024 | E9: Typical freighter payload utilisation
A10: CORSIA Intl Route Fraction | B10: 0.85 | C10: fraction | D10: ICAO A41-22 | E10: % of aviation emissions from international routes
A11: Global Efficiency Improvement | B11: -0.013 | C11: %/yr | D11: IATA/ATAG net-zero roadmap | E11: Fleet renewal + ATM; negative = improvement
A13: B CORSIA FRAMEWORK PARAMETERS
A14: Parameter | B14: Value | C14: Unit | D14: Source | E14: Notes
A15: Global Intl Aviation CO₂ — 2019 (actual) | B15: 359.4 | C15: Mt CO₂ | D15: ICAO Annual Report 2022 | E15: Pre-pandemic baseline reference year
A16: CORSIA Baseline Factor | B16: 0.85 | C16: fraction | D16: ICAO Assembly Resolution A41-22 | E16: Revised 2022: 85% of 2019 emissions
A17: CORSIA Baseline Emissions | B17: =B15*B16 -> 305.49 | C17: Mt CO₂ | D17: INPUTS calculated | E17: Auto-calculated: 2019 actual × baseline factor
A18: Global Intl CO₂ — 2025 Estimate | B18: 900 | C18: Mt CO₂ | D18: ICAO/IATA 2025 forecast | E18: Post-recovery trajectory
A19: CORSIA Phase 1 Start Year | B19: 2024 | C19: year | D19: ICAO A41-22 | E19: Voluntary phase
A20: CORSIA Phase 1 End Year | B20: 2026 | C20: year | D20: ICAO A41-22
A21: CORSIA Phase 2 Start Year | B21: 2027 | C21: year | D21: ICAO A41-22 | E21: Mandatory for all participating states
A22: CORSIA Phase 2 End Year | B22: 2035 | C22: year | D22: ICAO A41-22
A23: Phase 1 Route Coverage (% of intl routes) | B23: 0.8 | C23: fraction | D23: 126 CORSIA participating states | E23: Routes where both endpoints participate
A24: Phase 2 Route Coverage (% of intl routes) | B24: 0.95 | C24: fraction | D24: ICAO mandatory expansion | E24: Excludes LDC/SIDS/LLDC exemptions
A26: C CARBON CREDIT PRICES — CORSIA EEUs ($/t CO₂e)
A27: Phase | B27: Period | C27: Low ($/t) | D27: Mid ($/t) | E27: High ($/t)
A28: Phase 1 | B28: 2024–2026 | C28: 18 | D28: 35 | E28: 51
A29: Phase 2 | B29: 2027–2035 | C29: 27 | D29: 60 | E29: 91
A30: Post-2035 | B30: 2036–2050 | C30: 100 | D30: 150 | E30: 200
A32: D TRAFFIC GROWTH RATES — Net (pa, after efficiency) by Origin Region
A33: Origin Region | B33: Net Growth Rate (pa) | C33: Basis / Source | D33: CORSIA P1 Scope Note | F33: Notes
A34: EU | B34: 0.025 | C34: ICAO/OAG European Aviation Outlook | D34: All intl EU-state routes P1 eligible; ReFuelEU mandate applies | F34: Net of 1.3%/yr efficiency gain
A35: US | B35: 0.02 | C35: FAA Aerospace Forecast FY2024 | D35: All US intl routes P1 eligible; US domestic excluded | F35: Mature market; lower growth
A36: APAC | B36: 0.04 | C36: IATA APAC Growth Outlook 2024 | D36: P1 eligible if dest≠CN/IN/VN; JP/KR/AU/NZ/SG/MY/TH/PH/ID all participate | F36: Fastest growing region
A37: MENA | B37: 0.045 | C37: IATA GCC Aviation Outlook | D37: All GCC states P1 eligible | F37: Hub expansion; high growth
A38: LATAM | B38: 0.035 | C38: IATA Latin America Forecast | D38: P1 eligible excl. BR origin/dest; Colombia/Chile/Peru/Ecuador/Mexico all P1 | F38: Recovery + emerging markets
A39: ROW | B39: 0.03 | C39: ICAO/IATA blended forecast | D39: Excl. RU; most African states P1 eligible | F39: Mixed market maturity
A41: E SAF MANDATE % — Airport-Level Lookup (ROUTES cols Y & AA reference this table)
A42: VLOOKUP key: Origin Airport Code (ROUTES col E). Returns SAF blend % for 2025 and 2030. Airports not listed → formula returns 0% (no mandate).
A43: Origin Airport (IATA) | B43: SAF% 2025 | C43: SAF% 2030 | D43: SAF% 2035 | E43: SAF% 2040 | F43: SAF% 2045 | G43: SAF% 2050 | H43: Mandate Basis | I43: Regulatory Reference
A44: FRA | B44: 0.02 | C44: 0.06 | D44: 0.15 | E44: 0.3 | F44: 0.4 | G44: 0.5 | H44: EU – ReFuelEU | I44: Reg (EU) 2023/2405
A45: CDG | B45: 0.02 | C45: 0.06 | D45: 0.15 | E45: 0.3 | F45: 0.4 | G45: 0.5 | H45: EU – ReFuelEU | I45: Reg (EU) 2023/2405
A46: AMS | B46: 0.02 | C46: 0.06 | D46: 0.15 | E46: 0.3 | F46: 0.4 | G46: 0.5 | H46: EU – ReFuelEU | I46: Reg (EU) 2023/2405
A47: MAD | B47: 0.02 | C47: 0.06 | D47: 0.15 | E47: 0.3 | F47: 0.4 | G47: 0.5 | H47: EU – ReFuelEU | I47: Reg (EU) 2023/2405
A48: BCN | B48: 0.02 | C48: 0.06 | D48: 0.15 | E48: 0.3 | F48: 0.4 | G48: 0.5 | H48: EU – ReFuelEU | I48: Reg (EU) 2023/2405
A49: FCO | B49: 0.02 | C49: 0.06 | D49: 0.15 | E49: 0.3 | F49: 0.4 | G49: 0.5 | H49: EU – ReFuelEU | I49: Reg (EU) 2023/2405
A50: MUC | B50: 0.02 | C50: 0.06 | D50: 0.15 | E50: 0.3 | F50: 0.4 | G50: 0.5 | H50: EU – ReFuelEU | I50: Reg (EU) 2023/2405
A51: ZRH | B51: 0.02 | C51: 0.06 | D51: 0.15 | E51: 0.3 | F51: 0.4 | G51: 0.5 | H51: EU – ReFuelEU | I51: Reg (EU) 2023/2405
A52: VIE | B52: 0.02 | C52: 0.06 | D52: 0.15 | E52: 0.3 | F52: 0.4 | G52: 0.5 | H52: EU – ReFuelEU | I52: Reg (EU) 2023/2405
A53: CPH | B53: 0.02 | C53: 0.06 | D53: 0.15 | E53: 0.3 | F53: 0.4 | G53: 0.5 | H53: EU – ReFuelEU | I53: Reg (EU) 2023/2405
A54: HEL | B54: 0.02 | C54: 0.06 | D54: 0.15 | E54: 0.3 | F54: 0.4 | G54: 0.5 | H54: EU – ReFuelEU | I54: Reg (EU) 2023/2405
A55: LIS | B55: 0.02 | C55: 0.06 | D55: 0.15 | E55: 0.3 | F55: 0.4 | G55: 0.5 | H55: EU – ReFuelEU | I55: Reg (EU) 2023/2405
... A103: AKL | B103: 0 | C103: 0.02 | D103: 0.05 | E103: 0.15 | F103: 0.2 | G103: 0.3 | H103: NZ – Developing | I103: NZ MoT framework 2024
A105: F AIRCRAFT PERFORMANCE — Fuel Efficiency & Max Range (ROUTES col R & AIRCRAFT reference)
A106: Aircraft Type | B106: Fuel Efficiency (t/km) | C106: Max Range (km) | D106: Category | E106: Source
A107: A320neo | B107: 0.0039 | C107: 6300 | D107: Narrowbody | E107: Airbus AC-A-320neo; Piano-X
A108: A321neo | B108: 0.0042 | C108: 7400 | D108: Narrowbody | E108: Airbus AC-A-321neo; Piano-X
A109: B737-800 | B109: 0.0041 | C109: 5600 | D109: Narrowbody | E109: Boeing D6-58325-3; Piano-X
A110: B737MAX8 | B110: 0.0039 | C110: 6570 | D110: Narrowbody | E110: Boeing D6-58325-9; Piano-X
A111: A330-300 | B111: 0.0085 | C111: 11750 | D111: Widebody | E111: Airbus AC-A-330; Piano-X
A112: B787-9 | B112: 0.0079 | C112: 14140 | D112: Widebody | E112: Boeing D6-58325-2; Piano-X
A113: A350-900 | B113: 0.0079 | C113: 15000 | D113: Widebody | E113: Airbus AC-A-350-900; Piano-X
A114: B777-300ER | B114: 0.0089 | C114: 13650 | D114: Widebody | E114: Boeing D6-58325-6; Piano-X
A115: A380-800 | B115: 0.0105 | C115: 15200 | D115: Large WB | E115: Airbus AC-A-380; Piano-X
A116: B747-8 | B116: 0.01 | C116: 14800 | D116: Large WB | E116: Boeing D6-58325-4; Piano-X
A117: B777F | B117: 0.0082 | C117: 9200 | D117: Freighter | E117: Boeing D6-58325-6F; IATA WACF
A118: B747-8F | B118: 0.0096 | C118: 8130 | D118: Freighter | E118: Boeing D6-58325-4F; IATA WACF
... A120: B757F | B120: 0.0046 | C120: 5850 | D120: Freighter | E120: Boeing D6-58325-5; IATA WACF
A122: G GLOBAL MARKET REFERENCES — Jet Fuel Demand & SAF Production (Mt/yr)
A123: Year | B123: Global Jet Fuel Demand (Mt/yr) | C123: Global SAF Supply (Mt/yr) | D123: SAF Supply Source | E123: Note
A124: 2025 | B124: 320 | C124: 1.9 | D124: IEA/IATA Q3-2024 | E124: Post-pandemic recovery, ~95% of 2019 levels | G124: =C124/B124 -> 0.0059375
A125: 2026 | B125: 326 | C125: 2.8 | D125: IEA forecast | G125: =C125/B125 -> 0.0085889571
A126: 2027 | B126: 332 | C126: 4 | D126: IEA forecast | E126: CORSIA Phase 2 begins | G126: =C126/B126 -> 0.012048193
A127: 2028 | B127: 338 | C127: 5.5 | D127: IEA forecast | G127: =C127/B127 -> 0.016272189
A128: 2029 | B128: 344 | C128: 7.5 | D128: IEA forecast | G128: =C128/B128 -> 0.021802326
A129: 2030 | B129: 350 | C129: 10 | D129: IEA/IATA/ICAO target | E129: Key milestone year for all major mandates | G129: =C129/B129 -> 0.028571429
A130: 2035 | B130: 394 | C130: 42 | D130: IEA Net Zero 2035 | E130: ReFuelEU 20% mandate kicks in | G130: =C130/B130 -> 0.10659898
A131: 2040 | B131: 438 | C131: 100 | D131: IEA/ICAO projection | G131: =C131/B131 -> 0.2283105
A132: 2045 | B132: 480 | C132: 175 | D132: ICAO LTAG | G132: =C132/B132 -> 0.36458333
A133: 2050 | B133: 525 | C133: 300 | D133: ICAO LTAG net-zero | E133: Net-zero target year | G133: =C133/B133 -> 0.57142857
A135: H SAF SCENARIO PARAMETERS — Blending % by Region & Scenario
A136: Region | B136: Scenario | C136: 2025 | D136: 2026 | E136: 2027 | F136: 2028 | G136: 2029 | H136: 2030 | I136: 2035 | J136: 2040 | K136: 2050
A137: EU | B137: Baseline | C137: 0.02 | D137: 0.02 | E137: 0.022 | F137: 0.025 | G137: 0.027 | H137: 0.03 | I137: 0.055 | J137: 0.085 | K137: 0.15
A138: EU | B138: Policy | C138: 0.02 | D138: 0.02 | E138: 0.03 | F138: 0.04 | G138: 0.05 | H138: 0.06 | I138: 0.2 | J138: 0.34 | K138: 0.7
A139: EU | B139: Accelerated | C139: 0.02 | D139: 0.03 | E139: 0.045 | F139: 0.06 | G139: 0.07 | H139: 0.08 | I139: 0.25 | J139: 0.5 | K139: 0.85
A140: US | B140: Baseline | C140: 0.005 | D140: 0.007 | E140: 0.009 | F140: 0.011 | G140: 0.013 | H140: 0.015 | I140: 0.03 | J140: 0.06 | K140: 0.12
A141: US | B141: Policy | C141: 0.005 | D141: 0.01 | E141: 0.015 | F141: 0.02 | G141: 0.025 | H141: 0.03 | I141: 0.1 | J141: 0.18 | K141: 0.3
A142: US | B142: Accelerated | C142: 0.01 | D142: 0.02 | E142: 0.03 | F142: 0.04 | G142: 0.045 | H142: 0.05 | I142: 0.15 | J142: 0.3 | K142: 0.45
A143: APAC | B143: Baseline | C143: 0.001 | D143: 0.003 | E143: 0.005 | F143: 0.006 | G143: 0.007 | H143: 0.01 | I143: 0.025 | J143: 0.045 | K143: 0.09
A144: APAC | B144: Policy | C144: 0.003 | D144: 0.01 | E144: 0.018 | F144: 0.025 | G144: 0.03 | H144: 0.035 | I144: 0.1 | J144: 0.16 | K144: 0.25
A145: APAC | B145: Accelerated | C145: 0.005 | D145: 0.015 | E145: 0.03 | F145: 0.045 | G145: 0.052 | H145: 0.06 | I145: 0.15 | J145: 0.28 | K145: 0.4
A146: MENA | B146: Baseline | C146: 0 | D146: 0.001 | E146: 0.002 | F146: 0.002 | G146: 0.003 | H146: 0.003 | I146: 0.01 | J146: 0.02 | K146: 0.04
A147: MENA | B147: Policy | C147: 0 | D147: 0.002 | E147: 0.005 | F147: 0.007 | G147: 0.008 | H147: 0.01 | I147: 0.03 | J147: 0.06 | K147: 0.1
A148: MENA | B148: Accelerated | C148: 0.005 | D148: 0.008 | E148: 0.012 | F148: 0.015 | G148: 0.018 | H148: 0.02 | I148: 0.06 | J148: 0.12 | K148: 0.18
... A154: ROW | B154: Accelerated | C154: 0 | D154: 0.003 | E154: 0.007 | F154: 0.008 | G154: 0.009 | H154: 0.01 | I154: 0.04 | J154: 0.08 | K154: 0.12
A157: VERIFIED ICAO CCR BASELINES (Feb 2026)
A158: CORSIA Phase 1 baseline (2024-2026) | B158: 305.52207 | C158: Mt CO2 (305.522 Mt) — ICAO CCR Feb 2026
A159: 2024 actual Phase 1 eligible emissions | B159: 361.15964 | C159: Mt CO2 — ICAO CCR Feb 2026
A160: 2024 Sector Growth Factor | B160: 0.15405257 | C160: ICAO CCR Feb 2026
A161: 2024 offsetting obligation | B161: 55.6 | C161: Mt CO2 — EASA/ICAO 2026
A162: Jet fuel equivalent (Phase 1, 2024 actual) | B162: 114.3 | C162: Mt (361.2 Mt CO2 / 3.16 EF)

Sheet AIRCRAFT
A1: AIRCRAFT TYPE DATABASE — Fuel Efficiency Reference Table
A3: Aircraft Type | B3: Fuel Efficiency (t/km total) | C3: Category | D3: Typical Capacity (pax / t cargo) | E3: Typical Range (km) | F3: Notes / Applications
A4: A320neo | B4: 0.0039 | C4: Narrowbody | D4: 150 | E4: 3500 | F4: Narrow body short-medium haul
A5: A321neo | B5: 0.0042 | C5: Widebody | D5: 300 | E5: 12000 | F5: Narrow body medium haul
A6: B737-800 | B6: 0.0041 | C6: Narrowbody | D6: 150 | E6: 3500 | F6: Narrow body short-medium haul
A7: B737MAX8 | B7: 0.0039 | C7: Narrowbody | D7: 150 | E7: 3500 | F7: Narrow body short-medium haul
A8: A330-300 | B8: 0.0085 | C8: Widebody | D8: 300 | E8: 12000 | F8: Wide body medium-long haul
A9: B787-9 | B9: 0.0079 | C9: Widebody | D9: 300 | E9: 12000 | F9: Wide body long haul
A10: A350-900 | B10: 0.0079 | C10: Widebody | D10: 300 | E10: 12000 | F10: Wide body long haul
A11: B777-300ER | B11: 0.0089 | C11: Widebody | D11: 300 | E11: 12000 | F11: Wide body long haul
A12: A380-800 | B12: 0.0105 | C12: Widebody | D12: 555 | E12: 12000 | F12: Very large wide body
A13: B747-8 | B13: 0.01 | C13: Widebody | D13: 300 | E13: 12000 | F13: Very large wide body
A14: B777F | B14: 0.0082 | C14: Large widebody cargo freighter | D14: Cargo | E14: 102000 | F14: 9200
A15: B747-8F | B15: 0.0096 | C15: Very large widebody cargo freighter | D15: Cargo | E15: 137800 | F15: 8130
A16: B757F | B16: 0.0046 | C16: Medium narrowbody cargo freighter | D16: Cargo | E16: 22680 | F16: 5850
A17: B767F | B17: 0.0068 | C17: Medium-large widebody cargo freighter | D17: Cargo | E17: 52163 | F17: 6025
A20: ▌ FUEL EFFICIENCY NOTES
A21: • Fuel efficiency expressed as total fuel burn per km (all passengers + freight + aircraft weight).
A22: • Source: ICAO Aircraft Engine Emissions Databank, manufacturer fuel burn data, IATA Economics.
A23: • Cargo freighters (B777F, B747-8F) include fuel per km for typical payload; actual efficiency varies with load factor.
A24: • Efficiency improvements of 1.2-1.5%/yr expected through fleet renewal — see ASSUMPTIONS sheet.
A25: • CO₂ factor: multiply fuel (tonnes) × 3.16 to get CO₂ equivalent tonnes.

Sheet OPERATORS
A1: OPERATORS DATABASE — Passenger Airlines & Cargo Operators Subject to CORSIA / SAF Mandates
A3: ID | B3: Operator Name | C3: Home Country | D3: Region | E3: Hub IATA | F3: Hub Country | G3: Hub Region | H3: Operator Type | I3: Fleet Size | J3: Ownership Model | K3: CORSIA Liability | L3: CORSIA Phase 1 | M3: CORSIA Phase 2
A4: LH | B4: Lufthansa | C4: Germany | D4: EU | E4: FRA | F4: Germany | G4: EU | H4: Passenger Airline | I4: N/A | J4: Direct Owned | K4: CORSIA Direct Liable | L4: Yes | M4: Yes
A5: AF | B5: Air France | C5: France | D5: EU | E5: CDG | F5: France | G5: EU | H5: Passenger Airline | I5: N/A | J5: Direct Owned | K5: CORSIA Direct Liable | L5: Yes | M5: Yes
A6: BA | B6: British Airways | C6: UK | D6: EU | E6: LHR | F6: UK | G6: EU | H6: Passenger Airline | I6: N/A | J6: Direct Owned | K6: CORSIA Direct Liable | L6: Yes | M6: Yes
A7: KL | B7: KLM | C7: Netherlands | D7: EU | E7: AMS | F7: Netherlands | G7: EU | H7: Passenger Airline | I7: N/A | J7: Direct Owned | K7: CORSIA Direct Liable | L7: Yes | M7: Yes
A8: IB | B8: Iberia | C8: Spain | D8: EU | E8: MAD | F8: Spain | G8: EU | H8: Passenger Airline | I8: N/A | J8: Direct Owned | K8: CORSIA Direct Liable | L8: Yes | M8: Yes
A9: UA | B9: United Airlines | C9: USA | D9: US | E9: EWR | F9: USA | G9: US | H9: Passenger Airline | I9: N/A | J9: Direct Owned | K9: CORSIA Direct Liable | L9: Yes | M9: Yes
A10: AA | B10: American Airlines | C10: USA | D10: US | E10: DFW | F10: USA | G10: US | H10: Passenger Airline | I10: N/A | J10: Direct Owned | K10: CORSIA Direct Liable | L10: Yes | M10: Yes
A11: DL | B11: Delta Air Lines | C11: USA | D11: US | E11: ATL | F11: USA | G11: US | H11: Passenger Airline | I11: N/A | J11: Direct Owned | K11: CORSIA Direct Liable | L11: Yes | M11: Yes
A12: WN | B12: Southwest Airlines | C12: USA | D12: US | E12: DAL | F12: USA | G12: US | H12: Passenger Airline | I12: N/A | J12: Direct Owned | K12: CORSIA Direct Liable | L12: Yes | M12: Yes
A13: SQ | B13: Singapore Airlines | C13: Singapore | D13: APAC | E13: SIN | F13: Singapore | G13: APAC | H13: Passenger Airline | I13: N/A | J13: Direct Owned | K13: CORSIA Direct Liable | L13: Yes | M13: Yes
A14: NH | B14: ANA | C14: Japan | D14: APAC | E14: NRT | F14: Japan | G14: APAC | H14: Passenger Airline | I14: N/A | J14: Direct Owned | K14: CORSIA Direct Liable | L14: Yes | M14: Yes
... A23: TK | B23: Turkish Airlines | C23: Turkey | D23: ROW | E23: IST | F23: Turkey | G23: ROW | H23: Passenger Airline | I23: N/A | J23: Direct Owned | K23: CORSIA Direct Liable | L23: Yes | M23: Yes
A24: FX | B24: FedEx Express | C24: USA | D24: US | E24: MEM | F24: USA | G24: US | H24: Cargo Integrator | I24: 700 | J24: Direct Owned | K24: CORSIA Direct Liable | L24: Yes | M24: Yes
A25: 5X | B25: UPS Airlines | C25: USA | D25: US | E25: SDF | F25: USA | G25: US | H25: Cargo Integrator | I25: 291 | J25: Direct Owned | K25: CORSIA Direct Liable | L25: Yes | M25: Yes
A26: D0 | B26: DHL Aviation | C26: Germany | D26: EU | E26: CGN | F26: Germany | G26: EU | H26: Hybrid/ACMI | I26: 310 | J26: ACMI Partner | K26: CORSIA via AOC Holder | L26: Yes | M26: Yes
A27: K9 | B27: Amazon Air | C27: USA | D27: US | E27: CVG | F27: USA | G27: US | H27: E-Commerce/ACMI | I27: 90 | J27: Wet Lease | K27: CORSIA via Operator AOC | L27: Yes | M27: Yes
A28: 5Y | B28: Atlas Air | C28: USA | D28: US | E28: JFK | F28: USA | G28: US | H28: ACMI Provider | I28: 93 | J28: ACMI Lessor | K28: CORSIA Direct (Operator) | L28: Yes | M28: Yes
A29: K4 | B29: Kalitta Air | C29: USA | D29: US | E29: YIP | F29: USA | G29: US | H29: ACMI Charter | I29: 40 | J29: ACMI Lessor | K29: CORSIA Direct (Operator) | L29: Yes | M29: Yes
A30: ABR | B30: ASL Aviation Holdings | C30: Ireland | D30: EU | E30: DUB | F30: Ireland | G30: EU | H30: ACMI Provider | I30: 150 | J30: ACMI Lessor | K30: CORSIA Direct (Operator) | L30: Yes | M30: Yes
A31: CV | B31: Cargolux | C31: Luxembourg | D31: EU | E31: LUX | F31: Luxembourg | G31: EU | H31: Freighter Airline | I31: 30 | J31: Direct Owned | K31: CORSIA Direct Liable | L31: Yes | M31: Yes
A32: LHC | B32: Lufthansa Cargo | C32: Germany | D32: EU | E32: FRA | F32: Germany | G32: EU | H32: Freighter Airline | I32: 20 | J32: Direct Owned | K32: CORSIA Direct Liable | L32: Yes | M32: Yes
A33: QRC | B33: Qatar Airways Cargo | C33: Qatar | D33: MENA | E33: DOH | F33: Qatar | G33: MENA | H33: Freighter Airline | I33: 30 | J33: Direct Owned | K33: CORSIA Direct Liable | L33: Yes | M33: Yes
A34: EKC | B34: Emirates SkyCargo | C34: UAE | D34: MENA | E34: DXB | F34: UAE | G34: MENA | H34: Freighter Airline | I34: 11 | J34: Direct Owned | K34: CORSIA Direct Liable | L34: Yes | M34: Yes
A35: KE | B35: Korean Air | C35: South Korea | D35: APAC | E35: ICN | F35: South Korea | G35: APAC | H35: Freighter Airline | I35: 20 | J35: Direct Owned | K35: CORSIA Direct Liable | L35: Yes | M35: Yes
... A166: FV | B166: Rossiya Airlines | C166: Russia | D166: ROW | E166: LED | F166: Russia | G166: ROW | H166: Passenger Airline | I166: 65 | J166: Direct Owned | K166: CORSIA Direct Liable | L166: No | M166: Yes
A169: ▌ CORSIA APPLICABILITY NOTES & DEFINITIONS
A170: CORSIA Direct Liable | E170: Operator holds AOC; ICAO designator filed in Box 7 of flight plan. Full MRV + offsetting obligation applies.
A171: CORSIA via AOC Holder | E171: ACMI model: legal liability sits with the contracted operator (AOC holder). Economic cost passed through via contractual clauses.
A172: CORSIA via Operator AOC | E172: Wet-lease arrangement: logistics brand (e.g. Amazon) is NOT liable; ACMI operator (e.g. Atlas Air) holds CORSIA liability.
A173: Exempt - LDC | E173: Least Developed Country exemption per ICAO Assembly Resolution A41-22 (Annex to Resolution). MRV still required.
A174: Partial | E174: Route/state-level applicability varies. Phase 1: routes between non-participating state pairs are exempt.

Sheet SCENARIOS
A1: SCENARIO BUILDING SHEET
A3: Case Description | B3: C1 - A&M base case | C3: C2 - A&M policy-driven | D3: C3 - A&M climate push | E3: C4 - IATA reference | G3: to have option for the adjustment on the fuel efficiency
A4: Growth rate cases consideration | B4: EU: 2.5% US: 2.0% APAC: 4.0% MENA: 4.5% LATAM: 3.5% ROW: 3.0% | C4: EU: 2.5% US: 2.0% APAC: 4.0% MENA: 4.5% LATAM: 3.5% ROW: 3.0% | D4: EU: 2.5% US: 2.0% APAC: 4.0% MENA: 4.5% LATAM: 3.5% ROW: 3.0% | E4: EU: 3.0% US: 2.5% APAC: 5.0% MENA: 4.5% LATAM: 4.0% ROW: 3.5% | J4: Fuel efficiency is expressed in tonnes of fuel per kilometre for the whole aircraft (not per seat). Each route is assigned an aircraft type from this table, and the base efficiency is multiplied by an annual improvement factor: Eff(year) = Eff₂₀₂₅ × (1 − 0.015)^(year − 2025) The 1.5% per annum improvement rate reflects average fleet-level efficiency gains from new-generation aircraft (A320neo, A350, B787) entering service and retiring older frames. This rate can be adjusted here to test more aggressive or conservative technology scenarios. Heavier widebody aircraft (A380, B777) have lower efficiency per km in absolute terms but typically serve longer routes, so their contribution to total fuel burn depends heavily on route distance.
A5: Blending target % | B5: The most conservative scenario. Based on demand driven by states/regions with existing SAF blending mandate and targets | C5: The central scenario. Based on demand driven by states/regions with existing SAF blending mandate and targets, and international airlines reporting to CORSIA | D5: The 'high' scenario considering higher % of SAF blending than the A&M Policy-Driven Scenario for airlines with no currently binding targets | E5: IATA case is considered the most ambitious scenario pushing for high level of decarbonisation for the international aviation sector, targeting ~57% SAF consumption from total jet fuel by 2050. A&M has assumed ~50% SAF out of total international aviation jet fuel by 2050
A6: Fuel efficiency cases consideration | B6: No efficiency improvement | C6: 1.5% efficiency improvement every year | D6: 2.0% efficiency improvement every year | E6: No efficiency improvement
A7: Willingness to pay | B7: EU: 2600-3200 through 2050 US: 1500-2200 through 2050 APAC: 1300-1800 through 2050 MENA: 1000-1300 through 2050 | C7: EU: 2800-3600 through 2050 US: 1700-2400 through 2050 APAC: 1500-2000 through 2050 MENA: 1100-1400 through 2050 | D7: EU: 3000-4000 through 2050 US: 1700-2500 through 2050 APAC: 1600-2200 through 2050 MENA: 1200-1600 through 2050 | E7: EU: 3000-4000 through 2050 US: 1700-2500 through 2050 APAC: 1600-2200 through 2050 MENA: 1200-1600 through 2050
A8: Carbon pricing | B8: 2025: 30 USD 2050: 190 USD | C8: 2025: 30 USD 2050: 250 USD | D8: 2025: 30 USD 2050: 300 USD | E8: 2025: 30 USD 2050: 300 USD
A10: TRAFFIC GROWTH RATES — Net (pa, after efficiency) by Origin Region
A11: Scenarios | B11: C1 - A&M base case | C11: C2 - A&M policy-driven | D11: C3 - A&M climate push | E11: C4 - IATA reference | H11: reference
A12: Origin Region | B12: Net Growth Rate (pa) | C12: Net Growth Rate (pa) | D12: Net Growth Rate (pa) | E12: Net Growth Rate (pa) | H12: ~420 Mt in 2050
A13: EU | B13: 0.025 | C13: 0.025 | D13: 0.025 | E13: 0.03 | H13: 0.03
A14: US | B14: 0.02 | C14: 0.02 | D14: 0.02 | E14: 0.025 | H14: 0.025
A15: APAC | B15: 0.04 | C15: 0.04 | D15: 0.04 | E15: 0.05 | H15: 0.05
A16: MENA | B16: 0.045 | C16: 0.045 | D16: 0.045 | E16: 0.045 | H16: 0.045
A17: LATAM | B17: 0.035 | C17: 0.035 | D17: 0.035 | E17: 0.04 | H17: 0.04
A18: ROW | B18: 0.03 | C18: 0.03 | D18: 0.03 | E18: 0.035 | H18: 0.035
A20: SAF MANDATE % — Airport-Level Lookup (ROUTES cols Y & AA reference this table)
A21: VLOOKUP key: Origin Airport Code (ROUTES col E). Returns SAF blend % for 2025, 2030, 2035, 2040, 2045, 2050 | J21: Airports not listed → formula returns the values below
A22: Origin Airport (IATA) | B22: SAF% 2025 | C22: SAF% 2030 | D22: SAF% 2035 | E22: SAF% 2040 | F22: SAF% 2045 | G22: SAF% 2050 | J22: SAF% 2030 | K22: SAF% 2035 | L22: SAF% 2040 | M22: SAF% 2045 | N22: SAF% 2050
A23: FRA | B23: 0.02 | C23: 0.06 | D23: 0.15 | E23: 0.3 | F23: 0.4 | G23: 0.5 | I23: C1 - A&M base case | J23: 0 | K23: 0 | L23: 0 | M23: 0 | N23: 0
A24: CDG | B24: 0.02 | C24: 0.06 | D24: 0.15 | E24: 0.3 | F24: 0.4 | G24: 0.5 | I24: C2 - A&M policy-driven | J24: 0.01 | K24: 0.05 | L24: 0.1 | M24: 0.2 | N24: 0.25
A25: AMS | B25: 0.02 | C25: 0.06 | D25: 0.15 | E25: 0.3 | F25: 0.4 | G25: 0.5 | I25: C3 - A&M climate push | J25: 0.015 | K25: 0.075 | L25: 0.15 | M25: 0.2 | N25: 0.3
A26: MAD | B26: 0.02 | C26: 0.06 | D26: 0.15 | E26: 0.3 | F26: 0.4 | G26: 0.5 | I26: C4 - IATA reference | J26: 0.025 | K26: 0.1 | L26: 0.2 | M26: 0.3 | N26: 0.5
A27: BCN | B27: 0.02 | C27: 0.06 | D27: 0.15 | E27: 0.3 | F27: 0.4 | G27: 0.5
A28: FCO | B28: 0.02 | C28: 0.06 | D28: 0.15 | E28: 0.3 | F28: 0.4 | G28: 0.5
A29: MUC | B29: 0.02 | C29: 0.06 | D29: 0.15 | E29: 0.3 | F29: 0.4 | G29: 0.5
A30: ZRH | B30: 0.02 | C30: 0.06 | D30: 0.15 | E30: 0.3 | F30: 0.4 | G30: 0.5
A31: VIE | B31: 0.02 | C31: 0.06 | D31: 0.15 | E31: 0.3 | F31: 0.4 | G31: 0.5
A32: CPH | B32: 0.02 | C32: 0.06 | D32: 0.15 | E32: 0.3 | F32: 0.4 | G32: 0.5
A33: HEL | B33: 0.02 | C33: 0.06 | D33: 0.15 | E33: 0.3 | F33: 0.4 | G33: 0.5
A34: LIS | B34: 0.02 | C34: 0.06 | D34: 0.15 | E34: 0.3 | F34: 0.4 | G34: 0.5
A35: OSL | B35: 0.02 | C35: 0.06 | D35: 0.15 | E35: 0.3 | F35: 0.4 | G35: 0.5
A36: DUB | B36: 0.02 | C36: 0.06 | D36: 0.15 | E36: 0.3 | F36: 0.4 | G36: 0.5
A37: BUD | B37: 0.02 | C37: 0.06 | D37: 0.15 | E37: 0.3 | F37: 0.4 | G37: 0.5
A38: ORY | B38: 0.02 | C38: 0.06 | D38: 0.15 | E38: 0.3 | F38: 0.4 | G38: 0.5
... A82: AKL | B82: 0 | C82: 0.02 | D82: 0.05 | E82: 0.15 | F82: 0.2 | G82: 0.3
A84: Fuel efficiency improvement (Annual % improvement)
A85: Scenarios | B85: C1 - A&M base case | C85: C2 - A&M policy-driven | D85: C3 - A&M climate push | E85: C4 - IATA reference
B86: % Improvement (pa) | C86: % Improvement (pa) | D86: % Improvement (pa) | E86: % Improvement (pa)
A87: Fleet level improvement | B87: 0 | C87: 0.0025 | D87: 0.005 | E87: 0.025
A90: GLOBAL MARKET REFERENCES — Jet Fuel Demand & SAF Production (Mt/yr)
A91: Year | B91: Global Jet Fuel Demand (Mt/yr) | C91: Global SAF Supply (Mt/yr) | D91: SAF Supply Source | E91: Note
A92: 2025 | B92: 320 | C92: 1.9 | D92: IEA/IATA Q3-2024 | E92: Post-pandemic recovery, ~95% of 2019 levels
A93: 2026 | B93: 326 | C93: 2.8 | D93: IEA forecast
A94: 2027 | B94: 332 | C94: 4 | D94: IEA forecast | E94: CORSIA Phase 2 begins
A95: 2028 | B95: 338 | C95: 5.5 | D95: IEA forecast
A96: 2029 | B96: 344 | C96: 7.5 | D96: IEA forecast
A97: 2030 | B97: 350 | C97: 10 | D97: IEA/IATA/ICAO target | E97: Key milestone year for all major mandates
A98: 2035 | B98: 394 | C98: 42 | D98: IEA Net Zero 2035 | E98: ReFuelEU 20% mandate kicks in
A99: 2040 | B99: 438 | C99: 100 | D99: IEA/ICAO projection
A100: 2045 | B100: 480 | C100: 175 | D100: ICAO LTAG
A101: 2050 | B101: 525 | C101: 300 | D101: ICAO LTAG net-zero | E101: Net-zero target year
A104: VERIFIED ICAO CCR BASELINES (Feb 2026)
A105: CORSIA Phase 1 baseline (2024-2026) | B105: 305.52207 | C105: Mt CO2 (305.522 Mt) — ICAO CCR Feb 2026
A106: 2024 actual Phase 1 eligible emissions | B106: 361.15964 | C106: Mt CO2 — ICAO CCR Feb 2026
A107: 2024 Sector Growth Factor | B107: 0.15405257 | C107: ICAO CCR Feb 2026
A108: 2024 offsetting obligation | B108: 55.6 | C108: Mt CO2 — EASA/ICAO 2026
A109: Jet fuel equivalent (Phase 1, 2024 actual) | B109: 114.3 | C109: Mt (361.2 Mt CO2 / 3.16 EF)

Sheet ▌ CALC ▌
A1: CALC

Sheet Test
A1: FLIGHT ROUTES DATABASE — Comprehensive Route-Level Fuel & CORSIA/SAF Analysis | 242 Routes (64 Passenger original + 53 Cargo + 125 Expanded Passenger)
AB2: 5 | AD2: 10 | AF2: 15 | AH2: 20 | AJ2: 25 | AT2: SAF in tonnes per annum - Region | BC2: SAF in tonnes per annum - Airport | BM2: SAF in tonnes per annum - Country
A3: Route ID | B3: Airline ID | C3: Operator Name | D3: Segment (Pax/Cargo) | E3: Origin Airport | F3: Origin Country | G3: Origin Region | H3: Dest Airport | I3: Dest Country | J3: Dest Region | K3: Flight Category | L3: Aircraft Type | M3: Annual Flights 2025 | N3: Trips per Day | O3: Distance (km/trip) | P3: km Flown per Year | Q3: Growth Rate | R3: Fuel Eff. (t/km) | S3: Fuel per Trip (t) | T3: Fuel per Year 2025 (t) | U3: Fuel per Year 2025 (L) | V3: CO₂ per Year 2025 (t) | W3: CORSIA Phase 1 | X3: CORSIA Phase 2 | Y3: SAF% 2025 | Z3: SAF Demand 2025 (t) | AA3: SAF% 2030 | AB3: SAF Demand 2030 (t) | AC3: SAF% 2035 | AD3: SAF Demand 2035 (t) | AE3: SAF% 2040 | AF3: SAF Demand 2040 (t) | AG3: SAF% 2045 | AH3: SAF Demand 2045 (t) | AI3: SAF% 2050 | AJ3: SAF Demand 2050 (t) | AL3: Reciprocal in DB? | AM3: 2050 Global Jet Fuel demand | AU3: 2025 | AV3: 2030 | AW3: 2035 | AX3: 2040 | AY3: 2045 | AZ3: 2050 | BD3: 2025 | BE3: 2030 | BF3: 2035 | BG3: 2040 | BH3: 2045 | BI3: 2050 | BN3: 2025 | BO3: 2030 | BP3: 2035 | BQ3: 2040 | BR3: 2045 | BS3: 2050
A4: R001 | B4: LH | C4: Lufthansa | D4: Passenger | E4: FRA | F4: Germany | G4: EU | H4: JFK | I4: United States | J4: US | K4: international | L4: A350-900 | M4: 730 | N4: =M4/365 -> 2 | O4: 6200 | P4: =M4*O4 -> 4526000 | Q4: =IFERROR(VLOOKUP(G4,SCENARIOS!$A$13:$E$18,2,0),0.025) -> 0.025 | R4: =IFERROR(VLOOKUP(L4,INPUTS!$A$107:$B$120,2,0),0.0082) -> 0.0079 | S4: =O4*R4 -> 48.98 | T4: =M4*S4 -> 35755.4 | U4: =T4/INPUTS!$B$7*1000 -> 44694250 | V4: =T4*INPUTS!$B$6 -> 112987.06 | W4: Yes | X4: Yes | Y4: =IFERROR(VLOOKUP(E4,INPUTS!$A$44:$B$103,2,0),0) -> 0.02 | Z4: =T4*Y4 -> 715.108 | AA4: =IFERROR(VLOOKUP(E4,INPUTS!$A$44:$C$103,3,0),SCENARIOS!$J$23) -> 0.06 | AB4: =$T4*AA4*(1+$Q4)^AB$2 -> 2427.2372 | AC4: =IFERROR(VLOOKUP($E4,INPUTS!$A$44:$G$103,4,0),SCENARIOS!$K$23) -> 0.15 | AD4: =$T4*AC4*(1+$Q4)^AD$2 -> 6865.4902 | AE4: =IFERROR(VLOOKUP($E4,INPUTS!$A$44:$G$103,5,0),SCENARIOS!$L$23) -> 0.3 | AF4: =$T4*AE4*(1+$Q4)^AF$2 -> 15535.344 | AG4: =IFERROR(VLOOKUP($E4,INPUTS!$A$44:$G$103,6,0),SCENARIOS!$M$23) -> 0.4 | AH4: =$T4*AG4*(1+$Q4)^AH$2 -> 23435.755 | AI4: =IFERROR(VLOOKUP($E4,INPUTS!$A$44:$G$103,7,0),SCENARIOS!$N$23) -> 0.5 | AJ4: =$T4*AI4*(1+$Q4)^AJ$2 -> 33144.256 | AL4: =IF(H4="MULTI","MULTI",IF(COUNTIFS($E$4:$E$1277,H4,$H$4:$H$1277,E4)>0,"Y","N")) -> N | AM4: =T4*((1+Q4)^25) -> 66288.513 | AT4: EU | AU4: =SUMIF($G$4:$G$1277,$AT4,$Z$4:$Z$1277) -> 761802.07 | AV4: =SUMIF($G$4:$G$1277,$AT4,$AB$4:$AB$1277) -> 3015007 | AW4: =SUMIF($G$4:$G$1277,$AT4,$AD$4:$AD$1277) -> 7313783 | AX4: =SUMIF($G$4:$G$1277,$AT4,$AF$4:$AF$1277) -> 16549748 | AY4: =SUMIF($G$4:$G$1277,$AT4,$AH$4:$AH$1277) -> 24966028 | AZ4: =SUMIF($G$4:$G$1277,$AT4,$AJ$4:$AJ$1277) -> 35308461 | BC4: {=_xlfn._xlws.SORT(_xlfn.UNIQUE(E$4:E$1277))} -> ABU | BD4: =SUMIF($E$4:$E$1277,$BC4,$Z$4:$Z$1277) -> 0 | BE4: =SUMIF($E$4:$E$1277,$BC4,$AB$4:$AB$1277) -> 0 | BF4: =SUMIF($E$4:$E$1277,$BC4,$AD$4:$AD$1277) -> 0 | BG4: =SUMIF($E$4:$E$1277,$BC4,$AF$4:$AF$1277) -> 0 | BH4: =SUMIF($E$4:$E$1277,$BC4,$AH$4:$AH$1277) -> 0 | BI4: =SUMIF($E$4:$E$1277,$BC4,$AJ$4:$AJ$1277) -> 0 | BM4: {=_xlfn._xlws.SORT(_xlfn.UNIQUE(F$4:F$1277))} -> Argentina | BN4: =SUMIF($F$4:$F$1277,$BM4,$Z$4:$Z$1277) -> 0 | BO4: =SUMIF($F$4:$F$1277,$BM4,$AB$4:$AB$1277) -> 0 | BP4: =SUMIF($F$4:$F$1277,$BM4,$AD$4:$AD$1277) -> 0 | BQ4: =SUMIF($F$4:$F$1277,$BM4,$AF$4:$AF$1277) -> 0 | BR4: =SUMIF($F$4:$F$1277,$BM4,$AH$4:$AH$1277) -> 0 | BS4: =SUMIF($F$4:$F$1277,$BM4,$AJ$4:$AJ$1277) -> 0
A5: R002 | B5: LH | C5: Lufthansa | D5: Passenger | E5: FRA | F5: Germany | G5: EU | H5: PEK | I5: China | J5: APAC | K5: international | L5: A350-900 | M5: 365 | N5: =M5/365 -> 1 | O5: 9200 | P5: =M5*O5 -> 3358000 | Q5: =IFERROR(VLOOKUP(G5,SCENARIOS!$A$13:$E$18,2,0),0.025) -> 0.025 | R5: =IFERROR(VLOOKUP(L5,INPUTS!$A$107:$B$120,2,0),0.0082) -> 0.0079 | S5: =O5*R5 -> 72.68 | T5: =M5*S5 -> 26528.2 | U5: =T5/INPUTS!$B$7*1000 -> 33160250 | V5: =T5*INPUTS!$B$6 -> 83829.112 | W5: No | X5: Yes | Y5: =IFERROR(VLOOKUP(E5,INPUTS!$A$44:$B$103,2,0),0) -> 0.02 | Z5: =T5*Y5 -> 530.564 | AA5: =IFERROR(VLOOKUP(E5,INPUTS!$A$44:$C$103,3,0),SCENARIOS!$J$23) -> 0.06 | AB5: =$T5*AA5*(1+$Q5)^AB$2 -> 1800.8534 | AC5: =IFERROR(VLOOKUP($E5,INPUTS!$A$44:$G$103,4,0),SCENARIOS!$K$23) -> 0.15 | AD5: =$T5*AC5*(1+$Q5)^AD$2 -> 5093.7508 | AE5: =IFERROR(VLOOKUP($E5,INPUTS!$A$44:$G$103,5,0),SCENARIOS!$L$23) -> 0.3 | AF5: =$T5*AE5*(1+$Q5)^AF$2 -> 11526.223 | AG5: =IFERROR(VLOOKUP($E5,INPUTS!$A$44:$G$103,6,0),SCENARIOS!$M$23) -> 0.4 | AH5: =$T5*AG5*(1+$Q5)^AH$2 -> 17387.818 | AI5: =IFERROR(VLOOKUP($E5,INPUTS!$A$44:$G$103,7,0),SCENARIOS!$N$23) -> 0.5 | AJ5: =$T5*AI5*(1+$Q5)^AJ$2 -> 24590.9 | AL5: =IF(H5="MULTI","MULTI",IF(COUNTIFS($E$4:$E$1277,H5,$H$4:$H$1277,E5)>0,"Y","N")) -> N | AM5: =T5*((1+Q5)^25) -> 49181.8 | AT5: US | AU5: =SUMIF($G$4:$G$1277,$AT5,$Z$4:$Z$1277) -> 22105.417 | AV5: =SUMIF($G$4:$G$1277,$AT5,$AB$4:$AB$1277) -> 146437 | AW5: =SUMIF($G$4:$G$1277,$AT5,$AD$4:$AD$1277) -> 538927.59 | AX5: =SUMIF($G$4:$G$1277,$AT5,$AF$4:$AF$1277) -> 1190039.2 | AY5: =SUMIF($G$4:$G$1277,$AT5,$AH$4:$AH$1277) -> 1970849.2 | AZ5: =SUMIF($G$4:$G$1277,$AT5,$AJ$4:$AJ$1277) -> 2901302.3 | BC5: ADD | BD5: =SUMIF($E$4:$E$1277,$BC5,$Z$4:$Z$1277) -> 0 | BE5: =SUMIF($E$4:$E$1277,$BC5,$AB$4:$AB$1277) -> 0 | BF5: =SUMIF($E$4:$E$1277,$BC5,$AD$4:$AD$1277) -> 0 | BG5: =SUMIF($E$4:$E$1277,$BC5,$AF$4:$AF$1277) -> 0 | BH5: =SUMIF($E$4:$E$1277,$BC5,$AH$4:$AH$1277) -> 0 | BI5: =SUMIF($E$4:$E$1277,$BC5,$AJ$4:$AJ$1277) -> 0 | BM5: Australia | BN5: =SUMIF($F$4:$F$1277,$BM5,$Z$4:$Z$1277) -> 0 | BO5: =SUMIF($F$4:$F$1277,$BM5,$AB$4:$AB$1277) -> 366002.9 | BP5: =SUMIF($F$4:$F$1277,$BM5,$AD$4:$AD$1277) -> 890596.99 | BQ5: =SUMIF($F$4:$F$1277,$BM5,$AF$4:$AF$1277) -> 2167094.8 | BR5: =SUMIF($F$4:$F$1277,$BM5,$AH$4:$AH$1277) -> 3954903.3 | BS5: =SUMIF($F$4:$F$1277,$BM5,$AJ$4:$AJ$1277) -> 6415659.5
A6: R003 | B6: LH | C6: Lufthansa | D6: Passenger | E6: FRA | F6: Germany | G6: EU | H6: DXB | I6: UAE | J6: MENA | K6: international | L6: B787-9 | M6: 730 | N6: =M6/365 -> 2 | O6: 5100 | P6: =M6*O6 -> 3723000 | Q6: =IFERROR(VLOOKUP(G6,SCENARIOS!$A$13:$E$18,2,0),0.025) -> 0.025 | R6: =IFERROR(VLOOKUP(L6,INPUTS!$A$107:$B$120,2,0),0.0082) -> 0.0079 | S6: =O6*R6 -> 40.29 | T6: =M6*S6 -> 29411.7 | U6: =T6/INPUTS!$B$7*1000 -> 36764625 | V6: =T6*INPUTS!$B$6 -> 92940.972 | W6: Yes | X6: Yes | Y6: =IFERROR(VLOOKUP(E6,INPUTS!$A$44:$B$103,2,0),0) -> 0.02 | Z6: =T6*Y6 -> 588.234 | AA6: =IFERROR(VLOOKUP(E6,INPUTS!$A$44:$C$103,3,0),SCENARIOS!$J$23) -> 0.06 | AB6: =$T6*AA6*(1+$Q6)^AB$2 -> 1996.5983 | AC6: =IFERROR(VLOOKUP($E6,INPUTS!$A$44:$G$103,4,0),SCENARIOS!$K$23) -> 0.15 | AD6: =$T6*AC6*(1+$Q6)^AD$2 -> 5647.4194 | AE6: =IFERROR(VLOOKUP($E6,INPUTS!$A$44:$G$103,5,0),SCENARIOS!$L$23) -> 0.3 | AF6: =$T6*AE6*(1+$Q6)^AF$2 -> 12779.073 | AG6: =IFERROR(VLOOKUP($E6,INPUTS!$A$44:$G$103,6,0),SCENARIOS!$M$23) -> 0.4 | AH6: =$T6*AG6*(1+$Q6)^AH$2 -> 19277.798 | AI6: =IFERROR(VLOOKUP($E6,INPUTS!$A$44:$G$103,7,0),SCENARIOS!$N$23) -> 0.5 | AJ6: =$T6*AI6*(1+$Q6)^AJ$2 -> 27263.824 | AL6: =IF(H6="MULTI","MULTI",IF(COUNTIFS($E$4:$E$1277,H6,$H$4:$H$1277,E6)>0,"Y","N")) -> Y | AM6: =T6*((1+Q6)^25) -> 54527.648 | AT6: APAC | AU6: =SUMIF($G$4:$G$1277,$AT6,$Z$4:$Z$1277) -> 0 | AV6: =SUMIF($G$4:$G$1277,$AT6,$AB$4:$AB$1277) -> 1197524.6 | AW6: =SUMIF($G$4:$G$1277,$AT6,$AD$4:$AD$1277) -> 2845899.3 | AX6: =SUMIF($G$4:$G$1277,$AT6,$AF$4:$AF$1277) -> 6974002 | AY6: =SUMIF($G$4:$G$1277,$AT6,$AH$4:$AH$1277) -> 12130968 | AZ6: =SUMIF($G$4:$G$1277,$AT6,$AJ$4:$AJ$1277) -> 19267748 | BC6: AKL | BD6: =SUMIF($E$4:$E$1277,$BC6,$Z$4:$Z$1277) -> 0 | BE6: =SUMIF($E$4:$E$1277,$BC6,$AB$4:$AB$1277) -> 13256.928 | BF6: =SUMIF($E$4:$E$1277,$BC6,$AD$4:$AD$1277) -> 40322.699 | BG6: =SUMIF($E$4:$E$1277,$BC6,$AF$4:$AF$1277) -> 147176.19 | BH6: =SUMIF($E$4:$E$1277,$BC6,$AH$4:$AH$1277) -> 238749.78 | BI6: =SUMIF($E$4:$E$1277,$BC6,$AJ$4:$AJ$1277) -> 435713.42 | BM6: Austria | BN6: =SUMIF($F$4:$F$1277,$BM6,$Z$4:$Z$1277) -> 39805.758 | BO6: =SUMIF($F$4:$F$1277,$BM6,$AB$4:$AB$1277) -> 135109.69 | BP6: =SUMIF($F$4:$F$1277,$BM6,$AD$4:$AD$1277) -> 382160.52 | BQ6: =SUMIF($F$4:$F$1277,$BM6,$AF$4:$AF$1277) -> 864759.1 | BR6: =SUMIF($F$4:$F$1277,$BM6,$AH$4:$AH$1277) -> 1304527.4 | BS6: =SUMIF($F$4:$F$1277,$BM6,$AJ$4:$AJ$1277) -> 1844941.3
A7: R004 | B7: LH | C7: Lufthansa | D7: Passenger | E7: FRA | F7: Germany | G7: EU | H7: SIN | I7: Singapore | J7: APAC | K7: international | L7: A350-900 | M7: 365 | N7: =M7/365 -> 1 | O7: 10600 | P7: =M7*O7 -> 3869000 | Q7: =IFERROR(VLOOKUP(G7,SCENARIOS!$A$13:$E$18,2,0),0.025) -> 0.025 | R7: =IFERROR(VLOOKUP(L7,INPUTS!$A$107:$B$120,2,0),0.0082) -> 0.0079 | S7: =O7*R7 -> 83.74 | T7: =M7*S7 -> 30565.1 | U7: =T7/INPUTS!$B$7*1000 -> 38206375 | V7: =T7*INPUTS!$B$6 -> 96585.716 | W7: Yes | X7: Yes | Y7: =IFERROR(VLOOKUP(E7,INPUTS!$A$44:$B$103,2,0),0) -> 0.02 | Z7: =T7*Y7 -> 611.302 | AA7: =IFERROR(VLOOKUP(E7,INPUTS!$A$44:$C$103,3,0),SCENARIOS!$J$23) -> 0.06 | AB7: =$T7*AA7*(1+$Q7)^AB$2 -> 2074.8963 | AC7: =IFERROR(VLOOKUP($E7,INPUTS!$A$44:$G$103,4,0),SCENARIOS!$K$23) -> 0.15 | AD7: =$T7*AC7*(1+$Q7)^AD$2 -> 5868.8868 | AE7: =IFERROR(VLOOKUP($E7,INPUTS!$A$44:$G$103,5,0),SCENARIOS!$L$23) -> 0.3 | AF7: =$T7*AE7*(1+$Q7)^AF$2 -> 13280.213 | AG7: =IFERROR(VLOOKUP($E7,INPUTS!$A$44:$G$103,6,0),SCENARIOS!$M$23) -> 0.4 | AH7: =$T7*AG7*(1+$Q7)^AH$2 -> 20033.79 | AI7: =IFERROR(VLOOKUP($E7,INPUTS!$A$44:$G$103,7,0),SCENARIOS!$N$23) -> 0.5 | AJ7: =$T7*AI7*(1+$Q7)^AJ$2 -> 28332.993 | AL7: =IF(H7="MULTI","MULTI",IF(COUNTIFS($E$4:$E$1277,H7,$H$4:$H$1277,E7)>0,"Y","N")) -> Y | AM7: =T7*((1+Q7)^25) -> 56665.987 | AT7: MENA | AU7: =SUMIF($G$4:$G$1277,$AT7,$Z$4:$Z$1277) -> 0 | AV7: =SUMIF($G$4:$G$1277,$AT7,$AB$4:$AB$1277) -> 0 | AW7: =SUMIF($G$4:$G$1277,$AT7,$AD$4:$AD$1277) -> 0 | AX7: =SUMIF($G$4:$G$1277,$AT7,$AF$4:$AF$1277) -> 0 | AY7: =SUMIF($G$4:$G$1277,$AT7,$AH$4:$AH$1277) -> 0 | AZ7: =SUMIF($G$4:$G$1277,$AT7,$AJ$4:$AJ$1277) -> 0 | BC7: AMM | BD7: =SUMIF($E$4:$E$1277,$BC7,$Z$4:$Z$1277) -> 0 | BE7: =SUMIF($E$4:$E$1277,$BC7,$AB$4:$AB$1277) -> 0 | BF7: =SUMIF($E$4:$E$1277,$BC7,$AD$4:$AD$1277) -> 0 | BG7: =SUMIF($E$4:$E$1277,$BC7,$AF$4:$AF$1277) -> 0 | BH7: =SUMIF($E$4:$E$1277,$BC7,$AH$4:$AH$1277) -> 0 | BI7: =SUMIF($E$4:$E$1277,$BC7,$AJ$4:$AJ$1277) -> 0 | BM7: Bahrain | BN7: =SUMIF($F$4:$F$1277,$BM7,$Z$4:$Z$1277) -> 0 | BO7: =SUMIF($F$4:$F$1277,$BM7,$AB$4:$AB$1277) -> 0 | BP7: =SUMIF($F$4:$F$1277,$BM7,$AD$4:$AD$1277) -> 0 | BQ7: =SUMIF($F$4:$F$1277,$BM7,$AF$4:$AF$1277) -> 0 | BR7: =SUMIF($F$4:$F$1277,$BM7,$AH$4:$AH$1277) -> 0 | BS7: =SUMIF($F$4:$F$1277,$BM7,$AJ$4:$AJ$1277) -> 0
A8: R005 | B8: AF | C8: Air France | D8: Passenger | E8: CDG | F8: France | G8: EU | H8: JFK | I8: United States | J8: US | K8: international | L8: B787-9 | M8: 730 | N8: =M8/365 -> 2 | O8: 5830 | P8: =M8*O8 -> 4255900 | Q8: =IFERROR(VLOOKUP(G8,SCENARIOS!$A$13:$E$18,2,0),0.025) -> 0.025 | R8: =IFERROR(VLOOKUP(L8,INPUTS!$A$107:$B$120,2,0),0.0082) -> 0.0079 | S8: =O8*R8 -> 46.057 | T8: =M8*S8 -> 33621.61 | U8: =T8/INPUTS!$B$7*1000 -> 42027012 | V8: =T8*INPUTS!$B$6 -> 106244.29 | W8: Yes | X8: Yes | Y8: =IFERROR(VLOOKUP(E8,INPUTS!$A$44:$B$103,2,0),0) -> 0.02 | Z8: =T8*Y8 -> 672.4322 | AA8: =IFERROR(VLOOKUP(E8,INPUTS!$A$44:$C$103,3,0),SCENARIOS!$J$23) -> 0.06 | AB8: =$T8*AA8*(1+$Q8)^AB$2 -> 2282.3859 | AC8: =IFERROR(VLOOKUP($E8,INPUTS!$A$44:$G$103,4,0),SCENARIOS!$K$23) -> 0.15 | AD8: =$T8*AC8*(1+$Q8)^AD$2 -> 6455.7755 | AE8: =IFERROR(VLOOKUP($E8,INPUTS!$A$44:$G$103,5,0),SCENARIOS!$L$23) -> 0.3 | AF8: =$T8*AE8*(1+$Q8)^AF$2 -> 14608.235 | AG8: =IFERROR(VLOOKUP($E8,INPUTS!$A$44:$G$103,6,0),SCENARIOS!$M$23) -> 0.4 | AH8: =$T8*AG8*(1+$Q8)^AH$2 -> 22037.169 | AI8: =IFERROR(VLOOKUP($E8,INPUTS!$A$44:$G$103,7,0),SCENARIOS!$N$23) -> 0.5 | AJ8: =$T8*AI8*(1+$Q8)^AJ$2 -> 31166.293 | AL8: =IF(H8="MULTI","MULTI",IF(COUNTIFS($E$4:$E$1277,H8,$H$4:$H$1277,E8)>0,"Y","N")) -> Y | AM8: =T8*((1+Q8)^25) -> 62332.585 | AT8: LATAM | AU8: =SUMIF($G$4:$G$1277,$AT8,$Z$4:$Z$1277) -> 0 | AV8: =SUMIF($G$4:$G$1277,$AT8,$AB$4:$AB$1277) -> 0 | AW8: =SUMIF($G$4:$G$1277,$AT8,$AD$4:$AD$1277) -> 0 | AX8: =SUMIF($G$4:$G$1277,$AT8,$AF$4:$AF$1277) -> 0 | AY8: =SUMIF($G$4:$G$1277,$AT8,$AH$4:$AH$1277) -> 0 | AZ8: =SUMIF($G$4:$G$1277,$AT8,$AJ$4:$AJ$1277) -> 0 | BC8: AMS | BD8: =SUMIF($E$4:$E$1277,$BC8,$Z$4:$Z$1277) -> 49783.248 | BE8: =SUMIF($E$4:$E$1277,$BC8,$AB$4:$AB$1277) -> 168975.53 | BF8: =SUMIF($E$4:$E$1277,$BC8,$AD$4:$AD$1277) -> 477950.75 | BG8: =SUMIF($E$4:$E$1277,$BC8,$AF$4:$AF$1277) -> 1081514.8 | BH8: =SUMIF($E$4:$E$1277,$BC8,$AH$4:$AH$1277) -> 1631513 | BI8: =SUMIF($E$4:$E$1277,$BC8,$AJ$4:$AJ$1277) -> 2307384 | BM8: Belgium | BN8: =SUMIF($F$4:$F$1277,$BM8,$Z$4:$Z$1277) -> 3959.6358 | BO8: =SUMIF($F$4:$F$1277,$BM8,$AB$4:$AB$1277) -> 13439.893 | BP8: =SUMIF($F$4:$F$1277,$BM8,$AD$4:$AD$1277) -> 38015.014 | BQ8: =SUMIF($F$4:$F$1277,$BM8,$AF$4:$AF$1277) -> 86020.999 | BR8: =SUMIF($F$4:$F$1277,$BM8,$AH$4:$AH$1277) -> 129766.49 | BS8: =SUMIF($F$4:$F$1277,$BM8,$AJ$4:$AJ$1277) -> 183523.59
A9: R006 | B9: AF | C9: Air France | D9: Passenger | E9: CDG | F9: France | G9: EU | H9: NRT | I9: Japan | J9: APAC | K9: international | L9: B777-300ER | M9: 365 | N9: =M9/365 -> 1 | O9: 9730 | P9: =M9*O9 -> 3551450 | Q9: =IFERROR(VLOOKUP(G9,SCENARIOS!$A$13:$E$18,2,0),0.025) -> 0.025 | R9: =IFERROR(VLOOKUP(L9,INPUTS!$A$107:$B$120,2,0),0.0082) -> 0.0089 | S9: =O9*R9 -> 86.597 | T9: =M9*S9 -> 31607.905 | U9: =T9/INPUTS!$B$7*1000 -> 39509881 | V9: =T9*INPUTS!$B$6 -> 99880.98 | W9: Yes | X9: Yes | Y9: =IFERROR(VLOOKUP(E9,INPUTS!$A$44:$B$103,2,0),0) -> 0.02 | Z9: =T9*Y9 -> 632.1581 | AA9: =IFERROR(VLOOKUP(E9,INPUTS!$A$44:$C$103,3,0),SCENARIOS!$J$23) -> 0.06 | AB9: =$T9*AA9*(1+$Q9)^AB$2 -> 2145.6866 | AC9: =IFERROR(VLOOKUP($E9,INPUTS!$A$44:$G$103,4,0),SCENARIOS!$K$23) -> 0.15 | AD9: =$T9*AC9*(1+$Q9)^AD$2 -> 6069.1186 | AE9: =IFERROR(VLOOKUP($E9,INPUTS!$A$44:$G$103,5,0),SCENARIOS!$L$23) -> 0.3 | AF9: =$T9*AE9*(1+$Q9)^AF$2 -> 13733.301 | AG9: =IFERROR(VLOOKUP($E9,INPUTS!$A$44:$G$103,6,0),SCENARIOS!$M$23) -> 0.4 | AH9: =$T9*AG9*(1+$Q9)^AH$2 -> 20717.293 | AI9: =IFERROR(VLOOKUP($E9,INPUTS!$A$44:$G$103,7,0),SCENARIOS!$N$23) -> 0.5 | AJ9: =$T9*AI9*(1+$Q9)^AJ$2 -> 29299.644 | AL9: =IF(H9="MULTI","MULTI",IF(COUNTIFS($E$4:$E$1277,H9,$H$4:$H$1277,E9)>0,"Y","N")) -> Y | AM9: =T9*((1+Q9)^25) -> 58599.289 | AT9: ROW | AU9: =SUMIF($G$4:$G$1277,$AT9,$Z$4:$Z$1277) -> 0 | AV9: =SUMIF($G$4:$G$1277,$AT9,$AB$4:$AB$1277) -> 0 | AW9: =SUMIF($G$4:$G$1277,$AT9,$AD$4:$AD$1277) -> 0 | AX9: =SUMIF($G$4:$G$1277,$AT9,$AF$4:$AF$1277) -> 0 | AY9: =SUMIF($G$4:$G$1277,$AT9,$AH$4:$AH$1277) -> 0 | AZ9: =SUMIF($G$4:$G$1277,$AT9,$AJ$4:$AJ$1277) -> 0 | BC9: ANC | BD9: =SUMIF($E$4:$E$1277,$BC9,$Z$4:$Z$1277) -> 197.976 | BE9: =SUMIF($E$4:$E$1277,$BC9,$AB$4:$AB$1277) -> 1311.489 | BF9: =SUMIF($E$4:$E$1277,$BC9,$AD$4:$AD$1277) -> 4826.6328 | BG9: =SUMIF($E$4:$E$1277,$BC9,$AF$4:$AF$1277) -> 10657.985 | BH9: =SUMIF($E$4:$E$1277,$BC9,$AH$4:$AH$1277) -> 17650.915 | BI9: =SUMIF($E$4:$E$1277,$BC9,$AJ$4:$AJ$1277) -> 25984.049 | BM9: Brazil | BN9: =SUMIF($F$4:$F$1277,$BM9,$Z$4:$Z$1277) -> 0 | BO9: =SUMIF($F$4:$F$1277,$BM9,$AB$4:$AB$1277) -> 0 | BP9: =SUMIF($F$4:$F$1277,$BM9,$AD$4:$AD$1277) -> 0 | BQ9: =SUMIF($F$4:$F$1277,$BM9,$AF$4:$AF$1277) -> 0 | BR9: =SUMIF($F$4:$F$1277,$BM9,$AH$4:$AH$1277) -> 0 | BS9: =SUMIF($F$4:$F$1277,$BM9,$AJ$4:$AJ$1277) -> 0
A10: R007 | B10: BA | C10: British Airways | D10: Passenger | E10: LHR | F10: United Kingdom | G10: EU | H10: JFK | I10: United States | J10: US | K10: international | L10: B777-300ER | M10: 1460 | N10: =M10/365 -> 4 | O10: 5555 | P10: =M10*O10 -> 8110300 | Q10: =IFERROR(VLOOKUP(G10,SCENARIOS!$A$13:$E$18,2,0),0.025) -> 0.025 | R10: =IFERROR(VLOOKUP(L10,INPUTS!$A$107:$B$120,2,0),0.0082) -> 0.0089 | S10: =O10*R10 -> 49.4395 | T10: =M10*S10 -> 72181.67 | U10: =T10/INPUTS!$B$7*1000 -> 90227088 | V10: =T10*INPUTS!$B$6 -> 228094.08 | W10: Yes | X10: Yes | Y10: =IFERROR(VLOOKUP(E10,INPUTS!$A$44:$B$103,2,0),0) -> 0.02 | Z10: =T10*Y10 -> 1443.6334 | AA10: =IFERROR(VLOOKUP(E10,INPUTS!$A$44:$C$103,3,0),SCENARIOS!$J$23) -> 0.1 | AB10: =$T10*AA10*(1+$Q10)^AB$2 -> 8166.6934 | AC10: =IFERROR(VLOOKUP($E10,INPUTS!$A$44:$G$103,4,0),SCENARIOS!$K$23) -> 0.15 | AD10: =$T10*AC10*(1+$Q10)^AD$2 -> 13859.796 | AE10: =IFERROR(VLOOKUP($E10,INPUTS!$A$44:$G$103,5,0),SCENARIOS!$L$23) -> 0.3 | AF10: =$T10*AE10*(1+$Q10)^AF$2 -> 31362.174 | AG10: =IFERROR(VLOOKUP($E10,INPUTS!$A$44:$G$103,6,0),SCENARIOS!$M$23) -> 0.4 | AH10: =$T10*AG10*(1+$Q10)^AH$2 -> 47311.228 | AI10: =IFERROR(VLOOKUP($E10,INPUTS!$A$44:$G$103,7,0),SCENARIOS!$N$23) -> 0.5 | AJ10: =$T10*AI10*(1+$Q10)^AJ$2 -> 66910.391 | AL10: =IF(H10="MULTI","MULTI",IF(COUNTIFS($E$4:$E$1277,H10,$H$4:$H$1277,E10)>0,"Y","N")) -> Y | AM10: =T10*((1+Q10)^25) -> 133820.78 | BC10: ARN | BD10: =SUMIF($E$4:$E$1277,$BC10,$Z$4:$Z$1277) -> 0 | BE10: =SUMIF($E$4:$E$1277,$BC10,$AB$4:$AB$1277) -> 0 | BF10: =SUMIF($E$4:$E$1277,$BC10,$AD$4:$AD$1277) -> 0 | BG10: =SUMIF($E$4:$E$1277,$BC10,$AF$4:$AF$1277) -> 0 | BH10: =SUMIF($E$4:$E$1277,$BC10,$AH$4:$AH$1277) -> 0 | BI10: =SUMIF($E$4:$E$1277,$BC10,$AJ$4:$AJ$1277) -> 0 | BM10: Canada | BN10: =SUMIF($F$4:$F$1277,$BM10,$Z$4:$Z$1277) -> 0 | BO10: =SUMIF($F$4:$F$1277,$BM10,$AB$4:$AB$1277) -> 0 | BP10: =SUMIF($F$4:$F$1277,$BM10,$AD$4:$AD$1277) -> 0 | BQ10: =SUMIF($F$4:$F$1277,$BM10,$AF$4:$AF$1277) -> 0 | BR10: =SUMIF($F$4:$F$1277,$BM10,$AH$4:$AH$1277) -> 0 | BS10: =SUMIF($F$4:$F$1277,$BM10,$AJ$4:$AJ$1277) -> 0
A11: R008 | B11: BA | C11: British Airways | D11: Passenger | E11: LHR | F11: United Kingdom | G11: EU | H11: DXB | I11: UAE | J11: MENA | K11: international | L11: B777-300ER | M11: 1460 | N11: =M11/365 -> 4 | O11: 5490 | P11: =M11*O11 -> 8015400 | Q11: =IFERROR(VLOOKUP(G11,SCENARIOS!$A$13:$E$18,2,0),0.025) -> 0.025 | R11: =IFERROR(VLOOKUP(L11,INPUTS!$A$107:$B$120,2,0),0.0082) -> 0.0089 | S11: =O11*R11 -> 48.861 | T11: =M11*S11 -> 71337.06 | U11: =T11/INPUTS!$B$7*1000 -> 89171325 | V11: =T11*INPUTS!$B$6 -> 225425.11 | W11: Yes | X11: Yes | Y11: =IFERROR(VLOOKUP(E11,INPUTS!$A$44:$B$103,2,0),0) -> 0.02 | Z11: =T11*Y11 -> 1426.7412 | AA11: =IFERROR(VLOOKUP(E11,INPUTS!$A$44:$C$103,3,0),SCENARIOS!$J$23) -> 0.1 | AB11: =$T11*AA11*(1+$Q11)^AB$2 -> 8071.1336 | AC11: =IFERROR(VLOOKUP($E11,INPUTS!$A$44:$G$103,4,0),SCENARIOS!$K$23) -> 0.15 | AD11: =$T11*AC11*(1+$Q11)^AD$2 -> 13697.62 | AE11: =IFERROR(VLOOKUP($E11,INPUTS!$A$44:$G$103,5,0),SCENARIOS!$L$23) -> 0.3 | AF11: =$T11*AE11*(1+$Q11)^AF$2 -> 30995.2 | AG11: =IFERROR(VLOOKUP($E11,INPUTS!$A$44:$G$103,6,0),SCENARIOS!$M$23) -> 0.4 | AH11: =$T11*AG11*(1+$Q11)^AH$2 -> 46757.632 | AI11: =IFERROR(VLOOKUP($E11,INPUTS!$A$44:$G$103,7,0),SCENARIOS!$N$23) -> 0.5 | AJ11: =$T11*AI11*(1+$Q11)^AJ$2 -> 66127.461 | AL11: =IF(H11="MULTI","MULTI",IF(COUNTIFS($E$4:$E$1277,H11,$H$4:$H$1277,E11)>0,"Y","N")) -> Y | AM11: =T11*((1+Q11)^25) -> 132254.92 | AT11: Total | AU11: =SUM(AU4:AU9) -> 783907.49 | AV11: =SUM(AV4:AV9) -> 4358968.6 | AW11: =SUM(AW4:AW9) -> 10698610 | AX11: =SUM(AX4:AX9) -> 24713789 | AY11: =SUM(AY4:AY9) -> 39067846 | AZ11: =SUM(AZ4:AZ9) -> 57477512 | BC11: ATH | BD11: =SUMIF($E$4:$E$1277,$BC11,$Z$4:$Z$1277) -> 2623.5186 | BE11: =SUMIF($E$4:$E$1277,$BC11,$AB$4:$AB$1277) -> 8904.8115 | BF11: =SUMIF($E$4:$E$1277,$BC11,$AD$4:$AD$1277) -> 25187.442 | BG11: =SUMIF($E$4:$E$1277,$BC11,$AF$4:$AF$1277) -> 56994.558 | BH11: =SUMIF($E$4:$E$1277,$BC11,$AH$4:$AH$1277) -> 85978.814 | BI11: =SUMIF($E$4:$E$1277,$BC11,$AJ$4:$AJ$1277) -> 121596.42 | BM11: Chile | BN11: =SUMIF($F$4:$F$1277,$BM11,$Z$4:$Z$1277) -> 0 | BO11: =SUMIF($F$4:$F$1277,$BM11,$AB$4:$AB$1277) -> 0 | BP11: =SUMIF($F$4:$F$1277,$BM11,$AD$4:$AD$1277) -> 0 | BQ11: =SUMIF($F$4:$F$1277,$BM11,$AF$4:$AF$1277) -> 0 | BR11: =SUMIF($F$4:$F$1277,$BM11,$AH$4:$AH$1277) -> 0 | BS11: =SUMIF($F$4:$F$1277,$BM11,$AJ$4:$AJ$1277) -> 0
A12: R009 | B12: BA | C12: British Airways | D12: Passenger | E12: LHR | F12: United Kingdom | G12: EU | H12: HKG | I12: Hong Kong | J12: APAC | K12: international | L12: B777-300ER | M12: 730 | N12: =M12/365 -> 2 | O12: 9630 | P12: =M12*O12 -> 7029900 | Q12: =IFERROR(VLOOKUP(G12,SCENARIOS!$A$13:$E$18,2,0),0.025) -> 0.025 | R12: =IFERROR(VLOOKUP(L12,INPUTS!$A$107:$B$120,2,0),0.0082) -> 0.0089 | S12: =O12*R12 -> 85.707 | T12: =M12*S12 -> 62566.11 | U12: =T12/INPUTS!$B$7*1000 -> 78207638 | V12: =T12*INPUTS!$B$6 -> 197708.91 | W12: Yes | X12: Yes | Y12: =IFERROR(VLOOKUP(E12,INPUTS!$A$44:$B$103,2,0),0) -> 0.02 | Z12: =T12*Y12 -> 1251.3222 | AA12: =IFERROR(VLOOKUP(E12,INPUTS!$A$44:$C$103,3,0),SCENARIOS!$J$23) -> 0.1 | AB12: =$T12*AA12*(1+$Q12)^AB$2 -> 7078.7811 | AC12: =IFERROR(VLOOKUP($E12,INPUTS!$A$44:$G$103,4,0),SCENARIOS!$K$23) -> 0.15 | AD12: =$T12*AC12*(1+$Q12)^AD$2 -> 12013.487 | AE12: =IFERROR(VLOOKUP($E12,INPUTS!$A$44:$G$103,5,0),SCENARIOS!$L$23) -> 0.3 | AF12: =$T12*AE12*(1+$Q12)^AF$2 -> 27184.315 | AG12: =IFERROR(VLOOKUP($E12,INPUTS!$A$44:$G$103,6,0),SCENARIOS!$M$23) -> 0.4 | AH12: =$T12*AG12*(1+$Q12)^AH$2 -> 41008.743 | AI12: =IFERROR(VLOOKUP($E12,INPUTS!$A$44:$G$103,7,0),SCENARIOS!$N$23) -> 0.5 | AJ12: =$T12*AI12*(1+$Q12)^AJ$2 -> 57997.035 | AL12: =IF(H12="MULTI","MULTI",IF(COUNTIFS($E$4:$E$1277,H12,$H$4:$H$1277,E12)>0,"Y","N")) -> Y | AM12: =T12*((1+Q12)^25) -> 115994.07 | BC12: ATL | BD12: =SUMIF($E$4:$E$1277,$BC12,$Z$4:$Z$1277) -> 923.47238 | BE12: =SUMIF($E$4:$E$1277,$BC12,$AB$4:$AB$1277) -> 6117.5287 | BF12: =SUMIF($E$4:$E$1277,$BC12,$AD$4:$AD$1277) -> 22514.153 | BG12: =SUMIF($E$4:$E$1277,$BC12,$AF$4:$AF$1277) -> 49714.889 | BH12: =SUMIF($E$4:$E$1277,$BC12,$AH$4:$AH$1277) -> 82333.882 | BI12: =SUMIF($E$4:$E$1277,$BC12,$AJ$4:$AJ$1277) -> 121204.35 | BM12: China | BN12: =SUMIF($F$4:$F$1277,$BM12,$Z$4:$Z$1277) -> 0 | BO12: =SUMIF($F$4:$F$1277,$BM12,$AB$4:$AB$1277) -> 0 | BP12: =SUMIF($F$4:$F$1277,$BM12,$AD$4:$AD$1277) -> 0 | BQ12: =SUMIF($F$4:$F$1277,$BM12,$AF$4:$AF$1277) -> 0 | BR12: =SUMIF($F$4:$F$1277,$BM12,$AH$4:$AH$1277) -> 0 | BS12: =SUMIF($F$4:$F$1277,$BM12,$AJ$4:$AJ$1277) -> 0
A13: R010 | B13: BA | C13: British Airways | D13: Passenger | E13: LHR | F13: United Kingdom | G13: EU | H13: SYD | I13: Australia | J13: APAC | K13: international | L13: B787-9 | M13: 365 | N13: =M13/365 -> 1 | O13: 16990 | P13: =M13*O13 -> 6201350 | Q13: =IFERROR(VLOOKUP(G13,SCENARIOS!$A$13:$E$18,2,0),0.025) -> 0.025 | R13: =IFERROR(VLOOKUP(L13,INPUTS!$A$107:$B$120,2,0),0.0082) -> 0.0079 | S13: =O13*R13 -> 134.221 | T13: =M13*S13 -> 48990.665 | U13: =T13/INPUTS!$B$7*1000 -> 61238331 | V13: =T13*INPUTS!$B$6 -> 154810.5 | W13: Yes | X13: Yes | Y13: =IFERROR(VLOOKUP(E13,INPUTS!$A$44:$B$103,2,0),0) -> 0.02 | Z13: =T13*Y13 -> 979.8133 | AA13: =IFERROR(VLOOKUP(E13,INPUTS!$A$44:$C$103,3,0),SCENARIOS!$J$23) -> 0.1 | AB13: =$T13*AA13*(1+$Q13)^AB$2 -> 5542.8441 | AC13: =IFERROR(VLOOKUP($E13,INPUTS!$A$44:$G$103,4,0),SCENARIOS!$K$23) -> 0.15 | AD13: =$T13*AC13*(1+$Q13)^AD$2 -> 9406.829 | AE13: =IFERROR(VLOOKUP($E13,INPUTS!$A$44:$G$103,5,0),SCENARIOS!$L$23) -> 0.3 | AF13: =$T13*AE13*(1+$Q13)^AF$2 -> 21285.927 | AG13: =IFERROR(VLOOKUP($E13,INPUTS!$A$44:$G$103,6,0),SCENARIOS!$M$23) -> 0.4 | AH13: =$T13*AG13*(1+$Q13)^AH$2 -> 32110.764 | AI13: =IFERROR(VLOOKUP($E13,INPUTS!$A$44:$G$103,7,0),SCENARIOS!$N$23) -> 0.5 | AJ13: =$T13*AI13*(1+$Q13)^AJ$2 -> 45412.977 | AL13: =IF(H13="MULTI","MULTI",IF(COUNTIFS($E$4:$E$1277,H13,$H$4:$H$1277,E13)>0,"Y","N")) -> Y | AM13: =T13*((1+Q13)^25) -> 90825.954 | BC13: AUH | BD13: =SUMIF($E$4:$E$1277,$BC13,$Z$4:$Z$1277) -> 0 | BE13: =SUMIF($E$4:$E$1277,$BC13,$AB$4:$AB$1277) -> 0 | BF13: =SUMIF($E$4:$E$1277,$BC13,$AD$4:$AD$1277) -> 0 | BG13: =SUMIF($E$4:$E$1277,$BC13,$AF$4:$AF$1277) -> 0 | BH13: =SUMIF($E$4:$E$1277,$BC13,$AH$4:$AH$1277) -> 0 | BI13: =SUMIF($E$4:$E$1277,$BC13,$AJ$4:$AJ$1277) -> 0 | BM13: Colombia | BN13: =SUMIF($F$4:$F$1277,$BM13,$Z$4:$Z$1277) -> 0 | BO13: =SUMIF($F$4:$F$1277,$BM13,$AB$4:$AB$1277) -> 0 | BP13: =SUMIF($F$4:$F$1277,$BM13,$AD$4:$AD$1277) -> 0 | BQ13: =SUMIF($F$4:$F$1277,$BM13,$AF$4:$AF$1277) -> 0 | BR13: =SUMIF($F$4:$F$1277,$BM13,$AH$4:$AH$1277) -> 0 | BS13: =SUMIF($F$4:$F$1277,$BM13,$AJ$4:$AJ$1277) -> 0
A14: R011 | B14: KL | C14: KLM | D14: Passenger | E14: AMS | F14: Netherlands | G14: EU | H14: GRU | I14: Brazil | J14: LATAM | K14: international | L14: B787-9 | M14: 365 | N14: =M14/365 -> 1 | O14: 9980 | P14: =M14*O14 -> 3642700 | Q14: =IFERROR(VLOOKUP(G14,SCENARIOS!$A$13:$E$18,2,0),0.025) -> 0.025 | R14: =IFERROR(VLOOKUP(L14,INPUTS!$A$107:$B$120,2,0),0.0082) -> 0.0079 | S14: =O14*R14 -> 78.842 | T14: =M14*S14 -> 28777.33 | U14: =T14/INPUTS!$B$7*1000 -> 35971662 | V14: =T14*INPUTS!$B$6 -> 90936.363 | W14: Yes | X14: Yes | Y14: =IFERROR(VLOOKUP(E14,INPUTS!$A$44:$B$103,2,0),0) -> 0.02 | Z14: =T14*Y14 -> 575.5466 | AA14: =IFERROR(VLOOKUP(E14,INPUTS!$A$44:$C$103,3,0),SCENARIOS!$J$23) -> 0.06 | AB14: =$T14*AA14*(1+$Q14)^AB$2 -> 1953.5345 | AC14: =IFERROR(VLOOKUP($E14,INPUTS!$A$44:$G$103,4,0),SCENARIOS!$K$23) -> 0.15 | AD14: =$T14*AC14*(1+$Q14)^AD$2 -> 5525.6123 | AE14: =IFERROR(VLOOKUP($E14,INPUTS!$A$44:$G$103,5,0),SCENARIOS!$L$23) -> 0.3 | AF14: =$T14*AE14*(1+$Q14)^AF$2 -> 12503.446 | AG14: =IFERROR(VLOOKUP($E14,INPUTS!$A$44:$G$103,6,0),SCENARIOS!$M$23) -> 0.4 | AH14: =$T14*AG14*(1+$Q14)^AH$2 -> 18862.002 | AI14: =IFERROR(VLOOKUP($E14,INPUTS!$A$44:$G$103,7,0),SCENARIOS!$N$23) -> 0.5 | AJ14: =$T14*AI14*(1+$Q14)^AJ$2 -> 26675.781 | AL14: =IF(H14="MULTI","MULTI",IF(COUNTIFS($E$4:$E$1277,H14,$H$4:$H$1277,E14)>0,"Y","N")) -> N | AM14: =T14*((1+Q14)^25) -> 53351.561 | AT14: SAF in million tonnes per annum | BC14: BAH | BD14: =SUMIF($E$4:$E$1277,$BC14,$Z$4:$Z$1277) -> 0 | BE14: =SUMIF($E$4:$E$1277,$BC14,$AB$4:$AB$1277) -> 0 | BF14: =SUMIF($E$4:$E$1277,$BC14,$AD$4:$AD$1277) -> 0 | BG14: =SUMIF($E$4:$E$1277,$BC14,$AF$4:$AF$1277) -> 0 | BH14: =SUMIF($E$4:$E$1277,$BC14,$AH$4:$AH$1277) -> 0 | BI14: =SUMIF($E$4:$E$1277,$BC14,$AJ$4:$AJ$1277) -> 0 | BM14: Czechia | BN14: =SUMIF($F$4:$F$1277,$BM14,$Z$4:$Z$1277) -> 0 | BO14: =SUMIF($F$4:$F$1277,$BM14,$AB$4:$AB$1277) -> 0 | BP14: =SUMIF($F$4:$F$1277,$BM14,$AD$4:$AD$1277) -> 0 | BQ14: =SUMIF($F$4:$F$1277,$BM14,$AF$4:$AF$1277) -> 0 | BR14: =SUMIF($F$4:$F$1277,$BM14,$AH$4:$AH$1277) -> 0 | BS14: =SUMIF($F$4:$F$1277,$BM14,$AJ$4:$AJ$1277) -> 0
A15: R012 | B15: IB | C15: Iberia | D15: Passenger | E15: MAD | F15: Spain | G15: EU | H15: GRU | I15: Brazil | J15: LATAM | K15: international | L15: A350-900 | M15: 730 | N15: =M15/365 -> 2 | O15: 10000 | P15: =M15*O15 -> 7300000 | Q15: =IFERROR(VLOOKUP(G15,SCENARIOS!$A$13:$E$18,2,0),0.025) -> 0.025 | R15: =IFERROR(VLOOKUP(L15,INPUTS!$A$107:$B$120,2,0),0.0082) -> 0.0079 | S15: =O15*R15 -> 79 | T15: =M15*S15 -> 57670 | U15: =T15/INPUTS!$B$7*1000 -> 72087500 | V15: =T15*INPUTS!$B$6 -> 182237.2 | W15: Yes | X15: Yes | Y15: =IFERROR(VLOOKUP(E15,INPUTS!$A$44:$B$103,2,0),0) -> 0.02 | Z15: =T15*Y15 -> 1153.4 | AA15: =IFERROR(VLOOKUP(E15,INPUTS!$A$44:$C$103,3,0),SCENARIOS!$J$23) -> 0.06 | AB15: =$T15*AA15*(1+$Q15)^AB$2 -> 3914.8987 | AC15: =IFERROR(VLOOKUP($E15,INPUTS!$A$44:$G$103,4,0),SCENARIOS!$K$23) -> 0.15 | AD15: =$T15*AC15*(1+$Q15)^AD$2 -> 11073.371 | AE15: =IFERROR(VLOOKUP($E15,INPUTS!$A$44:$G$103,5,0),SCENARIOS!$L$23) -> 0.3 | AF15: =$T15*AE15*(1+$Q15)^AF$2 -> 25057.007 | AG15: =IFERROR(VLOOKUP($E15,INPUTS!$A$44:$G$103,6,0),SCENARIOS!$M$23) -> 0.4 | AH15: =$T15*AG15*(1+$Q15)^AH$2 -> 37799.604 | AI15: =IFERROR(VLOOKUP($E15,INPUTS!$A$44:$G$103,7,0),SCENARIOS!$N$23) -> 0.5 | AJ15: =$T15*AI15*(1+$Q15)^AJ$2 -> 53458.478 | AL15: =IF(H15="MULTI","MULTI",IF(COUNTIFS($E$4:$E$1277,H15,$H$4:$H$1277,E15)>0,"Y","N")) -> Y | AM15: =T15*((1+Q15)^25) -> 106916.96 | BC15: BCN | BD15: =SUMIF($E$4:$E$1277,$BC15,$Z$4:$Z$1277) -> 27991.031 | BE15: =SUMIF($E$4:$E$1277,$BC15,$AB$4:$AB$1277) -> 95007.847 | BF15: =SUMIF($E$4:$E$1277,$BC15,$AD$4:$AD$1277) -> 268731.65 | BG15: =SUMIF($E$4:$E$1277,$BC15,$AF$4:$AF$1277) -> 608090.38 | BH15: =SUMIF($E$4:$E$1277,$BC15,$AH$4:$AH$1277) -> 917331.27 | BI15: =SUMIF($E$4:$E$1277,$BC15,$AJ$4:$AJ$1277) -> 1297345.2 | BM15: Denmark | BN15: =SUMIF($F$4:$F$1277,$BM15,$Z$4:$Z$1277) -> 40816.131 | BO15: =SUMIF($F$4:$F$1277,$BM15,$AB$4:$AB$1277) -> 138539.12 | BP15: =SUMIF($F$4:$F$1277,$BM15,$AD$4:$AD$1277) -> 391860.74 | BQ15: =SUMIF($F$4:$F$1277,$BM15,$AF$4:$AF$1277) -> 886708.91 | BR15: =SUMIF($F$4:$F$1277,$BM15,$AH$4:$AH$1277) -> 1337639.7 | BS15: =SUMIF($F$4:$F$1277,$BM15,$AJ$4:$AJ$1277) -> 1891770.6
A16: R013 | B16: LH | C16: Lufthansa | D16: Passenger | E16: FRA | F16: Germany | G16: EU | H16: CDG | I16: France | J16: EU | K16: international | L16: A320neo | M16: 3650 | N16: =M16/365 -> 10 | O16: 480 | P16: =M16*O16 -> 1752000 | Q16: =IFERROR(VLOOKUP(G16,SCENARIOS!$A$13:$E$18,2,0),0.025) -> 0.025 | R16: =IFERROR(VLOOKUP(L16,INPUTS!$A$107:$B$120,2,0),0.0082) -> 0.0039 | S16: =O16*R16 -> 1.872 | T16: =M16*S16 -> 6832.8 | U16: =T16/INPUTS!$B$7*1000 -> 8541000 | V16: =T16*INPUTS!$B$6 -> 21591.648 | W16: Yes | X16: Yes | Y16: =IFERROR(VLOOKUP(E16,INPUTS!$A$44:$B$103,2,0),0) -> 0.02 | Z16: =T16*Y16 -> 136.656 | AA16: =IFERROR(VLOOKUP(E16,INPUTS!$A$44:$C$103,3,0),SCENARIOS!$J$23) -> 0.06 | AB16: =$T16*AA16*(1+$Q16)^AB$2 -> 463.84116 | AC16: =IFERROR(VLOOKUP($E16,INPUTS!$A$44:$G$103,4,0),SCENARIOS!$K$23) -> 0.15 | AD16: =$T16*AC16*(1+$Q16)^AD$2 -> 1311.9843 | AE16: =IFERROR(VLOOKUP($E16,INPUTS!$A$44:$G$103,5,0),SCENARIOS!$L$23) -> 0.3 | AF16: =$T16*AE16*(1+$Q16)^AF$2 -> 2968.7795 | AG16: =IFERROR(VLOOKUP($E16,INPUTS!$A$44:$G$103,6,0),SCENARIOS!$M$23) -> 0.4 | AH16: =$T16*AG16*(1+$Q16)^AH$2 -> 4478.5354 | AI16: =IFERROR(VLOOKUP($E16,INPUTS!$A$44:$G$103,7,0),SCENARIOS!$N$23) -> 0.5 | AJ16: =$T16*AI16*(1+$Q16)^AJ$2 -> 6333.8146 | AL16: =IF(H16="MULTI","MULTI",IF(COUNTIFS($E$4:$E$1277,H16,$H$4:$H$1277,E16)>0,"Y","N")) -> N | AM16: =T16*((1+Q16)^25) -> 12667.629 | AT16: EU | AU16: =AU4/1000000 -> 0.76180207 | AV16: =AV4/1000000 -> 3.015007 | AW16: =AW4/1000000 -> 7.313783 | AX16: =AX4/1000000 -> 16.549748 | AY16: =AY4/1000000 -> 24.966028 | AZ16: =AZ4/1000000 -> 35.308461 | BC16: BGY | BD16: =SUMIF($E$4:$E$1277,$BC16,$Z$4:$Z$1277) -> 0 | BE16: =SUMIF($E$4:$E$1277,$BC16,$AB$4:$AB$1277) -> 0 | BF16: =SUMIF($E$4:$E$1277,$BC16,$AD$4:$AD$1277) -> 0 | BG16: =SUMIF($E$4:$E$1277,$BC16,$AF$4:$AF$1277) -> 0 | BH16: =SUMIF($E$4:$E$1277,$BC16,$AH$4:$AH$1277) -> 0 | BI16: =SUMIF($E$4:$E$1277,$BC16,$AJ$4:$AJ$1277) -> 0 | BM16: Egypt | BN16: =SUMIF($F$4:$F$1277,$BM16,$Z$4:$Z$1277) -> 0 | BO16: =SUMIF($F$4:$F$1277,$BM16,$AB$4:$AB$1277) -> 0 | BP16: =SUMIF($F$4:$F$1277,$BM16,$AD$4:$AD$1277) -> 0 | BQ16: =SUMIF($F$4:$F$1277,$BM16,$AF$4:$AF$1277) -> 0 | BR16: =SUMIF($F$4:$F$1277,$BM16,$AH$4:$AH$1277) -> 0 | BS16: =SUMIF($F$4:$F$1277,$BM16,$AJ$4:$AJ$1277) -> 0
A17: R014 | B17: BA | C17: British Airways | D17: Passenger | E17: LHR | F17: United Kingdom | G17: EU | H17: AMS | I17: Netherlands | J17: EU | K17: international | L17: A320neo | M17: 3650 | N17: =M17/365 -> 10 | O17: 370 | P17: =M17*O17 -> 1350500 | Q17: =IFERROR(VLOOKUP(G17,SCENARIOS!$A$13:$E$18,2,0),0.025) -> 0.025 | R17: =IFERROR(VLOOKUP(L17,INPUTS!$A$107:$B$120,2,0),0.0082) -> 0.0039 | S17: =O17*R17 -> 1.443 | T17: =M17*S17 -> 5266.95 | U17: =T17/INPUTS!$B$7*1000 -> 6583687.5 | V17: =T17*INPUTS!$B$6 -> 16643.562 | W17: Yes | X17: Yes | Y17: =IFERROR(VLOOKUP(E17,INPUTS!$A$44:$B$103,2,0),0) -> 0.02 | Z17: =T17*Y17 -> 105.339 | AA17: =IFERROR(VLOOKUP(E17,INPUTS!$A$44:$C$103,3,0),SCENARIOS!$J$23) -> 0.1 | AB17: =$T17*AA17*(1+$Q17)^AB$2 -> 595.90705 | AC17: =IFERROR(VLOOKUP($E17,INPUTS!$A$44:$G$103,4,0),SCENARIOS!$K$23) -> 0.15 | AD17: =$T17*AC17*(1+$Q17)^AD$2 -> 1011.3212 | AE17: =IFERROR(VLOOKUP($E17,INPUTS!$A$44:$G$103,5,0),SCENARIOS!$L$23) -> 0.3 | AF17: =$T17*AE17*(1+$Q17)^AF$2 -> 2288.4342 | AG17: =IFERROR(VLOOKUP($E17,INPUTS!$A$44:$G$103,6,0),SCENARIOS!$M$23) -> 0.4 | AH17: =$T17*AG17*(1+$Q17)^AH$2 -> 3452.2043 | AI17: =IFERROR(VLOOKUP($E17,INPUTS!$A$44:$G$103,7,0),SCENARIOS!$N$23) -> 0.5 | AJ17: =$T17*AI17*(1+$Q17)^AJ$2 -> 4882.3154 | AL17: =IF(H17="MULTI","MULTI",IF(COUNTIFS($E$4:$E$1277,H17,$H$4:$H$1277,E17)>0,"Y","N")) -> N | AM17: =T17*((1+Q17)^25) -> 9764.6309 | AT17: US | AU17: =AU5/1000000 -> 0.022105417 | AV17: =AV5/1000000 -> 0.146437 | AW17: =AW5/1000000 -> 0.53892759 | AX17: =AX5/1000000 -> 1.1900392 | AY17: =AY5/1000000 -> 1.9708492 | AZ17: =AZ5/1000000 -> 2.9013023 | BC17: BKK | BD17: =SUMIF($E$4:$E$1277,$BC17,$Z$4:$Z$1277) -> 0 | BE17: =SUMIF($E$4:$E$1277,$BC17,$AB$4:$AB$1277) -> 0 | BF17: =SUMIF($E$4:$E$1277,$BC17,$AD$4:$AD$1277) -> 0 | BG17: =SUMIF($E$4:$E$1277,$BC17,$AF$4:$AF$1277) -> 0 | BH17: =SUMIF($E$4:$E$1277,$BC17,$AH$4:$AH$1277) -> 0 | BI17: =SUMIF($E$4:$E$1277,$BC17,$AJ$4:$AJ$1277) -> 0 | BM17: Ethiopia | BN17: =SUMIF($F$4:$F$1277,$BM17,$Z$4:$Z$1277) -> 0 | BO17: =SUMIF($F$4:$F$1277,$BM17,$AB$4:$AB$1277) -> 0 | BP17: =SUMIF($F$4:$F$1277,$BM17,$AD$4:$AD$1277) -> 0 | BQ17: =SUMIF($F$4:$F$1277,$BM17,$AF$4:$AF$1277) -> 0 | BR17: =SUMIF($F$4:$F$1277,$BM17,$AH$4:$AH$1277) -> 0 | BS17: =SUMIF($F$4:$F$1277,$BM17,$AJ$4:$AJ$1277) -> 0
A18: R015 | AT18: APAC | AU18: =AU6/1000000 -> 0 | AV18: =AV6/1000000 -> 1.1975246 | AW18: =AW6/1000000 -> 2.8458993 | AX18: =AX6/1000000 -> 6.974002 | AY18: =AY6/1000000 -> 12.130968 | AZ18: =AZ6/1000000 -> 19.267748 | BC18: BOG | BD18: =SUMIF($E$4:$E$1277,$BC18,$Z$4:$Z$1277) -> 0 | BE18: =SUMIF($E$4:$E$1277,$BC18,$AB$4:$AB$1277) -> 0 | BF18: =SUMIF($E$4:$E$1277,$BC18,$AD$4:$AD$1277) -> 0 | BG18: =SUMIF($E$4:$E$1277,$BC18,$AF$4:$AF$1277) -> 0 | BH18: =SUMIF($E$4:$E$1277,$BC18,$AH$4:$AH$1277) -> 0 | BI18: =SUMIF($E$4:$E$1277,$BC18,$AJ$4:$AJ$1277) -> 0 | BM18: Finland | BN18: =SUMIF($F$4:$F$1277,$BM18,$Z$4:$Z$1277) -> 44270.503 | BO18: =SUMIF($F$4:$F$1277,$BM18,$AB$4:$AB$1277) -> 150264.03 | BP18: =SUMIF($F$4:$F$1277,$BM18,$AD$4:$AD$1277) -> 425024.9 | BQ18: =SUMIF($F$4:$F$1277,$BM18,$AF$4:$AF$1277) -> 961753.33 | BR18: =SUMIF($F$4:$F$1277,$BM18,$AH$4:$AH$1277) -> 1450847.5 | BS18: =SUMIF($F$4:$F$1277,$BM18,$AJ$4:$AJ$1277) -> 2051876
A19: R016 | AT19: MENA | AU19: =AU7/1000000 -> 0 | AV19: =AV7/1000000 -> 0 | AW19: =AW7/1000000 -> 0 | AX19: =AX7/1000000 -> 0 | AY19: =AY7/1000000 -> 0 | AZ19: =AZ7/1000000 -> 0 | BC19: BOM | BD19: =SUMIF($E$4:$E$1277,$BC19,$Z$4:$Z$1277) -> 0 | BE19: =SUMIF($E$4:$E$1277,$BC19,$AB$4:$AB$1277) -> 0 | BF19: =SUMIF($E$4:$E$1277,$BC19,$AD$4:$AD$1277) -> 0 | BG19: =SUMIF($E$4:$E$1277,$BC19,$AF$4:$AF$1277) -> 0 | BH19: =SUMIF($E$4:$E$1277,$BC19,$AH$4:$AH$1277) -> 0 | BI19: =SUMIF($E$4:$E$1277,$BC19,$AJ$4:$AJ$1277) -> 0 | BM19: France | BN19: =SUMIF($F$4:$F$1277,$BM19,$Z$4:$Z$1277) -> 44677.704 | BO19: =SUMIF($F$4:$F$1277,$BM19,$AB$4:$AB$1277) -> 151646.16 | BP19: =SUMIF($F$4:$F$1277,$BM19,$AD$4:$AD$1277) -> 428934.29 | BQ19: =SUMIF($F$4:$F$1277,$BM19,$AF$4:$AF$1277) -> 970599.55 | BR19: =SUMIF($F$4:$F$1277,$BM19,$AH$4:$AH$1277) -> 1464192.4 | BS19: =SUMIF($F$4:$F$1277,$BM19,$AJ$4:$AJ$1277) -> 2070749.1
A20: R017 | B20: UA | C20: United Airlines | D20: Passenger | E20: EWR | F20: United States | G20: US | H20: LHR | I20: United Kingdom | J20: EU | K20: international | L20: B777-300ER | M20: 1460 | N20: =M20/365 -> 4 | O20: 5570 | P20: =M20*O20 -> 8132200 | Q20: =IFERROR(VLOOKUP(G20,SCENARIOS!$A$13:$E$18,2,0),0.025) -> 0.02 | R20: =IFERROR(VLOOKUP(L20,INPUTS!$A$107:$B$120,2,0),0.0082) -> 0.0089 | S20: =O20*R20 -> 49.573 | T20: =M20*S20 -> 72376.58 | U20: =T20/INPUTS!$B$7*1000 -> 90470725 | V20: =T20*INPUTS!$B$6 -> 228709.99 | W20: Yes | X20: Yes | Y20: =IFERROR(VLOOKUP(E20,INPUTS!$A$44:$B$103,2,0),0) -> 0.005 | Z20: =T20*Y20 -> 361.8829 | AA20: =IFERROR(VLOOKUP(E20,INPUTS!$A$44:$C$103,3,0),SCENARIOS!$J$23) -> 0.03 | AB20: =$T20*AA20*(1+$Q20)^AB$2 -> 2397.2878 | AC20: =IFERROR(VLOOKUP($E20,INPUTS!$A$44:$G$103,4,0),SCENARIOS!$K$23) -> 0.1 | AD20: =$T20*AC20*(1+$Q20)^AD$2 -> 8822.6647 | AE20: =IFERROR(VLOOKUP($E20,INPUTS!$A$44:$G$103,5,0),SCENARIOS!$L$23) -> 0.2 | AF20: =$T20*AE20*(1+$Q20)^AF$2 -> 19481.869 | AG20: =IFERROR(VLOOKUP($E20,INPUTS!$A$44:$G$103,6,0),SCENARIOS!$M$23) -> 0.3 | AH20: =$T20*AG20*(1+$Q20)^AH$2 -> 32264.337 | AI20: =IFERROR(VLOOKUP($E20,INPUTS!$A$44:$G$103,7,0),SCENARIOS!$N$23) -> 0.4 | AJ20: =$T20*AI20*(1+$Q20)^AJ$2 -> 47496.58 | AL20: =IF(H20="MULTI","MULTI",IF(COUNTIFS($E$4:$E$1277,H20,$H$4:$H$1277,E20)>0,"Y","N")) -> N | AM20: =T20*((1+Q20)^25) -> 118741.45 | AT20: LATAM | AU20: =AU8/1000000 -> 0 | AV20: =AV8/1000000 -> 0 | AW20: =AW8/1000000 -> 0 | AX20: =AX8/1000000 -> 0 | AY20: =AY8/1000000 -> 0 | AZ20: =AZ8/1000000 -> 0 | BC20: BOS | BD20: =SUMIF($E$4:$E$1277,$BC20,$Z$4:$Z$1277) -> 519.32917 | BE20: =SUMIF($E$4:$E$1277,$BC20,$AB$4:$AB$1277) -> 3440.2882 | BF20: =SUMIF($E$4:$E$1277,$BC20,$AD$4:$AD$1277) -> 12661.187 | BG20: =SUMIF($E$4:$E$1277,$BC20,$AF$4:$AF$1277) -> 27957.948 | BH20: =SUMIF($E$4:$E$1277,$BC20,$AH$4:$AH$1277) -> 46301.75 | BI20: =SUMIF($E$4:$E$1277,$BC20,$AJ$4:$AJ$1277) -> 68161.165 | BM20: Germany | BN20: =SUMIF($F$4:$F$1277,$BM20,$Z$4:$Z$1277) -> 28406.006 | BO20: =SUMIF($F$4:$F$1277,$BM20,$AB$4:$AB$1277) -> 96416.365 | BP20: =SUMIF($F$4:$F$1277,$BM20,$AD$4:$AD$1277) -> 272715.67 | BQ20: =SUMIF($F$4:$F$1277,$BM20,$AF$4:$AF$1277) -> 617105.49 | BR20: =SUMIF($F$4:$F$1277,$BM20,$AH$4:$AH$1277) -> 930930.96 | BS20: =SUMIF($F$4:$F$1277,$BM20,$AJ$4:$AJ$1277) -> 1316578.7
A21: R018 | B21: UA | C21: United Airlines | D21: Passenger | E21: ORD | F21: United States | G21: US | H21: NRT | I21: Japan | J21: APAC | K21: international | L21: B787-9 | M21: 730 | N21: =M21/365 -> 2 | O21: 10130 | P21: =M21*O21 -> 7394900 | Q21: =IFERROR(VLOOKUP(G21,SCENARIOS!$A$13:$E$18,2,0),0.025) -> 0.02 | R21: =IFERROR(VLOOKUP(L21,INPUTS!$A$107:$B$120,2,0),0.0082) -> 0.0079 | S21: =O21*R21 -> 80.027 | T21: =M21*S21 -> 58419.71 | U21: =T21/INPUTS!$B$7*1000 -> 73024638 | V21: =T21*INPUTS!$B$6 -> 184606.28 | W21: Yes | X21: Yes | Y21: =IFERROR(VLOOKUP(E21,INPUTS!$A$44:$B$103,2,0),0) -> 0.005 | Z21: =T21*Y21 -> 292.09855 | AA21: =IFERROR(VLOOKUP(E21,INPUTS!$A$44:$C$103,3,0),SCENARIOS!$J$23) -> 0.03 | AB21: =$T21*AA21*(1+$Q21)^AB$2 -> 1935.0024 | AC21: =IFERROR(VLOOKUP($E21,INPUTS!$A$44:$G$103,4,0),SCENARIOS!$K$23) -> 0.1 | AD21: =$T21*AC21*(1+$Q21)^AD$2 -> 7121.3301 | AE21: =IFERROR(VLOOKUP($E21,INPUTS!$A$44:$G$103,5,0),SCENARIOS!$L$23) -> 0.2 | AF21: =$T21*AE21*(1+$Q21)^AF$2 -> 15725.048 | AG21: =IFERROR(VLOOKUP($E21,INPUTS!$A$44:$G$103,6,0),SCENARIOS!$M$23) -> 0.3 | AH21: =$T21*AG21*(1+$Q21)^AH$2 -> 26042.585 | AI21: =IFERROR(VLOOKUP($E21,INPUTS!$A$44:$G$103,7,0),SCENARIOS!$N$23) -> 0.4 | AJ21: =$T21*AI21*(1+$Q21)^AJ$2 -> 38337.491 | AL21: =IF(H21="MULTI","MULTI",IF(COUNTIFS($E$4:$E$1277,H21,$H$4:$H$1277,E21)>0,"Y","N")) -> Y | AM21: =T21*((1+Q21)^25) -> 95843.726 | AT21: ROW | AU21: =AU9/1000000 -> 0 | AV21: =AV9/1000000 -> 0 | AW21: =AW9/1000000 -> 0 | AX21: =AX9/1000000 -> 0 | AY21: =AY9/1000000 -> 0 | AZ21: =AZ9/1000000 -> 0 | BC21: BRS | BD21: =SUMIF($E$4:$E$1277,$BC21,$Z$4:$Z$1277) -> 0 | BE21: =SUMIF($E$4:$E$1277,$BC21,$AB$4:$AB$1277) -> 0 | BF21: =SUMIF($E$4:$E$1277,$BC21,$AD$4:$AD$1277) -> 0 | BG21: =SUMIF($E$4:$E$1277,$BC21,$AF$4:$AF$1277) -> 0 | BH21: =SUMIF($E$4:$E$1277,$BC21,$AH$4:$AH$1277) -> 0 | BI21: =SUMIF($E$4:$E$1277,$BC21,$AJ$4:$AJ$1277) -> 0 | BM21: Greece | BN21: =SUMIF($F$4:$F$1277,$BM21,$Z$4:$Z$1277) -> 2623.5186 | BO21: =SUMIF($F$4:$F$1277,$BM21,$AB$4:$AB$1277) -> 8904.8115 | BP21: =SUMIF($F$4:$F$1277,$BM21,$AD$4:$AD$1277) -> 25187.442 | BQ21: =SUMIF($F$4:$F$1277,$BM21,$AF$4:$AF$1277) -> 56994.558 | BR21: =SUMIF($F$4:$F$1277,$BM21,$AH$4:$AH$1277) -> 85978.814 | BS21: =SUMIF($F$4:$F$1277,$BM21,$AJ$4:$AJ$1277) -> 121596.42
A22: R019 | B22: AA | C22: American Airlines | D22: Passenger | E22: DFW | F22: United States | G22: US | H22: LHR | I22: United Kingdom | J22: EU | K22: international | L22: B777-300ER | M22: 730 | N22: =M22/365 -> 2 | O22: 7640 | P22: =M22*O22 -> 5577200 | Q22: =IFERROR(VLOOKUP(G22,SCENARIOS!$A$13:$E$18,2,0),0.025) -> 0.02 | R22: =IFERROR(VLOOKUP(L22,INPUTS!$A$107:$B$120,2,0),0.0082) -> 0.0089 | S22: =O22*R22 -> 67.996 | T22: =M22*S22 -> 49637.08 | U22: =T22/INPUTS!$B$7*1000 -> 62046350 | V22: =T22*INPUTS!$B$6 -> 156853.17 | W22: Yes | X22: Yes | Y22: =IFERROR(VLOOKUP(E22,INPUTS!$A$44:$B$103,2,0),0) -> 0.005 | Z22: =T22*Y22 -> 248.1854 | AA22: =IFERROR(VLOOKUP(E22,INPUTS!$A$44:$C$103,3,0),SCENARIOS!$J$23) -> 0.03 | AB22: =$T22*AA22*(1+$Q22)^AB$2 -> 1644.1004 | AC22: =IFERROR(VLOOKUP($E22,INPUTS!$A$44:$G$103,4,0),SCENARIOS!$K$23) -> 0.1 | AD22: =$T22*AC22*(1+$Q22)^AD$2 -> 6050.7324 | AE22: =IFERROR(VLOOKUP($E22,INPUTS!$A$44:$G$103,5,0),SCENARIOS!$L$23) -> 0.2 | AF22: =$T22*AE22*(1+$Q22)^AF$2 -> 13360.995 | AG22: =IFERROR(VLOOKUP($E22,INPUTS!$A$44:$G$103,6,0),SCENARIOS!$M$23) -> 0.3 | AH22: =$T22*AG22*(1+$Q22)^AH$2 -> 22127.427 | AI22: =IFERROR(VLOOKUP($E22,INPUTS!$A$44:$G$103,7,0),SCENARIOS!$N$23) -> 0.4 | AJ22: =$T22*AI22*(1+$Q22)^AJ$2 -> 32573.956 | AL22: =IF(H22="MULTI","MULTI",IF(COUNTIFS($E$4:$E$1277,H22,$H$4:$H$1277,E22)>0,"Y","N")) -> N | AM22: =T22*((1+Q22)^25) -> 81434.891 | BC22: BRU | BD22: =SUMIF($E$4:$E$1277,$BC22,$Z$4:$Z$1277) -> 3959.6358 | BE22: =SUMIF($E$4:$E$1277,$BC22,$AB$4:$AB$1277) -> 13439.893 | BF22: =SUMIF($E$4:$E$1277,$BC22,$AD$4:$AD$1277) -> 38015.014 | BG22: =SUMIF($E$4:$E$1277,$BC22,$AF$4:$AF$1277) -> 86020.999 | BH22: =SUMIF($E$4:$E$1277,$BC22,$AH$4:$AH$1277) -> 129766.49 | BI22: =SUMIF($E$4:$E$1277,$BC22,$AJ$4:$AJ$1277) -> 183523.59 | BM22: Hong Kong | BN22: =SUMIF($F$4:$F$1277,$BM22,$Z$4:$Z$1277) -> 0 | BO22: =SUMIF($F$4:$F$1277,$BM22,$AB$4:$AB$1277) -> 0 | BP22: =SUMIF($F$4:$F$1277,$BM22,$AD$4:$AD$1277) -> 0 | BQ22: =SUMIF($F$4:$F$1277,$BM22,$AF$4:$AF$1277) -> 0 | BR22: =SUMIF($F$4:$F$1277,$BM22,$AH$4:$AH$1277) -> 0 | BS22: =SUMIF($F$4:$F$1277,$BM22,$AJ$4:$AJ$1277) -> 0
A23: R020 | B23: AA | C23: American Airlines | D23: Passenger | E23: JFK | F23: United States | G23: US | H23: CDG | I23: France | J23: EU | K23: international | L23: B787-9 | M23: 730 | N23: =M23/365 -> 2 | O23: 5850 | P23: =M23*O23 -> 4270500 | Q23: =IFERROR(VLOOKUP(G23,SCENARIOS!$A$13:$E$18,2,0),0.025) -> 0.02 | R23: =IFERROR(VLOOKUP(L23,INPUTS!$A$107:$B$120,2,0),0.0082) -> 0.0079 | S23: =O23*R23 -> 46.215 | T23: =M23*S23 -> 33736.95 | U23: =T23/INPUTS!$B$7*1000 -> 42171188 | V23: =T23*INPUTS!$B$6 -> 106608.76 | W23: Yes | X23: Yes | Y23: =IFERROR(VLOOKUP(E23,INPUTS!$A$44:$B$103,2,0),0) -> 0.005 | Z23: =T23*Y23 -> 168.68475 | AA23: =IFERROR(VLOOKUP(E23,INPUTS!$A$44:$C$103,3,0),SCENARIOS!$J$23) -> 0.03 | AB23: =$T23*AA23*(1+$Q23)^AB$2 -> 1117.4496 | AC23: =IFERROR(VLOOKUP($E23,INPUTS!$A$44:$G$103,4,0),SCENARIOS!$K$23) -> 0.1 | AD23: =$T23*AC23*(1+$Q23)^AD$2 -> 4112.5154 | AE23: =IFERROR(VLOOKUP($E23,INPUTS!$A$44:$G$103,5,0),SCENARIOS!$L$23) -> 0.2 | AF23: =$T23*AE23*(1+$Q23)^AF$2 -> 9081.0986 | AG23: =IFERROR(VLOOKUP($E23,INPUTS!$A$44:$G$103,6,0),SCENARIOS!$M$23) -> 0.3 | AH23: =$T23*AG23*(1+$Q23)^AH$2 -> 15039.4 | AI23: =IFERROR(VLOOKUP($E23,INPUTS!$A$44:$G$103,7,0),SCENARIOS!$N$23) -> 0.4 | AJ23: =$T23*AI23*(1+$Q23)^AJ$2 -> 22139.617 | AL23: =IF(H23="MULTI","MULTI",IF(COUNTIFS($E$4:$E$1277,H23,$H$4:$H$1277,E23)>0,"Y","N")) -> Y | AM23: =T23*((1+Q23)^25) -> 55349.042 | AT23: Total | AU23: =SUM(AU16:AU21) -> 0.78390749 | AV23: =SUM(AV16:AV21) -> 4.3589686 | AW23: =SUM(AW16:AW21) -> 10.69861 | AX23: =SUM(AX16:AX21) -> 24.713789 | AY23: =SUM(AY16:AY21) -> 39.067846 | AZ23: =SUM(AZ16:AZ21) -> 57.477512 | BC23: BSB | BD23: =SUMIF($E$4:$E$1277,$BC23,$Z$4:$Z$1277) -> 0 | BE23: =SUMIF($E$4:$E$1277,$BC23,$AB$4:$AB$1277) -> 0 | BF23: =SUMIF($E$4:$E$1277,$BC23,$AD$4:$AD$1277) -> 0 | BG23: =SUMIF($E$4:$E$1277,$BC23,$AF$4:$AF$1277) -> 0 | BH23: =SUMIF($E$4:$E$1277,$BC23,$AH$4:$AH$1277) -> 0 | BI23: =SUMIF($E$4:$E$1277,$BC23,$AJ$4:$AJ$1277) -> 0 | BM23: Hong Kong SAR | BN23: =SUMIF($F$4:$F$1277,$BM23,$Z$4:$Z$1277) -> 0 | BO23: =SUMIF($F$4:$F$1277,$BM23,$AB$4:$AB$1277) -> 0 | BP23: =SUMIF($F$4:$F$1277,$BM23,$AD$4:$AD$1277) -> 0 | BQ23: =SUMIF($F$4:$F$1277,$BM23,$AF$4:$AF$1277) -> 0 | BR23: =SUMIF($F$4:$F$1277,$BM23,$AH$4:$AH$1277) -> 0 | BS23: =SUMIF($F$4:$F$1277,$BM23,$AJ$4:$AJ$1277) -> 0
A24: R021 | B24: DL | C24: Delta Air Lines | D24: Passenger | E24: ATL | F24: United States | G24: US | H24: CDG | I24: France | J24: EU | K24: international | L24: A350-900 | M24: 365 | N24: =M24/365 -> 1 | O24: 7830 | P24: =M24*O24 -> 2857950 | Q24: =IFERROR(VLOOKUP(G24,SCENARIOS!$A$13:$E$18,2,0),0.025) -> 0.02 | R24: =IFERROR(VLOOKUP(L24,INPUTS!$A$107:$B$120,2,0),0.0082) -> 0.0079 | S24: =O24*R24 -> 61.857 | T24: =M24*S24 -> 22577.805 | U24: =T24/INPUTS!$B$7*1000 -> 28222256 | V24: =T24*INPUTS!$B$6 -> 71345.864 | W24: Yes | X24: Yes | Y24: =IFERROR(VLOOKUP(E24,INPUTS!$A$44:$B$103,2,0),0) -> 0.005 | Z24: =T24*Y24 -> 112.88903 | AA24: =IFERROR(VLOOKUP(E24,INPUTS!$A$44:$C$103,3,0),SCENARIOS!$J$23) -> 0.03 | AB24: =$T24*AA24*(1+$Q24)^AB$2 -> 747.83163 | AC24: =IFERROR(VLOOKUP($E24,INPUTS!$A$44:$G$103,4,0),SCENARIOS!$K$23) -> 0.1 | AD24: =$T24*AC24*(1+$Q24)^AD$2 -> 2752.2218 | AE24: =IFERROR(VLOOKUP($E24,INPUTS!$A$44:$G$103,5,0),SCENARIOS!$L$23) -> 0.2 | AF24: =$T24*AE24*(1+$Q24)^AF$2 -> 6077.3506 | AG24: =IFERROR(VLOOKUP($E24,INPUTS!$A$44:$G$103,6,0),SCENARIOS!$M$23) -> 0.3 | AH24: =$T24*AG24*(1+$Q24)^AH$2 -> 10064.829 | AI24: =IFERROR(VLOOKUP($E24,INPUTS!$A$44:$G$103,7,0),SCENARIOS!$N$23) -> 0.4 | AJ24: =$T24*AI24*(1+$Q24)^AJ$2 -> 14816.513 | AL24: =IF(H24="MULTI","MULTI",IF(COUNTIFS($E$4:$E$1277,H24,$H$4:$H$1277,E24)>0,"Y","N")) -> Y | AM24: =T24*((1+Q24)^25) -> 37041.282 | BC24: BUD | BD24: =SUMIF($E$4:$E$1277,$BC24,$Z$4:$Z$1277) -> 40888.612 | BE24: =SUMIF($E$4:$E$1277,$BC24,$AB$4:$AB$1277) -> 138785.13 | BF24: =SUMIF($E$4:$E$1277,$BC24,$AD$4:$AD$1277) -> 392556.6 | BG24: =SUMIF($E$4:$E$1277,$BC24,$AF$4:$AF$1277) -> 888283.52 | BH24: =SUMIF($E$4:$E$1277,$BC24,$AH$4:$AH$1277) -> 1340015 | BI24: =SUMIF($E$4:$E$1277,$BC24,$AJ$4:$AJ$1277) -> 1895130 | BM24: Hungary | BN24: =SUMIF($F$4:$F$1277,$BM24,$Z$4:$Z$1277) -> 40888.612 | BO24: =SUMIF($F$4:$F$1277,$BM24,$AB$4:$AB$1277) -> 138785.13 | BP24: =SUMIF($F$4:$F$1277,$BM24,$AD$4:$AD$1277) -> 392556.6 | BQ24: =SUMIF($F$4:$F$1277,$BM24,$AF$4:$AF$1277) -> 888283.52 | BR24: =SUMIF($F$4:$F$1277,$BM24,$AH$4:$AH$1277) -> 1340015 | BS24: =SUMIF($F$4:$F$1277,$BM24,$AJ$4:$AJ$1277) -> 1895130
A25: R022 | B25: DL | C25: Delta Air Lines | D25: Passenger | E25: JFK | F25: United States | G25: US | H25: NRT | I25: Japan | J25: APAC | K25: international | L25: B787-9 | M25: 730 | N25: =M25/365 -> 2 | O25: 10800 | P25: =M25*O25 -> 7884000 | Q25: =IFERROR(VLOOKUP(G25,SCENARIOS!$A$13:$E$18,2,0),0.025) -> 0.02 | R25: =IFERROR(VLOOKUP(L25,INPUTS!$A$107:$B$120,2,0),0.0082) -> 0.0079 | S25: =O25*R25 -> 85.32 | T25: =M25*S25 -> 62283.6 | U25: =T25/INPUTS!$B$7*1000 -> 77854500 | V25: =T25*INPUTS!$B$6 -> 196816.18 | W25: Yes | X25: Yes | Y25: =IFERROR(VLOOKUP(E25,INPUTS!$A$44:$B$103,2,0),0) -> 0.005 | Z25: =T25*Y25 -> 311.418 | AA25: =IFERROR(VLOOKUP(E25,INPUTS!$A$44:$C$103,3,0),SCENARIOS!$J$23) -> 0.03 | AB25: =$T25*AA25*(1+$Q25)^AB$2 -> 2062.9838 | AC25: =IFERROR(VLOOKUP($E25,INPUTS!$A$44:$G$103,4,0),SCENARIOS!$K$23) -> 0.1 | AD25: =$T25*AC25*(1+$Q25)^AD$2 -> 7592.3361 | AE25: =IFERROR(VLOOKUP($E25,INPUTS!$A$44:$G$103,5,0),SCENARIOS!$L$23) -> 0.2 | AF25: =$T25*AE25*(1+$Q25)^AF$2 -> 16765.105 | AG25: =IFERROR(VLOOKUP($E25,INPUTS!$A$44:$G$103,6,0),SCENARIOS!$M$23) -> 0.3 | AH25: =$T25*AG25*(1+$Q25)^AH$2 -> 27765.046 | AI25: =IFERROR(VLOOKUP($E25,INPUTS!$A$44:$G$103,7,0),SCENARIOS!$N$23) -> 0.4 | AJ25: =$T25*AI25*(1+$Q25)^AJ$2 -> 40873.139 | AL25: =IF(H25="MULTI","MULTI",IF(COUNTIFS($E$4:$E$1277,H25,$H$4:$H$1277,E25)>0,"Y","N")) -> Y | AM25: =T25*((1+Q25)^25) -> 102182.85 | BC25: CAI | BD25: =SUMIF($E$4:$E$1277,$BC25,$Z$4:$Z$1277) -> 0 | BE25: =SUMIF($E$4:$E$1277,$BC25,$AB$4:$AB$1277) -> 0 | BF25: =SUMIF($E$4:$E$1277,$BC25,$AD$4:$AD$1277) -> 0 | BG25: =SUMIF($E$4:$E$1277,$BC25,$AF$4:$AF$1277) -> 0 | BH25: =SUMIF($E$4:$E$1277,$BC25,$AH$4:$AH$1277) -> 0 | BI25: =SUMIF($E$4:$E$1277,$BC25,$AJ$4:$AJ$1277) -> 0 | BM25: Iceland | BN25: =SUMIF($F$4:$F$1277,$BM25,$Z$4:$Z$1277) -> 0 | BO25: =SUMIF($F$4:$F$1277,$BM25,$AB$4:$AB$1277) -> 0 | BP25: =SUMIF($F$4:$F$1277,$BM25,$AD$4:$AD$1277) -> 0 | BQ25: =SUMIF($F$4:$F$1277,$BM25,$AF$4:$AF$1277) -> 0 | BR25: =SUMIF($F$4:$F$1277,$BM25,$AH$4:$AH$1277) -> 0 | BS25: =SUMIF($F$4:$F$1277,$BM25,$AJ$4:$AJ$1277) -> 0
A26: R023 | B26: UA | C26: United Airlines | D26: Passenger | E26: EWR | F26: United States | G26: US | H26: DXB | I26: UAE | J26: MENA | K26: international | L26: B777-300ER | M26: 365 | N26: =M26/365 -> 1 | O26: 11560 | P26: =M26*O26 -> 4219400 | Q26: =IFERROR(VLOOKUP(G26,SCENARIOS!$A$13:$E$18,2,0),0.025) -> 0.02 | R26: =IFERROR(VLOOKUP(L26,INPUTS!$A$107:$B$120,2,0),0.0082) -> 0.0089 | S26: =O26*R26 -> 102.884 | T26: =M26*S26 -> 37552.66 | U26: =T26/INPUTS!$B$7*1000 -> 46940825 | V26: =T26*INPUTS!$B$6 -> 118666.41 | W26: Yes | X26: Yes | Y26: =IFERROR(VLOOKUP(E26,INPUTS!$A$44:$B$103,2,0),0) -> 0.005 | Z26: =T26*Y26 -> 187.7633 | AA26: =IFERROR(VLOOKUP(E26,INPUTS!$A$44:$C$103,3,0),SCENARIOS!$J$23) -> 0.03 | AB26: =$T26*AA26*(1+$Q26)^AB$2 -> 1243.8351 | AC26: =IFERROR(VLOOKUP($E26,INPUTS!$A$44:$G$103,4,0),SCENARIOS!$K$23) -> 0.1 | AD26: =$T26*AC26*(1+$Q26)^AD$2 -> 4577.6483 | AE26: =IFERROR(VLOOKUP($E26,INPUTS!$A$44:$G$103,5,0),SCENARIOS!$L$23) -> 0.2 | AF26: =$T26*AE26*(1+$Q26)^AF$2 -> 10108.187 | AG26: =IFERROR(VLOOKUP($E26,INPUTS!$A$44:$G$103,6,0),SCENARIOS!$M$23) -> 0.3 | AH26: =$T26*AG26*(1+$Q26)^AH$2 -> 16740.383 | AI26: =IFERROR(VLOOKUP($E26,INPUTS!$A$44:$G$103,7,0),SCENARIOS!$N$23) -> 0.4 | AJ26: =$T26*AI26*(1+$Q26)^AJ$2 -> 24643.648 | AL26: =IF(H26="MULTI","MULTI",IF(COUNTIFS($E$4:$E$1277,H26,$H$4:$H$1277,E26)>0,"Y","N")) -> N | AM26: =T26*((1+Q26)^25) -> 61609.119 | BC26: CAN | BD26: =SUMIF($E$4:$E$1277,$BC26,$Z$4:$Z$1277) -> 0 | BE26: =SUMIF($E$4:$E$1277,$BC26,$AB$4:$AB$1277) -> 0 | BF26: =SUMIF($E$4:$E$1277,$BC26,$AD$4:$AD$1277) -> 0 | BG26: =SUMIF($E$4:$E$1277,$BC26,$AF$4:$AF$1277) -> 0 | BH26: =SUMIF($E$4:$E$1277,$BC26,$AH$4:$AH$1277) -> 0 | BI26: =SUMIF($E$4:$E$1277,$BC26,$AJ$4:$AJ$1277) -> 0 | BM26: India | BN26: =SUMIF($F$4:$F$1277,$BM26,$Z$4:$Z$1277) -> 0 | BO26: =SUMIF($F$4:$F$1277,$BM26,$AB$4:$AB$1277) -> 0 | BP26: =SUMIF($F$4:$F$1277,$BM26,$AD$4:$AD$1277) -> 0 | BQ26: =SUMIF($F$4:$F$1277,$BM26,$AF$4:$AF$1277) -> 0 | BR26: =SUMIF($F$4:$F$1277,$BM26,$AH$4:$AH$1277) -> 0 | BS26: =SUMIF($F$4:$F$1277,$BM26,$AJ$4:$AJ$1277) -> 0
A27: R024 | AT27: Year | AU27: 2025 | AV27: 2030 | AW27: 2035 | AX27: 2040 | AY27: 2045 | AZ27: 2050 | BC27: CDG | BD27: =SUMIF($E$4:$E$1277,$BC27,$Z$4:$Z$1277) -> 44677.704 | BE27: =SUMIF($E$4:$E$1277,$BC27,$AB$4:$AB$1277) -> 151646.16 | BF27: =SUMIF($E$4:$E$1277,$BC27,$AD$4:$AD$1277) -> 428934.29 | BG27: =SUMIF($E$4:$E$1277,$BC27,$AF$4:$AF$1277) -> 970599.55 | BH27: =SUMIF($E$4:$E$1277,$BC27,$AH$4:$AH$1277) -> 1464192.4 | BI27: =SUMIF($E$4:$E$1277,$BC27,$AJ$4:$AJ$1277) -> 2070749.1 | BM27: Indonesia | BN27: =SUMIF($F$4:$F$1277,$BM27,$Z$4:$Z$1277) -> 0 | BO27: =SUMIF($F$4:$F$1277,$BM27,$AB$4:$AB$1277) -> 0 | BP27: =SUMIF($F$4:$F$1277,$BM27,$AD$4:$AD$1277) -> 0 | BQ27: =SUMIF($F$4:$F$1277,$BM27,$AF$4:$AF$1277) -> 0 | BR27: =SUMIF($F$4:$F$1277,$BM27,$AH$4:$AH$1277) -> 0 | BS27: =SUMIF($F$4:$F$1277,$BM27,$AJ$4:$AJ$1277) -> 0
A28: R025 | AT28: Global Jet Fuel Demand (Mt/yr) | AU28: 320 | AV28: 350 | AW28: 394 | AX28: 438 | AY28: 480 | AZ28: 525 | BC28: CGK | BD28: =SUMIF($E$4:$E$1277,$BC28,$Z$4:$Z$1277) -> 0 | BE28: =SUMIF($E$4:$E$1277,$BC28,$AB$4:$AB$1277) -> 0 | BF28: =SUMIF($E$4:$E$1277,$BC28,$AD$4:$AD$1277) -> 0 | BG28: =SUMIF($E$4:$E$1277,$BC28,$AF$4:$AF$1277) -> 0 | BH28: =SUMIF($E$4:$E$1277,$BC28,$AH$4:$AH$1277) -> 0 | BI28: =SUMIF($E$4:$E$1277,$BC28,$AJ$4:$AJ$1277) -> 0 | BM28: Ireland | BN28: =SUMIF($F$4:$F$1277,$BM28,$Z$4:$Z$1277) -> 29718.364 | BO28: =SUMIF($F$4:$F$1277,$BM28,$AB$4:$AB$1277) -> 100870.8 | BP28: =SUMIF($F$4:$F$1277,$BM28,$AD$4:$AD$1277) -> 285315.14 | BQ28: =SUMIF($F$4:$F$1277,$BM28,$AF$4:$AF$1277) -> 645615.79 | BR28: =SUMIF($F$4:$F$1277,$BM28,$AH$4:$AH$1277) -> 973940 | BS28: =SUMIF($F$4:$F$1277,$BM28,$AJ$4:$AJ$1277) -> 1377404.6
A29: R026 | AT29: Global SAF Supply (Mt/yr) | AU29: 1.9 | AV29: 10 | AW29: 42 | AX29: 100 | AY29: 175 | AZ29: 300 | BC29: CGN | BD29: =SUMIF($E$4:$E$1277,$BC29,$Z$4:$Z$1277) -> 0 | BE29: =SUMIF($E$4:$E$1277,$BC29,$AB$4:$AB$1277) -> 0 | BF29: =SUMIF($E$4:$E$1277,$BC29,$AD$4:$AD$1277) -> 0 | BG29: =SUMIF($E$4:$E$1277,$BC29,$AF$4:$AF$1277) -> 0 | BH29: =SUMIF($E$4:$E$1277,$BC29,$AH$4:$AH$1277) -> 0 | BI29: =SUMIF($E$4:$E$1277,$BC29,$AJ$4:$AJ$1277) -> 0 | BM29: Italy | BN29: =SUMIF($F$4:$F$1277,$BM29,$Z$4:$Z$1277) -> 22012.206 | BO29: =SUMIF($F$4:$F$1277,$BM29,$AB$4:$AB$1277) -> 74714.373 | BP29: =SUMIF($F$4:$F$1277,$BM29,$AD$4:$AD$1277) -> 211331.14 | BQ29: =SUMIF($F$4:$F$1277,$BM29,$AF$4:$AF$1277) -> 478203.57 | BR29: =SUMIF($F$4:$F$1277,$BM29,$AH$4:$AH$1277) -> 721391.26 | BS29: =SUMIF($F$4:$F$1277,$BM29,$AJ$4:$AJ$1277) -> 1020235
A30: R027 | B30: SQ | C30: Singapore Airlines | D30: Passenger | E30: SIN | F30: Singapore | G30: APAC | H30: LHR | I30: United Kingdom | J30: EU | K30: international | L30: A350-900 | M30: 730 | N30: =M30/365 -> 2 | O30: 10840 | P30: =M30*O30 -> 7913200 | Q30: =IFERROR(VLOOKUP(G30,SCENARIOS!$A$13:$E$18,2,0),0.025) -> 0.04 | R30: =IFERROR(VLOOKUP(L30,INPUTS!$A$107:$B$120,2,0),0.0082) -> 0.0079 | S30: =O30*R30 -> 85.636 | T30: =M30*S30 -> 62514.28 | U30: =T30/INPUTS!$B$7*1000 -> 78142850 | V30: =T30*INPUTS!$B$6 -> 197545.12 | W30: Yes | X30: Yes | Y30: =IFERROR(VLOOKUP(E30,INPUTS!$A$44:$B$103,2,0),0) -> 0 | Z30: =T30*Y30 -> 0 | AA30: =IFERROR(VLOOKUP(E30,INPUTS!$A$44:$C$103,3,0),SCENARIOS!$J$23) -> 0.03 | AB30: =$T30*AA30*(1+$Q30)^AB$2 -> 2281.7454 | AC30: =IFERROR(VLOOKUP($E30,INPUTS!$A$44:$G$103,4,0),SCENARIOS!$K$23) -> 0.1 | AD30: =$T30*AC30*(1+$Q30)^AD$2 -> 9253.6406 | AE30: =IFERROR(VLOOKUP($E30,INPUTS!$A$44:$G$103,5,0),SCENARIOS!$L$23) -> 0.2 | AF30: =$T30*AE30*(1+$Q30)^AF$2 -> 22516.937 | AG30: =IFERROR(VLOOKUP($E30,INPUTS!$A$44:$G$103,6,0),SCENARIOS!$M$23) -> 0.3 | AH30: =$T30*AG30*(1+$Q30)^AH$2 -> 41092.946 | AI30: =IFERROR(VLOOKUP($E30,INPUTS!$A$44:$G$103,7,0),SCENARIOS!$N$23) -> 0.4 | AJ30: =$T30*AI30*(1+$Q30)^AJ$2 -> 66661.136 | AL30: =IF(H30="MULTI","MULTI",IF(COUNTIFS($E$4:$E$1277,H30,$H$4:$H$1277,E30)>0,"Y","N")) -> Y | AM30: =T30*((1+Q30)^25) -> 166652.84 | BC30: CIA | BD30: =SUMIF($E$4:$E$1277,$BC30,$Z$4:$Z$1277) -> 0 | BE30: =SUMIF($E$4:$E$1277,$BC30,$AB$4:$AB$1277) -> 0 | BF30: =SUMIF($E$4:$E$1277,$BC30,$AD$4:$AD$1277) -> 0 | BG30: =SUMIF($E$4:$E$1277,$BC30,$AF$4:$AF$1277) -> 0 | BH30: =SUMIF($E$4:$E$1277,$BC30,$AH$4:$AH$1277) -> 0 | BI30: =SUMIF($E$4:$E$1277,$BC30,$AJ$4:$AJ$1277) -> 0 | BM30: Japan | BN30: =SUMIF($F$4:$F$1277,$BM30,$Z$4:$Z$1277) -> 0 | BO30: =SUMIF($F$4:$F$1277,$BM30,$AB$4:$AB$1277) -> 629223.07 | BP30: =SUMIF($F$4:$F$1277,$BM30,$AD$4:$AD$1277) -> 1148319.1 | BQ30: =SUMIF($F$4:$F$1277,$BM30,$AF$4:$AF$1277) -> 2794211.6 | BR30: =SUMIF($F$4:$F$1277,$BM30,$AH$4:$AH$1277) -> 4532780.8 | BS30: =SUMIF($F$4:$F$1277,$BM30,$AJ$4:$AJ$1277) -> 6893526.2
A31: R028 | B31: SQ | C31: Singapore Airlines | D31: Passenger | E31: SIN | F31: Singapore | G31: APAC | H31: JFK | I31: United States | J31: US | K31: international | L31: A350-900 | M31: 365 | N31: =M31/365 -> 1 | O31: 15340 | P31: =M31*O31 -> 5599100 | Q31: =IFERROR(VLOOKUP(G31,SCENARIOS!$A$13:$E$18,2,0),0.025) -> 0.04 | R31: =IFERROR(VLOOKUP(L31,INPUTS!$A$107:$B$120,2,0),0.0082) -> 0.0079 | S31: =O31*R31 -> 121.186 | T31: =M31*S31 -> 44232.89 | U31: =T31/INPUTS!$B$7*1000 -> 55291112 | V31: =T31*INPUTS!$B$6 -> 139775.93 | W31: Yes | X31: Yes | Y31: =IFERROR(VLOOKUP(E31,INPUTS!$A$44:$B$103,2,0),0) -> 0 | Z31: =T31*Y31 -> 0 | AA31: =IFERROR(VLOOKUP(E31,INPUTS!$A$44:$C$103,3,0),SCENARIOS!$J$23) -> 0.03 | AB31: =$T31*AA31*(1+$Q31)^AB$2 -> 1614.4822 | AC31: =IFERROR(VLOOKUP($E31,INPUTS!$A$44:$G$103,4,0),SCENARIOS!$K$23) -> 0.1 | AD31: =$T31*AC31*(1+$Q31)^AD$2 -> 6547.5483 | AE31: =IFERROR(VLOOKUP($E31,INPUTS!$A$44:$G$103,5,0),SCENARIOS!$L$23) -> 0.2 | AF31: =$T31*AE31*(1+$Q31)^AF$2 -> 15932.187 | AG31: =IFERROR(VLOOKUP($E31,INPUTS!$A$44:$G$103,6,0),SCENARIOS!$M$23) -> 0.3 | AH31: =$T31*AG31*(1+$Q31)^AH$2 -> 29075.913 | AI31: =IFERROR(VLOOKUP($E31,INPUTS!$A$44:$G$103,7,0),SCENARIOS!$N$23) -> 0.4 | AJ31: =$T31*AI31*(1+$Q31)^AJ$2 -> 47167.058 | AL31: =IF(H31="MULTI","MULTI",IF(COUNTIFS($E$4:$E$1277,H31,$H$4:$H$1277,E31)>0,"Y","N")) -> N | AM31: =T31*((1+Q31)^25) -> 117917.65 | AU31: =AU29/AU28 -> 0.0059375 | AV31: =AV29/AV28 -> 0.028571429 | AW31: =AW29/AW28 -> 0.10659898 | AX31: =AX29/AX28 -> 0.2283105 | AY31: =AY29/AY28 -> 0.36458333 | AZ31: =AZ29/AZ28 -> 0.57142857 | BC31: CMN | BD31: =SUMIF($E$4:$E$1277,$BC31,$Z$4:$Z$1277) -> 0 | BE31: =SUMIF($E$4:$E$1277,$BC31,$AB$4:$AB$1277) -> 0 | BF31: =SUMIF($E$4:$E$1277,$BC31,$AD$4:$AD$1277) -> 0 | BG31: =SUMIF($E$4:$E$1277,$BC31,$AF$4:$AF$1277) -> 0 | BH31: =SUMIF($E$4:$E$1277,$BC31,$AH$4:$AH$1277) -> 0 | BI31: =SUMIF($E$4:$E$1277,$BC31,$AJ$4:$AJ$1277) -> 0 | BM31: Jordan | BN31: =SUMIF($F$4:$F$1277,$BM31,$Z$4:$Z$1277) -> 0 | BO31: =SUMIF($F$4:$F$1277,$BM31,$AB$4:$AB$1277) -> 0 | BP31: =SUMIF($F$4:$F$1277,$BM31,$AD$4:$AD$1277) -> 0 | BQ31: =SUMIF($F$4:$F$1277,$BM31,$AF$4:$AF$1277) -> 0 | BR31: =SUMIF($F$4:$F$1277,$BM31,$AH$4:$AH$1277) -> 0 | BS31: =SUMIF($F$4:$F$1277,$BM31,$AJ$4:$AJ$1277) -> 0
A32: R029 | B32: NH | C32: ANA | D32: Passenger | E32: NRT | F32: Japan | G32: APAC | H32: LAX | I32: United States | J32: US | K32: international | L32: B777-300ER | M32: 1095 | N32: =M32/365 -> 3 | O32: 9570 | P32: =M32*O32 -> 10479150 | Q32: =IFERROR(VLOOKUP(G32,SCENARIOS!$A$13:$E$18,2,0),0.025) -> 0.04 | R32: =IFERROR(VLOOKUP(L32,INPUTS!$A$107:$B$120,2,0),0.0082) -> 0.0089 | S32: =O32*R32 -> 85.173 | T32: =M32*S32 -> 93264.435 | U32: =T32/INPUTS!$B$7*1000 -> 1.1658054e+08 | V32: =T32*INPUTS!$B$6 -> 294715.61 | W32: Yes | X32: Yes | Y32: =IFERROR(VLOOKUP(E32,INPUTS!$A$44:$B$103,2,0),0) -> 0 | Z32: =T32*Y32 -> 0 | AA32: =IFERROR(VLOOKUP(E32,INPUTS!$A$44:$C$103,3,0),SCENARIOS!$J$23) -> 0.1 | AB32: =$T32*AA32*(1+$Q32)^AB$2 -> 11347.045 | AC32: =IFERROR(VLOOKUP($E32,INPUTS!$A$44:$G$103,4,0),SCENARIOS!$K$23) -> 0.15 | AD32: =$T32*AC32*(1+$Q32)^AD$2 -> 20708.122 | AE32: =IFERROR(VLOOKUP($E32,INPUTS!$A$44:$G$103,5,0),SCENARIOS!$L$23) -> 0.3 | AF32: =$T32*AE32*(1+$Q32)^AF$2 -> 50389.194 | AG32: =IFERROR(VLOOKUP($E32,INPUTS!$A$44:$G$103,6,0),SCENARIOS!$M$23) -> 0.4 | AH32: =$T32*AG32*(1+$Q32)^AH$2 -> 81741.545 | AI32: =IFERROR(VLOOKUP($E32,INPUTS!$A$44:$G$103,7,0),SCENARIOS!$N$23) -> 0.5 | AJ32: =$T32*AI32*(1+$Q32)^AJ$2 -> 124313.86 | AL32: =IF(H32="MULTI","MULTI",IF(COUNTIFS($E$4:$E$1277,H32,$H$4:$H$1277,E32)>0,"Y","N")) -> Y | AM32: =T32*((1+Q32)^25) -> 248627.72 | BC32: COK | BD32: =SUMIF($E$4:$E$1277,$BC32,$Z$4:$Z$1277) -> 0 | BE32: =SUMIF($E$4:$E$1277,$BC32,$AB$4:$AB$1277) -> 0 | BF32: =SUMIF($E$4:$E$1277,$BC32,$AD$4:$AD$1277) -> 0 | BG32: =SUMIF($E$4:$E$1277,$BC32,$AF$4:$AF$1277) -> 0 | BH32: =SUMIF($E$4:$E$1277,$BC32,$AH$4:$AH$1277) -> 0 | BI32: =SUMIF($E$4:$E$1277,$BC32,$AJ$4:$AJ$1277) -> 0 | BM32: Kenya | BN32: =SUMIF($F$4:$F$1277,$BM32,$Z$4:$Z$1277) -> 0 | BO32: =SUMIF($F$4:$F$1277,$BM32,$AB$4:$AB$1277) -> 0 | BP32: =SUMIF($F$4:$F$1277,$BM32,$AD$4:$AD$1277) -> 0 | BQ32: =SUMIF($F$4:$F$1277,$BM32,$AF$4:$AF$1277) -> 0 | BR32: =SUMIF($F$4:$F$1277,$BM32,$AH$4:$AH$1277) -> 0 | BS32: =SUMIF($F$4:$F$1277,$BM32,$AJ$4:$AJ$1277) -> 0
A33: R030 | B33: NH | C33: ANA | D33: Passenger | E33: NRT | F33: Japan | G33: APAC | H33: LHR | I33: United Kingdom | J33: EU | K33: international | L33: B787-9 | M33: 730 | N33: =M33/365 -> 2 | O33: 9570 | P33: =M33*O33 -> 6986100 | Q33: =IFERROR(VLOOKUP(G33,SCENARIOS!$A$13:$E$18,2,0),0.025) -> 0.04 | R33: =IFERROR(VLOOKUP(L33,INPUTS!$A$107:$B$120,2,0),0.0082) -> 0.0079 | S33: =O33*R33 -> 75.603 | T33: =M33*S33 -> 55190.19 | U33: =T33/INPUTS!$B$7*1000 -> 68987738 | V33: =T33*INPUTS!$B$6 -> 174401 | W33: Yes | X33: Yes | Y33: =IFERROR(VLOOKUP(E33,INPUTS!$A$44:$B$103,2,0),0) -> 0 | Z33: =T33*Y33 -> 0 | AA33: =IFERROR(VLOOKUP(E33,INPUTS!$A$44:$C$103,3,0),SCENARIOS!$J$23) -> 0.1 | AB33: =$T33*AA33*(1+$Q33)^AB$2 -> 6714.7305 | AC33: =IFERROR(VLOOKUP($E33,INPUTS!$A$44:$G$103,4,0),SCENARIOS!$K$23) -> 0.15 | AD33: =$T33*AC33*(1+$Q33)^AD$2 -> 12254.244 | AE33: =IFERROR(VLOOKUP($E33,INPUTS!$A$44:$G$103,5,0),SCENARIOS!$L$23) -> 0.3 | AF33: =$T33*AE33*(1+$Q33)^AF$2 -> 29818.324 | AG33: =IFERROR(VLOOKUP($E33,INPUTS!$A$44:$G$103,6,0),SCENARIOS!$M$23) -> 0.4 | AH33: =$T33*AG33*(1+$Q33)^AH$2 -> 48371.401 | AI33: =IFERROR(VLOOKUP($E33,INPUTS!$A$44:$G$103,7,0),SCENARIOS!$N$23) -> 0.5 | AJ33: =$T33*AI33*(1+$Q33)^AJ$2 -> 73564.007 | AL33: =IF(H33="MULTI","MULTI",IF(COUNTIFS($E$4:$E$1277,H33,$H$4:$H$1277,E33)>0,"Y","N")) -> Y | AM33: =T33*((1+Q33)^25) -> 147128.01 | BC33: CPH | BD33: =SUMIF($E$4:$E$1277,$BC33,$Z$4:$Z$1277) -> 40816.131 | BE33: =SUMIF($E$4:$E$1277,$BC33,$AB$4:$AB$1277) -> 138539.12 | BF33: =SUMIF($E$4:$E$1277,$BC33,$AD$4:$AD$1277) -> 391860.74 | BG33: =SUMIF($E$4:$E$1277,$BC33,$AF$4:$AF$1277) -> 886708.91 | BH33: =SUMIF($E$4:$E$1277,$BC33,$AH$4:$AH$1277) -> 1337639.7 | BI33: =SUMIF($E$4:$E$1277,$BC33,$AJ$4:$AJ$1277) -> 1891770.6 | BM33: Kuwait | BN33: =SUMIF($F$4:$F$1277,$BM33,$Z$4:$Z$1277) -> 0 | BO33: =SUMIF($F$4:$F$1277,$BM33,$AB$4:$AB$1277) -> 0 | BP33: =SUMIF($F$4:$F$1277,$BM33,$AD$4:$AD$1277) -> 0 | BQ33: =SUMIF($F$4:$F$1277,$BM33,$AF$4:$AF$1277) -> 0 | BR33: =SUMIF($F$4:$F$1277,$BM33,$AH$4:$AH$1277) -> 0 | BS33: =SUMIF($F$4:$F$1277,$BM33,$AJ$4:$AJ$1277) -> 0
A34: R031 | B34: CX | C34: Cathay Pacific | D34: Passenger | E34: HKG | F34: Hong Kong | G34: APAC | H34: LHR | I34: United Kingdom | J34: EU | K34: international | L34: A350-900 | M34: 1095 | N34: =M34/365 -> 3 | O34: 9660 | P34: =M34*O34 -> 10577700 | Q34: =IFERROR(VLOOKUP(G34,SCENARIOS!$A$13:$E$18,2,0),0.025) -> 0.04 | R34: =IFERROR(VLOOKUP(L34,INPUTS!$A$107:$B$120,2,0),0.0082) -> 0.0079 | S34: =O34*R34 -> 76.314 | T34: =M34*S34 -> 83563.83 | U34: =T34/INPUTS!$B$7*1000 -> 1.0445479e+08 | V34: =T34*INPUTS!$B$6 -> 264061.7 | W34: Yes | X34: Yes | Y34: =IFERROR(VLOOKUP(E34,INPUTS!$A$44:$B$103,2,0),0) -> 0 | Z34: =T34*Y34 -> 0 | AA34: =IFERROR(VLOOKUP(E34,INPUTS!$A$44:$C$103,3,0),SCENARIOS!$J$23) -> 0 | AB34: =$T34*AA34*(1+$Q34)^AB$2 -> 0 | AC34: =IFERROR(VLOOKUP($E34,INPUTS!$A$44:$G$103,4,0),SCENARIOS!$K$23) -> 0 | AD34: =$T34*AC34*(1+$Q34)^AD$2 -> 0 | AE34: =IFERROR(VLOOKUP($E34,INPUTS!$A$44:$G$103,5,0),SCENARIOS!$L$23) -> 0 | AF34: =$T34*AE34*(1+$Q34)^AF$2 -> 0 | AG34: =IFERROR(VLOOKUP($E34,INPUTS!$A$44:$G$103,6,0),SCENARIOS!$M$23) -> 0 | AH34: =$T34*AG34*(1+$Q34)^AH$2 -> 0 | AI34: =IFERROR(VLOOKUP($E34,INPUTS!$A$44:$G$103,7,0),SCENARIOS!$N$23) -> 0 | AJ34: =$T34*AI34*(1+$Q34)^AJ$2 -> 0 | AL34: =IF(H34="MULTI","MULTI",IF(COUNTIFS($E$4:$E$1277,H34,$H$4:$H$1277,E34)>0,"Y","N")) -> Y | AM34: =T34*((1+Q34)^25) -> 222767.49 | AT34: Bottom-up jet fuel demand | BC34: CTU | BD34: =SUMIF($E$4:$E$1277,$BC34,$Z$4:$Z$1277) -> 0 | BE34: =SUMIF($E$4:$E$1277,$BC34,$AB$4:$AB$1277) -> 0 | BF34: =SUMIF($E$4:$E$1277,$BC34,$AD$4:$AD$1277) -> 0 | BG34: =SUMIF($E$4:$E$1277,$BC34,$AF$4:$AF$1277) -> 0 | BH34: =SUMIF($E$4:$E$1277,$BC34,$AH$4:$AH$1277) -> 0 | BI34: =SUMIF($E$4:$E$1277,$BC34,$AJ$4:$AJ$1277) -> 0 | BM34: Latvia | BN34: =SUMIF($F$4:$F$1277,$BM34,$Z$4:$Z$1277) -> 0 | BO34: =SUMIF($F$4:$F$1277,$BM34,$AB$4:$AB$1277) -> 0 | BP34: =SUMIF($F$4:$F$1277,$BM34,$AD$4:$AD$1277) -> 0 | BQ34: =SUMIF($F$4:$F$1277,$BM34,$AF$4:$AF$1277) -> 0 | BR34: =SUMIF($F$4:$F$1277,$BM34,$AH$4:$AH$1277) -> 0 | BS34: =SUMIF($F$4:$F$1277,$BM34,$AJ$4:$AJ$1277) -> 0
A35: R032 | B35: CA | C35: Air China | D35: Passenger | E35: PEK | F35: China | G35: APAC | H35: LHR | I35: United Kingdom | J35: EU | K35: international | L35: B777-300ER | M35: 730 | N35: =M35/365 -> 2 | O35: 8150 | P35: =M35*O35 -> 5949500 | Q35: =IFERROR(VLOOKUP(G35,SCENARIOS!$A$13:$E$18,2,0),0.025) -> 0.04 | R35: =IFERROR(VLOOKUP(L35,INPUTS!$A$107:$B$120,2,0),0.0082) -> 0.0089 | S35: =O35*R35 -> 72.535 | T35: =M35*S35 -> 52950.55 | U35: =T35/INPUTS!$B$7*1000 -> 66188188 | V35: =T35*INPUTS!$B$6 -> 167323.74 | W35: No | X35: Yes | Y35: =IFERROR(VLOOKUP(E35,INPUTS!$A$44:$B$103,2,0),0) -> 0 | Z35: =T35*Y35 -> 0 | AA35: =IFERROR(VLOOKUP(E35,INPUTS!$A$44:$C$103,3,0),SCENARIOS!$J$23) -> 0 | AB35: =$T35*AA35*(1+$Q35)^AB$2 -> 0 | AC35: =IFERROR(VLOOKUP($E35,INPUTS!$A$44:$G$103,4,0),SCENARIOS!$K$23) -> 0 | AD35: =$T35*AC35*(1+$Q35)^AD$2 -> 0 | AE35: =IFERROR(VLOOKUP($E35,INPUTS!$A$44:$G$103,5,0),SCENARIOS!$L$23) -> 0 | AF35: =$T35*AE35*(1+$Q35)^AF$2 -> 0 | AG35: =IFERROR(VLOOKUP($E35,INPUTS!$A$44:$G$103,6,0),SCENARIOS!$M$23) -> 0 | AH35: =$T35*AG35*(1+$Q35)^AH$2 -> 0 | AI35: =IFERROR(VLOOKUP($E35,INPUTS!$A$44:$G$103,7,0),SCENARIOS!$N$23) -> 0 | AJ35: =$T35*AI35*(1+$Q35)^AJ$2 -> 0 | AL35: =IF(H35="MULTI","MULTI",IF(COUNTIFS($E$4:$E$1277,H35,$H$4:$H$1277,E35)>0,"Y","N")) -> N | AM35: =T35*((1+Q35)^25) -> 141157.5 | AU35: 0 | AV35: =AU35+5 -> 5 | AW35: =AV35+5 -> 10 | AX35: =AW35+5 -> 15 | AY35: =AX35+5 -> 20 | AZ35: =AY35+5 -> 25 | BC35: CVG | BD35: =SUMIF($E$4:$E$1277,$BC35,$Z$4:$Z$1277) -> 0 | BE35: =SUMIF($E$4:$E$1277,$BC35,$AB$4:$AB$1277) -> 0 | BF35: =SUMIF($E$4:$E$1277,$BC35,$AD$4:$AD$1277) -> 0 | BG35: =SUMIF($E$4:$E$1277,$BC35,$AF$4:$AF$1277) -> 0 | BH35: =SUMIF($E$4:$E$1277,$BC35,$AH$4:$AH$1277) -> 0 | BI35: =SUMIF($E$4:$E$1277,$BC35,$AJ$4:$AJ$1277) -> 0 | BM35: Luxembourg | BN35: =SUMIF($F$4:$F$1277,$BM35,$Z$4:$Z$1277) -> 0 | BO35: =SUMIF($F$4:$F$1277,$BM35,$AB$4:$AB$1277) -> 0 | BP35: =SUMIF($F$4:$F$1277,$BM35,$AD$4:$AD$1277) -> 0 | BQ35: =SUMIF($F$4:$F$1277,$BM35,$AF$4:$AF$1277) -> 0 | BR35: =SUMIF($F$4:$F$1277,$BM35,$AH$4:$AH$1277) -> 0 | BS35: =SUMIF($F$4:$F$1277,$BM35,$AJ$4:$AJ$1277) -> 0
A36: R033 | B36: QF | C36: Qantas | D36: Passenger | E36: SYD | F36: Australia | G36: APAC | H36: LHR | I36: United Kingdom | J36: EU | K36: international | L36: B787-9 | M36: 365 | N36: =M36/365 -> 1 | O36: 16990 | P36: =M36*O36 -> 6201350 | Q36: =IFERROR(VLOOKUP(G36,SCENARIOS!$A$13:$E$18,2,0),0.025) -> 0.04 | R36: =IFERROR(VLOOKUP(L36,INPUTS!$A$107:$B$120,2,0),0.0082) -> 0.0079 | S36: =O36*R36 -> 134.221 | T36: =M36*S36 -> 48990.665 | U36: =T36/INPUTS!$B$7*1000 -> 61238331 | V36: =T36*INPUTS!$B$6 -> 154810.5 | W36: Yes | X36: Yes | Y36: =IFERROR(VLOOKUP(E36,INPUTS!$A$44:$B$103,2,0),0) -> 0 | Z36: =T36*Y36 -> 0 | AA36: =IFERROR(VLOOKUP(E36,INPUTS!$A$44:$C$103,3,0),SCENARIOS!$J$23) -> 0.05 | AB36: =$T36*AA36*(1+$Q36)^AB$2 -> 2980.2317 | AC36: =IFERROR(VLOOKUP($E36,INPUTS!$A$44:$G$103,4,0),SCENARIOS!$K$23) -> 0.1 | AD36: =$T36*AC36*(1+$Q36)^AD$2 -> 7251.8152 | AE36: =IFERROR(VLOOKUP($E36,INPUTS!$A$44:$G$103,5,0),SCENARIOS!$L$23) -> 0.2 | AF36: =$T36*AE36*(1+$Q36)^AF$2 -> 17645.884 | AG36: =IFERROR(VLOOKUP($E36,INPUTS!$A$44:$G$103,6,0),SCENARIOS!$M$23) -> 0.3 | AH36: =$T36*AG36*(1+$Q36)^AH$2 -> 32203.374 | AI36: =IFERROR(VLOOKUP($E36,INPUTS!$A$44:$G$103,7,0),SCENARIOS!$N$23) -> 0.4 | AJ36: =$T36*AI36*(1+$Q36)^AJ$2 -> 52240.438 | AL36: =IF(H36="MULTI","MULTI",IF(COUNTIFS($E$4:$E$1277,H36,$H$4:$H$1277,E36)>0,"Y","N")) -> Y | AM36: =T36*((1+Q36)^25) -> 130601.09 | AU36: 2025 | AV36: 2030 | AW36: 2035 | AX36: 2040 | AY36: 2045 | AZ36: 2050 | BC36: DAD | BD36: =SUMIF($E$4:$E$1277,$BC36,$Z$4:$Z$1277) -> 0 | BE36: =SUMIF($E$4:$E$1277,$BC36,$AB$4:$AB$1277) -> 0 | BF36: =SUMIF($E$4:$E$1277,$BC36,$AD$4:$AD$1277) -> 0 | BG36: =SUMIF($E$4:$E$1277,$BC36,$AF$4:$AF$1277) -> 0 | BH36: =SUMIF($E$4:$E$1277,$BC36,$AH$4:$AH$1277) -> 0 | BI36: =SUMIF($E$4:$E$1277,$BC36,$AJ$4:$AJ$1277) -> 0 | BM36: Malaysia | BN36: =SUMIF($F$4:$F$1277,$BM36,$Z$4:$Z$1277) -> 0 | BO36: =SUMIF($F$4:$F$1277,$BM36,$AB$4:$AB$1277) -> 0 | BP36: =SUMIF($F$4:$F$1277,$BM36,$AD$4:$AD$1277) -> 0 | BQ36: =SUMIF($F$4:$F$1277,$BM36,$AF$4:$AF$1277) -> 0 | BR36: =SUMIF($F$4:$F$1277,$BM36,$AH$4:$AH$1277) -> 0 | BS36: =SUMIF($F$4:$F$1277,$BM36,$AJ$4:$AJ$1277) -> 0
A37: R034 | B37: SQ | C37: Singapore Airlines | D37: Passenger | E37: SIN | F37: Singapore | G37: APAC | H37: DXB | I37: UAE | J37: MENA | K37: international | L37: A350-900 | M37: 1095 | N37: =M37/365 -> 3 | O37: 6350 | P37: =M37*O37 -> 6953250 | Q37: =IFERROR(VLOOKUP(G37,SCENARIOS!$A$13:$E$18,2,0),0.025) -> 0.04 | R37: =IFERROR(VLOOKUP(L37,INPUTS!$A$107:$B$120,2,0),0.0082) -> 0.0079 | S37: =O37*R37 -> 50.165 | T37: =M37*S37 -> 54930.675 | U37: =T37/INPUTS!$B$7*1000 -> 68663344 | V37: =T37*INPUTS!$B$6 -> 173580.93 | W37: Yes | X37: Yes | Y37: =IFERROR(VLOOKUP(E37,INPUTS!$A$44:$B$103,2,0),0) -> 0 | Z37: =T37*Y37 -> 0 | AA37: =IFERROR(VLOOKUP(E37,INPUTS!$A$44:$C$103,3,0),SCENARIOS!$J$23) -> 0.03 | AB37: =$T37*AA37*(1+$Q37)^AB$2 -> 2004.947 | AC37: =IFERROR(VLOOKUP($E37,INPUTS!$A$44:$G$103,4,0),SCENARIOS!$K$23) -> 0.1 | AD37: =$T37*AC37*(1+$Q37)^AD$2 -> 8131.0818 | AE37: =IFERROR(VLOOKUP($E37,INPUTS!$A$44:$G$103,5,0),SCENARIOS!$L$23) -> 0.2 | AF37: =$T37*AE37*(1+$Q37)^AF$2 -> 19785.408 | AG37: =IFERROR(VLOOKUP($E37,INPUTS!$A$44:$G$103,6,0),SCENARIOS!$M$23) -> 0.3 | AH37: =$T37*AG37*(1+$Q37)^AH$2 -> 36107.962 | AI37: =IFERROR(VLOOKUP($E37,INPUTS!$A$44:$G$103,7,0),SCENARIOS!$N$23) -> 0.4 | AJ37: =$T37*AI37*(1+$Q37)^AJ$2 -> 58574.476 | AL37: =IF(H37="MULTI","MULTI",IF(COUNTIFS($E$4:$E$1277,H37,$H$4:$H$1277,E37)>0,"Y","N")) -> Y | AM37: =T37*((1+Q37)^25) -> 146436.19 | AT37: EU | AU37: =SUMIF($G$4:$G$1277,$AT37,$T$4:$T$1277)*(1+SCENARIOS!$B13)^AU$35 -> 53878455 | AV37: =SUMIF($G$4:$G$1277,$AT37,$T$4:$T$1277)*(1+SCENARIOS!$B13)^AV$35 -> 60958527 | AW37: =SUMIF($G$4:$G$1277,$AT37,$T$4:$T$1277)*(1+SCENARIOS!$B13)^AW$35 -> 68968978 | AX37: =SUMIF($G$4:$G$1277,$AT37,$T$4:$T$1277)*(1+SCENARIOS!$B13)^AX$35 -> 78032068 | AY37: =SUMIF($G$4:$G$1277,$AT37,$T$4:$T$1277)*(1+SCENARIOS!$B13)^AY$35 -> 88286123 | AZ37: =SUMIF($G$4:$G$1277,$AT37,$T$4:$T$1277)*(1+SCENARIOS!$B13)^AZ$35 -> 99887644 | BC37: DAL | BD37: =SUMIF($E$4:$E$1277,$BC37,$Z$4:$Z$1277) -> 0 | BE37: =SUMIF($E$4:$E$1277,$BC37,$AB$4:$AB$1277) -> 0 | BF37: =SUMIF($E$4:$E$1277,$BC37,$AD$4:$AD$1277) -> 0 | BG37: =SUMIF($E$4:$E$1277,$BC37,$AF$4:$AF$1277) -> 0 | BH37: =SUMIF($E$4:$E$1277,$BC37,$AH$4:$AH$1277) -> 0 | BI37: =SUMIF($E$4:$E$1277,$BC37,$AJ$4:$AJ$1277) -> 0 | BM37: Mexico | BN37: =SUMIF($F$4:$F$1277,$BM37,$Z$4:$Z$1277) -> 0 | BO37: =SUMIF($F$4:$F$1277,$BM37,$AB$4:$AB$1277) -> 0 | BP37: =SUMIF($F$4:$F$1277,$BM37,$AD$4:$AD$1277) -> 0 | BQ37: =SUMIF($F$4:$F$1277,$BM37,$AF$4:$AF$1277) -> 0 | BR37: =SUMIF($F$4:$F$1277,$BM37,$AH$4:$AH$1277) -> 0 | BS37: =SUMIF($F$4:$F$1277,$BM37,$AJ$4:$AJ$1277) -> 0
A38: R035 | AT38: US | AU38: =SUMIF($G$4:$G$1277,$AT38,$T$4:$T$1277)*(1+SCENARIOS!$B14)^AU$35 -> 14640951 | AV38: =SUMIF($G$4:$G$1277,$AT38,$T$4:$T$1277)*(1+SCENARIOS!$B14)^AV$35 -> 16164792 | AW38: =SUMIF($G$4:$G$1277,$AT38,$T$4:$T$1277)*(1+SCENARIOS!$B14)^AW$35 -> 17847237 | AX38: =SUMIF($G$4:$G$1277,$AT38,$T$4:$T$1277)*(1+SCENARIOS!$B14)^AX$35 -> 19704792 | AY38: =SUMIF($G$4:$G$1277,$AT38,$T$4:$T$1277)*(1+SCENARIOS!$B14)^AY$35 -> 21755682 | AZ38: =SUMIF($G$4:$G$1277,$AT38,$T$4:$T$1277)*(1+SCENARIOS!$B14)^AZ$35 -> 24020031 | BC38: DEL | BD38: =SUMIF($E$4:$E$1277,$BC38,$Z$4:$Z$1277) -> 0 | BE38: =SUMIF($E$4:$E$1277,$BC38,$AB$4:$AB$1277) -> 0 | BF38: =SUMIF($E$4:$E$1277,$BC38,$AD$4:$AD$1277) -> 0 | BG38: =SUMIF($E$4:$E$1277,$BC38,$AF$4:$AF$1277) -> 0 | BH38: =SUMIF($E$4:$E$1277,$BC38,$AH$4:$AH$1277) -> 0 | BI38: =SUMIF($E$4:$E$1277,$BC38,$AJ$4:$AJ$1277) -> 0 | BM38: Morocco | BN38: =SUMIF($F$4:$F$1277,$BM38,$Z$4:$Z$1277) -> 0 | BO38: =SUMIF($F$4:$F$1277,$BM38,$AB$4:$AB$1277) -> 0 | BP38: =SUMIF($F$4:$F$1277,$BM38,$AD$4:$AD$1277) -> 0 | BQ38: =SUMIF($F$4:$F$1277,$BM38,$AF$4:$AF$1277) -> 0 | BR38: =SUMIF($F$4:$F$1277,$BM38,$AH$4:$AH$1277) -> 0 | BS38: =SUMIF($F$4:$F$1277,$BM38,$AJ$4:$AJ$1277) -> 0
A39: R036 | AT39: APAC | AU39: =SUMIF($G$4:$G$1277,$AT39,$T$4:$T$1277)*(1+SCENARIOS!$B15)^AU$35 -> 78584203 | AV39: =SUMIF($G$4:$G$1277,$AT39,$T$4:$T$1277)*(1+SCENARIOS!$B15)^AV$35 -> 95609699 | AW39: =SUMIF($G$4:$G$1277,$AT39,$T$4:$T$1277)*(1+SCENARIOS!$B15)^AW$35 -> 1.1632382e+08 | AX39: =SUMIF($G$4:$G$1277,$AT39,$T$4:$T$1277)*(1+SCENARIOS!$B15)^AX$35 -> 1.4152571e+08 | AY39: =SUMIF($G$4:$G$1277,$AT39,$T$4:$T$1277)*(1+SCENARIOS!$B15)^AY$35 -> 1.7218767e+08 | AZ39: =SUMIF($G$4:$G$1277,$AT39,$T$4:$T$1277)*(1+SCENARIOS!$B15)^AZ$35 -> 2.0949262e+08 | BC39: DEN | BD39: =SUMIF($E$4:$E$1277,$BC39,$Z$4:$Z$1277) -> 3432 | BE39: =SUMIF($E$4:$E$1277,$BC39,$AB$4:$AB$1277) -> 22735.232 | BF39: =SUMIF($E$4:$E$1277,$BC39,$AD$4:$AD$1277) -> 83671.777 | BG39: =SUMIF($E$4:$E$1277,$BC39,$AF$4:$AF$1277) -> 184760.81 | BH39: =SUMIF($E$4:$E$1277,$BC39,$AH$4:$AH$1277) -> 305986.29 | BI39: =SUMIF($E$4:$E$1277,$BC39,$AJ$4:$AJ$1277) -> 450444.78 | BM39: Netherlands | BN39: =SUMIF($F$4:$F$1277,$BM39,$Z$4:$Z$1277) -> 49783.248 | BO39: =SUMIF($F$4:$F$1277,$BM39,$AB$4:$AB$1277) -> 168975.53 | BP39: =SUMIF($F$4:$F$1277,$BM39,$AD$4:$AD$1277) -> 477950.75 | BQ39: =SUMIF($F$4:$F$1277,$BM39,$AF$4:$AF$1277) -> 1081514.8 | BR39: =SUMIF($F$4:$F$1277,$BM39,$AH$4:$AH$1277) -> 1631513 | BS39: =SUMIF($F$4:$F$1277,$BM39,$AJ$4:$AJ$1277) -> 2307384
A40: R037 | B40: EK | C40: Emirates | D40: Passenger | E40: DXB | F40: UAE | G40: MENA | H40: LHR | I40: United Kingdom | J40: EU | K40: international | L40: A380-800 | M40: 2190 | N40: =M40/365 -> 6 | O40: 5490 | P40: =M40*O40 -> 12023100 | Q40: =IFERROR(VLOOKUP(G40,SCENARIOS!$A$13:$E$18,2,0),0.025) -> 0.045 | R40: =IFERROR(VLOOKUP(L40,INPUTS!$A$107:$B$120,2,0),0.0082) -> 0.0105 | S40: =O40*R40 -> 57.645 | T40: =M40*S40 -> 126242.55 | U40: =T40/INPUTS!$B$7*1000 -> 1.5780319e+08 | V40: =T40*INPUTS!$B$6 -> 398926.46 | W40: Yes | X40: Yes | Y40: =IFERROR(VLOOKUP(E40,INPUTS!$A$44:$B$103,2,0),0) -> 0 | Z40: =T40*Y40 -> 0 | AA40: =IFERROR(VLOOKUP(E40,INPUTS!$A$44:$C$103,3,0),SCENARIOS!$J$23) -> 0 | AB40: =$T40*AA40*(1+$Q40)^AB$2 -> 0 | AC40: =IFERROR(VLOOKUP($E40,INPUTS!$A$44:$G$103,4,0),SCENARIOS!$K$23) -> 0 | AD40: =$T40*AC40*(1+$Q40)^AD$2 -> 0 | AE40: =IFERROR(VLOOKUP($E40,INPUTS!$A$44:$G$103,5,0),SCENARIOS!$L$23) -> 0 | AF40: =$T40*AE40*(1+$Q40)^AF$2 -> 0 | AG40: =IFERROR(VLOOKUP($E40,INPUTS!$A$44:$G$103,6,0),SCENARIOS!$M$23) -> 0 | AH40: =$T40*AG40*(1+$Q40)^AH$2 -> 0 | AI40: =IFERROR(VLOOKUP($E40,INPUTS!$A$44:$G$103,7,0),SCENARIOS!$N$23) -> 0 | AJ40: =$T40*AI40*(1+$Q40)^AJ$2 -> 0 | AL40: =IF(H40="MULTI","MULTI",IF(COUNTIFS($E$4:$E$1277,H40,$H$4:$H$1277,E40)>0,"Y","N")) -> Y | AM40: =T40*((1+Q40)^25) -> 379413.71 | AT40: MENA | AU40: =SUMIF($G$4:$G$1277,$AT40,$T$4:$T$1277)*(1+SCENARIOS!$B16)^AU$35 -> 11275125 | AV40: =SUMIF($G$4:$G$1277,$AT40,$T$4:$T$1277)*(1+SCENARIOS!$B16)^AV$35 -> 14050857 | AW40: =SUMIF($G$4:$G$1277,$AT40,$T$4:$T$1277)*(1+SCENARIOS!$B16)^AW$35 -> 17509924 | AX40: =SUMIF($G$4:$G$1277,$AT40,$T$4:$T$1277)*(1+SCENARIOS!$B16)^AX$35 -> 21820552 | AY40: =SUMIF($G$4:$G$1277,$AT40,$T$4:$T$1277)*(1+SCENARIOS!$B16)^AY$35 -> 27192377 | AZ40: =SUMIF($G$4:$G$1277,$AT40,$T$4:$T$1277)*(1+SCENARIOS!$B16)^AZ$35 -> 33886649 | BC40: DFW | BD40: =SUMIF($E$4:$E$1277,$BC40,$Z$4:$Z$1277) -> 1000.6069 | BE40: =SUMIF($E$4:$E$1277,$BC40,$AB$4:$AB$1277) -> 6628.5052 | BF40: =SUMIF($E$4:$E$1277,$BC40,$AD$4:$AD$1277) -> 24394.684 | BG40: =SUMIF($E$4:$E$1277,$BC40,$AF$4:$AF$1277) -> 53867.405 | BH40: =SUMIF($E$4:$E$1277,$BC40,$AH$4:$AH$1277) -> 89210.952 | BI40: =SUMIF($E$4:$E$1277,$BC40,$AJ$4:$AJ$1277) -> 131328.13 | BM40: New Zealand | BN40: =SUMIF($F$4:$F$1277,$BM40,$Z$4:$Z$1277) -> 0 | BO40: =SUMIF($F$4:$F$1277,$BM40,$AB$4:$AB$1277) -> 13256.928 | BP40: =SUMIF($F$4:$F$1277,$BM40,$AD$4:$AD$1277) -> 40322.699 | BQ40: =SUMIF($F$4:$F$1277,$BM40,$AF$4:$AF$1277) -> 147176.19 | BR40: =SUMIF($F$4:$F$1277,$BM40,$AH$4:$AH$1277) -> 238749.78 | BS40: =SUMIF($F$4:$F$1277,$BM40,$AJ$4:$AJ$1277) -> 435713.42
A41: R038 | B41: EK | C41: Emirates | D41: Passenger | E41: DXB | F41: UAE | G41: MENA | H41: JFK | I41: United States | J41: US | K41: international | L41: A380-800 | M41: 1460 | N41: =M41/365 -> 4 | O41: 11060 | P41: =M41*O41 -> 16147600 | Q41: =IFERROR(VLOOKUP(G41,SCENARIOS!$A$13:$E$18,2,0),0.025) -> 0.045 | R41: =IFERROR(VLOOKUP(L41,INPUTS!$A$107:$B$120,2,0),0.0082) -> 0.0105 | S41: =O41*R41 -> 116.13 | T41: =M41*S41 -> 169549.8 | U41: =T41/INPUTS!$B$7*1000 -> 211937250 | V41: =T41*INPUTS!$B$6 -> 535777.37 | W41: Yes | X41: Yes | Y41: =IFERROR(VLOOKUP(E41,INPUTS!$A$44:$B$103,2,0),0) -> 0 | Z41: =T41*Y41 -> 0 | AA41: =IFERROR(VLOOKUP(E41,INPUTS!$A$44:$C$103,3,0),SCENARIOS!$J$23) -> 0 | AB41: =$T41*AA41*(1+$Q41)^AB$2 -> 0 | AC41: =IFERROR(VLOOKUP($E41,INPUTS!$A$44:$G$103,4,0),SCENARIOS!$K$23) -> 0 | AD41: =$T41*AC41*(1+$Q41)^AD$2 -> 0 | AE41: =IFERROR(VLOOKUP($E41,INPUTS!$A$44:$G$103,5,0),SCENARIOS!$L$23) -> 0 | AF41: =$T41*AE41*(1+$Q41)^AF$2 -> 0 | AG41: =IFERROR(VLOOKUP($E41,INPUTS!$A$44:$G$103,6,0),SCENARIOS!$M$23) -> 0 | AH41: =$T41*AG41*(1+$Q41)^AH$2 -> 0 | AI41: =IFERROR(VLOOKUP($E41,INPUTS!$A$44:$G$103,7,0),SCENARIOS!$N$23) -> 0 | AJ41: =$T41*AI41*(1+$Q41)^AJ$2 -> 0 | AL41: =IF(H41="MULTI","MULTI",IF(COUNTIFS($E$4:$E$1277,H41,$H$4:$H$1277,E41)>0,"Y","N")) -> N | AM41: =T41*((1+Q41)^25) -> 509570.81 | AT41: LATAM | AU41: =SUMIF($G$4:$G$1277,$AT41,$T$4:$T$1277)*(1+SCENARIOS!$B17)^AU$35 -> 16099842 | AV41: =SUMIF($G$4:$G$1277,$AT41,$T$4:$T$1277)*(1+SCENARIOS!$B17)^AV$35 -> 19121562 | AW41: =SUMIF($G$4:$G$1277,$AT41,$T$4:$T$1277)*(1+SCENARIOS!$B17)^AW$35 -> 22710418 | AX41: =SUMIF($G$4:$G$1277,$AT41,$T$4:$T$1277)*(1+SCENARIOS!$B17)^AX$35 -> 26972852 | AY41: =SUMIF($G$4:$G$1277,$AT41,$T$4:$T$1277)*(1+SCENARIOS!$B17)^AY$35 -> 32035287 | AZ41: =SUMIF($G$4:$G$1277,$AT41,$T$4:$T$1277)*(1+SCENARIOS!$B17)^AZ$35 -> 38047871 | BC41: DMK | BD41: =SUMIF($E$4:$E$1277,$BC41,$Z$4:$Z$1277) -> 0 | BE41: =SUMIF($E$4:$E$1277,$BC41,$AB$4:$AB$1277) -> 0 | BF41: =SUMIF($E$4:$E$1277,$BC41,$AD$4:$AD$1277) -> 0 | BG41: =SUMIF($E$4:$E$1277,$BC41,$AF$4:$AF$1277) -> 0 | BH41: =SUMIF($E$4:$E$1277,$BC41,$AH$4:$AH$1277) -> 0 | BI41: =SUMIF($E$4:$E$1277,$BC41,$AJ$4:$AJ$1277) -> 0 | BM41: Norway | BN41: =SUMIF($F$4:$F$1277,$BM41,$Z$4:$Z$1277) -> 25978.549 | BO41: =SUMIF($F$4:$F$1277,$BM41,$AB$4:$AB$1277) -> 88177.029 | BP41: =SUMIF($F$4:$F$1277,$BM41,$AD$4:$AD$1277) -> 249410.54 | BQ41: =SUMIF($F$4:$F$1277,$BM41,$AF$4:$AF$1277) -> 564370.26 | BR41: =SUMIF($F$4:$F$1277,$BM41,$AH$4:$AH$1277) -> 851377.53 | BS41: =SUMIF($F$4:$F$1277,$BM41,$AJ$4:$AJ$1277) -> 1204069.4
A42: R039 | B42: EK | C42: Emirates | D42: Passenger | E42: DXB | F42: UAE | G42: MENA | H42: SYD | I42: Australia | J42: APAC | K42: international | L42: A380-800 | M42: 1095 | N42: =M42/365 -> 3 | O42: 12050 | P42: =M42*O42 -> 13194750 | Q42: =IFERROR(VLOOKUP(G42,SCENARIOS!$A$13:$E$18,2,0),0.025) -> 0.045 | R42: =IFERROR(VLOOKUP(L42,INPUTS!$A$107:$B$120,2,0),0.0082) -> 0.0105 | S42: =O42*R42 -> 126.525 | T42: =M42*S42 -> 138544.88 | U42: =T42/INPUTS!$B$7*1000 -> 1.7318109e+08 | V42: =T42*INPUTS!$B$6 -> 437801.8 | W42: Yes | X42: Yes | Y42: =IFERROR(VLOOKUP(E42,INPUTS!$A$44:$B$103,2,0),0) -> 0 | Z42: =T42*Y42 -> 0 | AA42: =IFERROR(VLOOKUP(E42,INPUTS!$A$44:$C$103,3,0),SCENARIOS!$J$23) -> 0 | AB42: =$T42*AA42*(1+$Q42)^AB$2 -> 0 | AC42: =IFERROR(VLOOKUP($E42,INPUTS!$A$44:$G$103,4,0),SCENARIOS!$K$23) -> 0 | AD42: =$T42*AC42*(1+$Q42)^AD$2 -> 0 | AE42: =IFERROR(VLOOKUP($E42,INPUTS!$A$44:$G$103,5,0),SCENARIOS!$L$23) -> 0 | AF42: =$T42*AE42*(1+$Q42)^AF$2 -> 0 | AG42: =IFERROR(VLOOKUP($E42,INPUTS!$A$44:$G$103,6,0),SCENARIOS!$M$23) -> 0 | AH42: =$T42*AG42*(1+$Q42)^AH$2 -> 0 | AI42: =IFERROR(VLOOKUP($E42,INPUTS!$A$44:$G$103,7,0),SCENARIOS!$N$23) -> 0 | AJ42: =$T42*AI42*(1+$Q42)^AJ$2 -> 0 | AL42: =IF(H42="MULTI","MULTI",IF(COUNTIFS($E$4:$E$1277,H42,$H$4:$H$1277,E42)>0,"Y","N")) -> Y | AM42: =T42*((1+Q42)^25) -> 416387.54 | AT42: ROW | AU42: =SUMIF($G$4:$G$1277,$AT42,$T$4:$T$1277)*(1+SCENARIOS!$B18)^AU$35 -> 3127682.1 | AV42: =SUMIF($G$4:$G$1277,$AT42,$T$4:$T$1277)*(1+SCENARIOS!$B18)^AV$35 -> 3625840.7 | AW42: =SUMIF($G$4:$G$1277,$AT42,$T$4:$T$1277)*(1+SCENARIOS!$B18)^AW$35 -> 4203343.2 | AX42: =SUMIF($G$4:$G$1277,$AT42,$T$4:$T$1277)*(1+SCENARIOS!$B18)^AX$35 -> 4872826.8 | AY42: =SUMIF($G$4:$G$1277,$AT42,$T$4:$T$1277)*(1+SCENARIOS!$B18)^AY$35 -> 5648941.7 | AZ42: =SUMIF($G$4:$G$1277,$AT42,$T$4:$T$1277)*(1+SCENARIOS!$B18)^AZ$35 -> 6548671.7 | BC42: DOH | BD42: =SUMIF($E$4:$E$1277,$BC42,$Z$4:$Z$1277) -> 0 | BE42: =SUMIF($E$4:$E$1277,$BC42,$AB$4:$AB$1277) -> 0 | BF42: =SUMIF($E$4:$E$1277,$BC42,$AD$4:$AD$1277) -> 0 | BG42: =SUMIF($E$4:$E$1277,$BC42,$AF$4:$AF$1277) -> 0 | BH42: =SUMIF($E$4:$E$1277,$BC42,$AH$4:$AH$1277) -> 0 | BI42: =SUMIF($E$4:$E$1277,$BC42,$AJ$4:$AJ$1277) -> 0 | BM42: Oman | BN42: =SUMIF($F$4:$F$1277,$BM42,$Z$4:$Z$1277) -> 0 | BO42: =SUMIF($F$4:$F$1277,$BM42,$AB$4:$AB$1277) -> 0 | BP42: =SUMIF($F$4:$F$1277,$BM42,$AD$4:$AD$1277) -> 0 | BQ42: =SUMIF($F$4:$F$1277,$BM42,$AF$4:$AF$1277) -> 0 | BR42: =SUMIF($F$4:$F$1277,$BM42,$AH$4:$AH$1277) -> 0 | BS42: =SUMIF($F$4:$F$1277,$BM42,$AJ$4:$AJ$1277) -> 0
A43: R040 | B43: QR | C43: Qatar Airways | D43: Passenger | E43: DOH | F43: Qatar | G43: MENA | H43: LHR | I43: United Kingdom | J43: EU | K43: international | L43: A350-900 | M43: 1825 | N43: =M43/365 -> 5 | O43: 5720 | P43: =M43*O43 -> 10439000 | Q43: =IFERROR(VLOOKUP(G43,SCENARIOS!$A$13:$E$18,2,0),0.025) -> 0.045 | R43: =IFERROR(VLOOKUP(L43,INPUTS!$A$107:$B$120,2,0),0.0082) -> 0.0079 | S43: =O43*R43 -> 45.188 | T43: =M43*S43 -> 82468.1 | U43: =T43/INPUTS!$B$7*1000 -> 103085125 | V43: =T43*INPUTS!$B$6 -> 260599.2 | W43: Yes | X43: Yes | Y43: =IFERROR(VLOOKUP(E43,INPUTS!$A$44:$B$103,2,0),0) -> 0 | Z43: =T43*Y43 -> 0 | AA43: =IFERROR(VLOOKUP(E43,INPUTS!$A$44:$C$103,3,0),SCENARIOS!$J$23) -> 0 | AB43: =$T43*AA43*(1+$Q43)^AB$2 -> 0 | AC43: =IFERROR(VLOOKUP($E43,INPUTS!$A$44:$G$103,4,0),SCENARIOS!$K$23) -> 0 | AD43: =$T43*AC43*(1+$Q43)^AD$2 -> 0 | AE43: =IFERROR(VLOOKUP($E43,INPUTS!$A$44:$G$103,5,0),SCENARIOS!$L$23) -> 0 | AF43: =$T43*AE43*(1+$Q43)^AF$2 -> 0 | AG43: =IFERROR(VLOOKUP($E43,INPUTS!$A$44:$G$103,6,0),SCENARIOS!$M$23) -> 0 | AH43: =$T43*AG43*(1+$Q43)^AH$2 -> 0 | AI43: =IFERROR(VLOOKUP($E43,INPUTS!$A$44:$G$103,7,0),SCENARIOS!$N$23) -> 0 | AJ43: =$T43*AI43*(1+$Q43)^AJ$2 -> 0 | AL43: =IF(H43="MULTI","MULTI",IF(COUNTIFS($E$4:$E$1277,H43,$H$4:$H$1277,E43)>0,"Y","N")) -> Y | AM43: =T43*((1+Q43)^25) -> 247852.47 | AT43: Total | AU43: =SUM(AU37:AU42) -> 1.7760626e+08 | AV43: =SUM(AV37:AV42) -> 2.0953128e+08 | AW43: =SUM(AW37:AW42) -> 2.4756372e+08 | AX43: =SUM(AX37:AX42) -> 2.929288e+08 | AY43: =SUM(AY37:AY42) -> 3.4710608e+08 | AZ43: =SUM(AZ37:AZ42) -> 4.1188349e+08 | BC43: DUB | BD43: =SUMIF($E$4:$E$1277,$BC43,$Z$4:$Z$1277) -> 29718.364 | BE43: =SUMIF($E$4:$E$1277,$BC43,$AB$4:$AB$1277) -> 100870.8 | BF43: =SUMIF($E$4:$E$1277,$BC43,$AD$4:$AD$1277) -> 285315.14 | BG43: =SUMIF($E$4:$E$1277,$BC43,$AF$4:$AF$1277) -> 645615.79 | BH43: =SUMIF($E$4:$E$1277,$BC43,$AH$4:$AH$1277) -> 973940 | BI43: =SUMIF($E$4:$E$1277,$BC43,$AJ$4:$AJ$1277) -> 1377404.6 | BM43: Panama | BN43: =SUMIF($F$4:$F$1277,$BM43,$Z$4:$Z$1277) -> 0 | BO43: =SUMIF($F$4:$F$1277,$BM43,$AB$4:$AB$1277) -> 0 | BP43: =SUMIF($F$4:$F$1277,$BM43,$AD$4:$AD$1277) -> 0 | BQ43: =SUMIF($F$4:$F$1277,$BM43,$AF$4:$AF$1277) -> 0 | BR43: =SUMIF($F$4:$F$1277,$BM43,$AH$4:$AH$1277) -> 0 | BS43: =SUMIF($F$4:$F$1277,$BM43,$AJ$4:$AJ$1277) -> 0
A44: R041 | B44: QR | C44: Qatar Airways | D44: Passenger | E44: DOH | F44: Qatar | G44: MENA | H44: JFK | I44: United States | J44: US | K44: international | L44: B777-300ER | M44: 730 | N44: =M44/365 -> 2 | O44: 11825 | P44: =M44*O44 -> 8632250 | Q44: =IFERROR(VLOOKUP(G44,SCENARIOS!$A$13:$E$18,2,0),0.025) -> 0.045 | R44: =IFERROR(VLOOKUP(L44,INPUTS!$A$107:$B$120,2,0),0.0082) -> 0.0089 | S44: =O44*R44 -> 105.2425 | T44: =M44*S44 -> 76827.025 | U44: =T44/INPUTS!$B$7*1000 -> 96033781 | V44: =T44*INPUTS!$B$6 -> 242773.4 | W44: Yes | X44: Yes | Y44: =IFERROR(VLOOKUP(E44,INPUTS!$A$44:$B$103,2,0),0) -> 0 | Z44: =T44*Y44 -> 0 | AA44: =IFERROR(VLOOKUP(E44,INPUTS!$A$44:$C$103,3,0),SCENARIOS!$J$23) -> 0 | AB44: =$T44*AA44*(1+$Q44)^AB$2 -> 0 | AC44: =IFERROR(VLOOKUP($E44,INPUTS!$A$44:$G$103,4,0),SCENARIOS!$K$23) -> 0 | AD44: =$T44*AC44*(1+$Q44)^AD$2 -> 0 | AE44: =IFERROR(VLOOKUP($E44,INPUTS!$A$44:$G$103,5,0),SCENARIOS!$L$23) -> 0 | AF44: =$T44*AE44*(1+$Q44)^AF$2 -> 0 | AG44: =IFERROR(VLOOKUP($E44,INPUTS!$A$44:$G$103,6,0),SCENARIOS!$M$23) -> 0 | AH44: =$T44*AG44*(1+$Q44)^AH$2 -> 0 | AI44: =IFERROR(VLOOKUP($E44,INPUTS!$A$44:$G$103,7,0),SCENARIOS!$N$23) -> 0 | AJ44: =$T44*AI44*(1+$Q44)^AJ$2 -> 0 | AL44: =IF(H44="MULTI","MULTI",IF(COUNTIFS($E$4:$E$1277,H44,$H$4:$H$1277,E44)>0,"Y","N")) -> N | AM44: =T44*((1+Q44)^25) -> 230898.59 | BC44: DUS | BD44: =SUMIF($E$4:$E$1277,$BC44,$Z$4:$Z$1277) -> 0 | BE44: =SUMIF($E$4:$E$1277,$BC44,$AB$4:$AB$1277) -> 0 | BF44: =SUMIF($E$4:$E$1277,$BC44,$AD$4:$AD$1277) -> 0 | BG44: =SUMIF($E$4:$E$1277,$BC44,$AF$4:$AF$1277) -> 0 | BH44: =SUMIF($E$4:$E$1277,$BC44,$AH$4:$AH$1277) -> 0 | BI44: =SUMIF($E$4:$E$1277,$BC44,$AJ$4:$AJ$1277) -> 0 | BM44: Peru | BN44: =SUMIF($F$4:$F$1277,$BM44,$Z$4:$Z$1277) -> 0 | BO44: =SUMIF($F$4:$F$1277,$BM44,$AB$4:$AB$1277) -> 0 | BP44: =SUMIF($F$4:$F$1277,$BM44,$AD$4:$AD$1277) -> 0 | BQ44: =SUMIF($F$4:$F$1277,$BM44,$AF$4:$AF$1277) -> 0 | BR44: =SUMIF($F$4:$F$1277,$BM44,$AH$4:$AH$1277) -> 0 | BS44: =SUMIF($F$4:$F$1277,$BM44,$AJ$4:$AJ$1277) -> 0
A45: R042 | B45: SV | C45: Saudia | D45: Passenger | E45: RUH | F45: Saudi Arabia | G45: MENA | H45: LHR | I45: United Kingdom | J45: EU | K45: international | L45: B787-9 | M45: 730 | N45: =M45/365 -> 2 | O45: 6760 | P45: =M45*O45 -> 4934800 | Q45: =IFERROR(VLOOKUP(G45,SCENARIOS!$A$13:$E$18,2,0),0.025) -> 0.045 | R45: =IFERROR(VLOOKUP(L45,INPUTS!$A$107:$B$120,2,0),0.0082) -> 0.0079 | S45: =O45*R45 -> 53.404 | T45: =M45*S45 -> 38984.92 | U45: =T45/INPUTS!$B$7*1000 -> 48731150 | V45: =T45*INPUTS!$B$6 -> 123192.35 | W45: Yes | X45: Yes | Y45: =IFERROR(VLOOKUP(E45,INPUTS!$A$44:$B$103,2,0),0) -> 0 | Z45: =T45*Y45 -> 0 | AA45: =IFERROR(VLOOKUP(E45,INPUTS!$A$44:$C$103,3,0),SCENARIOS!$J$23) -> 0 | AB45: =$T45*AA45*(1+$Q45)^AB$2 -> 0 | AC45: =IFERROR(VLOOKUP($E45,INPUTS!$A$44:$G$103,4,0),SCENARIOS!$K$23) -> 0 | AD45: =$T45*AC45*(1+$Q45)^AD$2 -> 0 | AE45: =IFERROR(VLOOKUP($E45,INPUTS!$A$44:$G$103,5,0),SCENARIOS!$L$23) -> 0 | AF45: =$T45*AE45*(1+$Q45)^AF$2 -> 0 | AG45: =IFERROR(VLOOKUP($E45,INPUTS!$A$44:$G$103,6,0),SCENARIOS!$M$23) -> 0 | AH45: =$T45*AG45*(1+$Q45)^AH$2 -> 0 | AI45: =IFERROR(VLOOKUP($E45,INPUTS!$A$44:$G$103,7,0),SCENARIOS!$N$23) -> 0 | AJ45: =$T45*AI45*(1+$Q45)^AJ$2 -> 0 | AL45: =IF(H45="MULTI","MULTI",IF(COUNTIFS($E$4:$E$1277,H45,$H$4:$H$1277,E45)>0,"Y","N")) -> Y | AM45: =T45*((1+Q45)^25) -> 117166.62 | AT45: % SAF | AU45: =AU11/AU43 -> 0.004413738 | AV45: =AV11/AV43 -> 0.020803427 | AW45: =AW11/AW43 -> 0.043215581 | AX45: =AX11/AX43 -> 0.084367906 | AY45: =AY11/AY43 -> 0.11255304 | AZ45: =AZ11/AZ43 -> 0.13954799 | BC45: DXB | BD45: =SUMIF($E$4:$E$1277,$BC45,$Z$4:$Z$1277) -> 0 | BE45: =SUMIF($E$4:$E$1277,$BC45,$AB$4:$AB$1277) -> 0 | BF45: =SUMIF($E$4:$E$1277,$BC45,$AD$4:$AD$1277) -> 0 | BG45: =SUMIF($E$4:$E$1277,$BC45,$AF$4:$AF$1277) -> 0 | BH45: =SUMIF($E$4:$E$1277,$BC45,$AH$4:$AH$1277) -> 0 | BI45: =SUMIF($E$4:$E$1277,$BC45,$AJ$4:$AJ$1277) -> 0 | BM45: Philippines | BN45: =SUMIF($F$4:$F$1277,$BM45,$Z$4:$Z$1277) -> 0 | BO45: =SUMIF($F$4:$F$1277,$BM45,$AB$4:$AB$1277) -> 0 | BP45: =SUMIF($F$4:$F$1277,$BM45,$AD$4:$AD$1277) -> 0 | BQ45: =SUMIF($F$4:$F$1277,$BM45,$AF$4:$AF$1277) -> 0 | BR45: =SUMIF($F$4:$F$1277,$BM45,$AH$4:$AH$1277) -> 0 | BS45: =SUMIF($F$4:$F$1277,$BM45,$AJ$4:$AJ$1277) -> 0
A46: R043 | B46: SV | C46: Saudia | D46: Passenger | E46: JED | F46: Saudi Arabia | G46: MENA | H46: JFK | I46: United States | J46: US | K46: international | L46: B787-9 | M46: 365 | N46: =M46/365 -> 1 | O46: 11430 | P46: =M46*O46 -> 4171950 | Q46: =IFERROR(VLOOKUP(G46,SCENARIOS!$A$13:$E$18,2,0),0.025) -> 0.045 | R46: =IFERROR(VLOOKUP(L46,INPUTS!$A$107:$B$120,2,0),0.0082) -> 0.0079 | S46: =O46*R46 -> 90.297 | T46: =M46*S46 -> 32958.405 | U46: =T46/INPUTS!$B$7*1000 -> 41198006 | V46: =T46*INPUTS!$B$6 -> 104148.56 | W46: Yes | X46: Yes | Y46: =IFERROR(VLOOKUP(E46,INPUTS!$A$44:$B$103,2,0),0) -> 0 | Z46: =T46*Y46 -> 0 | AA46: =IFERROR(VLOOKUP(E46,INPUTS!$A$44:$C$103,3,0),SCENARIOS!$J$23) -> 0 | AB46: =$T46*AA46*(1+$Q46)^AB$2 -> 0 | AC46: =IFERROR(VLOOKUP($E46,INPUTS!$A$44:$G$103,4,0),SCENARIOS!$K$23) -> 0 | AD46: =$T46*AC46*(1+$Q46)^AD$2 -> 0 | AE46: =IFERROR(VLOOKUP($E46,INPUTS!$A$44:$G$103,5,0),SCENARIOS!$L$23) -> 0 | AF46: =$T46*AE46*(1+$Q46)^AF$2 -> 0 | AG46: =IFERROR(VLOOKUP($E46,INPUTS!$A$44:$G$103,6,0),SCENARIOS!$M$23) -> 0 | AH46: =$T46*AG46*(1+$Q46)^AH$2 -> 0 | AI46: =IFERROR(VLOOKUP($E46,INPUTS!$A$44:$G$103,7,0),SCENARIOS!$N$23) -> 0 | AJ46: =$T46*AI46*(1+$Q46)^AJ$2 -> 0 | AL46: =IF(H46="MULTI","MULTI",IF(COUNTIFS($E$4:$E$1277,H46,$H$4:$H$1277,E46)>0,"Y","N")) -> N | AM46: =T46*((1+Q46)^25) -> 99054.326 | BC46: EWR | BD46: =SUMIF($E$4:$E$1277,$BC46,$Z$4:$Z$1277) -> 1634.0404 | BE46: =SUMIF($E$4:$E$1277,$BC46,$AB$4:$AB$1277) -> 10824.676 | BF46: =SUMIF($E$4:$E$1277,$BC46,$AD$4:$AD$1277) -> 39837.722 | BG46: =SUMIF($E$4:$E$1277,$BC46,$AF$4:$AF$1277) -> 87968.128 | BH46: =SUMIF($E$4:$E$1277,$BC46,$AH$4:$AH$1277) -> 145685.88 | BI46: =SUMIF($E$4:$E$1277,$BC46,$AJ$4:$AJ$1277) -> 214465.32 | BM46: Poland | BN46: =SUMIF($F$4:$F$1277,$BM46,$Z$4:$Z$1277) -> 21623.524 | BO46: =SUMIF($F$4:$F$1277,$BM46,$AB$4:$AB$1277) -> 73395.097 | BP46: =SUMIF($F$4:$F$1277,$BM46,$AD$4:$AD$1277) -> 207599.54 | BQ46: =SUMIF($F$4:$F$1277,$BM46,$AF$4:$AF$1277) -> 469759.65 | BR46: =SUMIF($F$4:$F$1277,$BM46,$AH$4:$AH$1277) -> 708653.23 | BS46: =SUMIF($F$4:$F$1277,$BM46,$AJ$4:$AJ$1277) -> 1002220.1
A47: R044 | BC47: EZE | BD47: =SUMIF($E$4:$E$1277,$BC47,$Z$4:$Z$1277) -> 0 | BE47: =SUMIF($E$4:$E$1277,$BC47,$AB$4:$AB$1277) -> 0 | BF47: =SUMIF($E$4:$E$1277,$BC47,$AD$4:$AD$1277) -> 0 | BG47: =SUMIF($E$4:$E$1277,$BC47,$AF$4:$AF$1277) -> 0 | BH47: =SUMIF($E$4:$E$1277,$BC47,$AH$4:$AH$1277) -> 0 | BI47: =SUMIF($E$4:$E$1277,$BC47,$AJ$4:$AJ$1277) -> 0 | BM47: Portugal | BN47: =SUMIF($F$4:$F$1277,$BM47,$Z$4:$Z$1277) -> 51612.63 | BO47: =SUMIF($F$4:$F$1277,$BM47,$AB$4:$AB$1277) -> 175184.86 | BP47: =SUMIF($F$4:$F$1277,$BM47,$AD$4:$AD$1277) -> 495513.98 | BQ47: =SUMIF($F$4:$F$1277,$BM47,$AF$4:$AF$1277) -> 1121257.2 | BR47: =SUMIF($F$4:$F$1277,$BM47,$AH$4:$AH$1277) -> 1691466.1 | BS47: =SUMIF($F$4:$F$1277,$BM47,$AJ$4:$AJ$1277) -> 2392173.3
A48: R045 | B48: LA | C48: LATAM Airlines | D48: Passenger | E48: GRU | F48: Brazil | G48: LATAM | H48: JFK | I48: United States | J48: US | K48: international | L48: B787-9 | M48: 730 | N48: =M48/365 -> 2 | O48: 7710 | P48: =M48*O48 -> 5628300 | Q48: =IFERROR(VLOOKUP(G48,SCENARIOS!$A$13:$E$18,2,0),0.025) -> 0.035 | R48: =IFERROR(VLOOKUP(L48,INPUTS!$A$107:$B$120,2,0),0.0082) -> 0.0079 | S48: =O48*R48 -> 60.909 | T48: =M48*S48 -> 44463.57 | U48: =T48/INPUTS!$B$7*1000 -> 55579462 | V48: =T48*INPUTS!$B$6 -> 140504.88 | W48: Yes | X48: Yes | Y48: =IFERROR(VLOOKUP(E48,INPUTS!$A$44:$B$103,2,0),0) -> 0 | Z48: =T48*Y48 -> 0 | AA48: =IFERROR(VLOOKUP(E48,INPUTS!$A$44:$C$103,3,0),SCENARIOS!$J$23) -> 0 | AB48: =$T48*AA48*(1+$Q48)^AB$2 -> 0 | AC48: =IFERROR(VLOOKUP($E48,INPUTS!$A$44:$G$103,4,0),SCENARIOS!$K$23) -> 0 | AD48: =$T48*AC48*(1+$Q48)^AD$2 -> 0 | AE48: =IFERROR(VLOOKUP($E48,INPUTS!$A$44:$G$103,5,0),SCENARIOS!$L$23) -> 0 | AF48: =$T48*AE48*(1+$Q48)^AF$2 -> 0 | AG48: =IFERROR(VLOOKUP($E48,INPUTS!$A$44:$G$103,6,0),SCENARIOS!$M$23) -> 0 | AH48: =$T48*AG48*(1+$Q48)^AH$2 -> 0 | AI48: =IFERROR(VLOOKUP($E48,INPUTS!$A$44:$G$103,7,0),SCENARIOS!$N$23) -> 0 | AJ48: =$T48*AI48*(1+$Q48)^AJ$2 -> 0 | AL48: =IF(H48="MULTI","MULTI",IF(COUNTIFS($E$4:$E$1277,H48,$H$4:$H$1277,E48)>0,"Y","N")) -> Y | AM48: =T48*((1+Q48)^25) -> 105078.31 | BC48: FCO | BD48: =SUMIF($E$4:$E$1277,$BC48,$Z$4:$Z$1277) -> 22012.206 | BE48: =SUMIF($E$4:$E$1277,$BC48,$AB$4:$AB$1277) -> 74714.373 | BF48: =SUMIF($E$4:$E$1277,$BC48,$AD$4:$AD$1277) -> 211331.14 | BG48: =SUMIF($E$4:$E$1277,$BC48,$AF$4:$AF$1277) -> 478203.57 | BH48: =SUMIF($E$4:$E$1277,$BC48,$AH$4:$AH$1277) -> 721391.26 | BI48: =SUMIF($E$4:$E$1277,$BC48,$AJ$4:$AJ$1277) -> 1020235 | BM48: Qatar | BN48: =SUMIF($F$4:$F$1277,$BM48,$Z$4:$Z$1277) -> 0 | BO48: =SUMIF($F$4:$F$1277,$BM48,$AB$4:$AB$1277) -> 0 | BP48: =SUMIF($F$4:$F$1277,$BM48,$AD$4:$AD$1277) -> 0 | BQ48: =SUMIF($F$4:$F$1277,$BM48,$AF$4:$AF$1277) -> 0 | BR48: =SUMIF($F$4:$F$1277,$BM48,$AH$4:$AH$1277) -> 0 | BS48: =SUMIF($F$4:$F$1277,$BM48,$AJ$4:$AJ$1277) -> 0
A49: R046 | B49: LA | C49: LATAM Airlines | D49: Passenger | E49: GRU | F49: Brazil | G49: LATAM | H49: MAD | I49: Spain | J49: EU | K49: international | L49: B787-9 | M49: 730 | N49: =M49/365 -> 2 | O49: 9280 | P49: =M49*O49 -> 6774400 | Q49: =IFERROR(VLOOKUP(G49,SCENARIOS!$A$13:$E$18,2,0),0.025) -> 0.035 | R49: =IFERROR(VLOOKUP(L49,INPUTS!$A$107:$B$120,2,0),0.0082) -> 0.0079 | S49: =O49*R49 -> 73.312 | T49: =M49*S49 -> 53517.76 | U49: =T49/INPUTS!$B$7*1000 -> 66897200 | V49: =T49*INPUTS!$B$6 -> 169116.12 | W49: Yes | X49: Yes | Y49: =IFERROR(VLOOKUP(E49,INPUTS!$A$44:$B$103,2,0),0) -> 0 | Z49: =T49*Y49 -> 0 | AA49: =IFERROR(VLOOKUP(E49,INPUTS!$A$44:$C$103,3,0),SCENARIOS!$J$23) -> 0 | AB49: =$T49*AA49*(1+$Q49)^AB$2 -> 0 | AC49: =IFERROR(VLOOKUP($E49,INPUTS!$A$44:$G$103,4,0),SCENARIOS!$K$23) -> 0 | AD49: =$T49*AC49*(1+$Q49)^AD$2 -> 0 | AE49: =IFERROR(VLOOKUP($E49,INPUTS!$A$44:$G$103,5,0),SCENARIOS!$L$23) -> 0 | AF49: =$T49*AE49*(1+$Q49)^AF$2 -> 0 | AG49: =IFERROR(VLOOKUP($E49,INPUTS!$A$44:$G$103,6,0),SCENARIOS!$M$23) -> 0 | AH49: =$T49*AG49*(1+$Q49)^AH$2 -> 0 | AI49: =IFERROR(VLOOKUP($E49,INPUTS!$A$44:$G$103,7,0),SCENARIOS!$N$23) -> 0 | AJ49: =$T49*AI49*(1+$Q49)^AJ$2 -> 0 | AL49: =IF(H49="MULTI","MULTI",IF(COUNTIFS($E$4:$E$1277,H49,$H$4:$H$1277,E49)>0,"Y","N")) -> Y | AM49: =T49*((1+Q49)^25) -> 126475.58 | BC49: FLL | BD49: =SUMIF($E$4:$E$1277,$BC49,$Z$4:$Z$1277) -> 3352.6454 | BE49: =SUMIF($E$4:$E$1277,$BC49,$AB$4:$AB$1277) -> 22209.549 | BF49: =SUMIF($E$4:$E$1277,$BC49,$AD$4:$AD$1277) -> 81737.121 | BG49: =SUMIF($E$4:$E$1277,$BC49,$AF$4:$AF$1277) -> 180488.77 | BH49: =SUMIF($E$4:$E$1277,$BC49,$AH$4:$AH$1277) -> 298911.28 | BI49: =SUMIF($E$4:$E$1277,$BC49,$AJ$4:$AJ$1277) -> 440029.61 | BM49: Russia | BN49: =SUMIF($F$4:$F$1277,$BM49,$Z$4:$Z$1277) -> 0 | BO49: =SUMIF($F$4:$F$1277,$BM49,$AB$4:$AB$1277) -> 0 | BP49: =SUMIF($F$4:$F$1277,$BM49,$AD$4:$AD$1277) -> 0 | BQ49: =SUMIF($F$4:$F$1277,$BM49,$AF$4:$AF$1277) -> 0 | BR49: =SUMIF($F$4:$F$1277,$BM49,$AH$4:$AH$1277) -> 0 | BS49: =SUMIF($F$4:$F$1277,$BM49,$AJ$4:$AJ$1277) -> 0
A50: R047 | B50: LA | C50: LATAM Airlines | D50: Passenger | E50: SCL | F50: Chile | G50: LATAM | H50: LAX | I50: United States | J50: US | K50: international | L50: B787-9 | M50: 365 | N50: =M50/365 -> 1 | O50: 8870 | P50: =M50*O50 -> 3237550 | Q50: =IFERROR(VLOOKUP(G50,SCENARIOS!$A$13:$E$18,2,0),0.025) -> 0.035 | R50: =IFERROR(VLOOKUP(L50,INPUTS!$A$107:$B$120,2,0),0.0082) -> 0.0079 | S50: =O50*R50 -> 70.073 | T50: =M50*S50 -> 25576.645 | U50: =T50/INPUTS!$B$7*1000 -> 31970806 | V50: =T50*INPUTS!$B$6 -> 80822.198 | W50: Yes | X50: Yes | Y50: =IFERROR(VLOOKUP(E50,INPUTS!$A$44:$B$103,2,0),0) -> 0 | Z50: =T50*Y50 -> 0 | AA50: =IFERROR(VLOOKUP(E50,INPUTS!$A$44:$C$103,3,0),SCENARIOS!$J$23) -> 0 | AB50: =$T50*AA50*(1+$Q50)^AB$2 -> 0 | AC50: =IFERROR(VLOOKUP($E50,INPUTS!$A$44:$G$103,4,0),SCENARIOS!$K$23) -> 0 | AD50: =$T50*AC50*(1+$Q50)^AD$2 -> 0 | AE50: =IFERROR(VLOOKUP($E50,INPUTS!$A$44:$G$103,5,0),SCENARIOS!$L$23) -> 0 | AF50: =$T50*AE50*(1+$Q50)^AF$2 -> 0 | AG50: =IFERROR(VLOOKUP($E50,INPUTS!$A$44:$G$103,6,0),SCENARIOS!$M$23) -> 0 | AH50: =$T50*AG50*(1+$Q50)^AH$2 -> 0 | AI50: =IFERROR(VLOOKUP($E50,INPUTS!$A$44:$G$103,7,0),SCENARIOS!$N$23) -> 0 | AJ50: =$T50*AI50*(1+$Q50)^AJ$2 -> 0 | AL50: =IF(H50="MULTI","MULTI",IF(COUNTIFS($E$4:$E$1277,H50,$H$4:$H$1277,E50)>0,"Y","N")) -> N | AM50: =T50*((1+Q50)^25) -> 60443.878 | BC50: FRA | BD50: =SUMIF($E$4:$E$1277,$BC50,$Z$4:$Z$1277) -> 21068.415 | BE50: =SUMIF($E$4:$E$1277,$BC50,$AB$4:$AB$1277) -> 71510.932 | BF50: =SUMIF($E$4:$E$1277,$BC50,$AD$4:$AD$1277) -> 202270.14 | BG50: =SUMIF($E$4:$E$1277,$BC50,$AF$4:$AF$1277) -> 457700.2 | BH50: =SUMIF($E$4:$E$1277,$BC50,$AH$4:$AH$1277) -> 690461.01 | BI50: =SUMIF($E$4:$E$1277,$BC50,$AJ$4:$AJ$1277) -> 976491.58 | BM50: Saudi Arabia | BN50: =SUMIF($F$4:$F$1277,$BM50,$Z$4:$Z$1277) -> 0 | BO50: =SUMIF($F$4:$F$1277,$BM50,$AB$4:$AB$1277) -> 0 | BP50: =SUMIF($F$4:$F$1277,$BM50,$AD$4:$AD$1277) -> 0 | BQ50: =SUMIF($F$4:$F$1277,$BM50,$AF$4:$AF$1277) -> 0 | BR50: =SUMIF($F$4:$F$1277,$BM50,$AH$4:$AH$1277) -> 0 | BS50: =SUMIF($F$4:$F$1277,$BM50,$AJ$4:$AJ$1277) -> 0
A51: R048 | B51: AV | C51: Avianca | D51: Passenger | E51: BOG | F51: Colombia | G51: LATAM | H51: MAD | I51: Spain | J51: EU | K51: international | L51: B787-9 | M51: 365 | N51: =M51/365 -> 1 | O51: 8810 | P51: =M51*O51 -> 3215650 | Q51: =IFERROR(VLOOKUP(G51,SCENARIOS!$A$13:$E$18,2,0),0.025) -> 0.035 | R51: =IFERROR(VLOOKUP(L51,INPUTS!$A$107:$B$120,2,0),0.0082) -> 0.0079 | S51: =O51*R51 -> 69.599 | T51: =M51*S51 -> 25403.635 | U51: =T51/INPUTS!$B$7*1000 -> 31754544 | V51: =T51*INPUTS!$B$6 -> 80275.487 | W51: Yes | X51: Yes | Y51: =IFERROR(VLOOKUP(E51,INPUTS!$A$44:$B$103,2,0),0) -> 0 | Z51: =T51*Y51 -> 0 | AA51: =IFERROR(VLOOKUP(E51,INPUTS!$A$44:$C$103,3,0),SCENARIOS!$J$23) -> 0 | AB51: =$T51*AA51*(1+$Q51)^AB$2 -> 0 | AC51: =IFERROR(VLOOKUP($E51,INPUTS!$A$44:$G$103,4,0),SCENARIOS!$K$23) -> 0 | AD51: =$T51*AC51*(1+$Q51)^AD$2 -> 0 | AE51: =IFERROR(VLOOKUP($E51,INPUTS!$A$44:$G$103,5,0),SCENARIOS!$L$23) -> 0 | AF51: =$T51*AE51*(1+$Q51)^AF$2 -> 0 | AG51: =IFERROR(VLOOKUP($E51,INPUTS!$A$44:$G$103,6,0),SCENARIOS!$M$23) -> 0 | AH51: =$T51*AG51*(1+$Q51)^AH$2 -> 0 | AI51: =IFERROR(VLOOKUP($E51,INPUTS!$A$44:$G$103,7,0),SCENARIOS!$N$23) -> 0 | AJ51: =$T51*AI51*(1+$Q51)^AJ$2 -> 0 | AL51: =IF(H51="MULTI","MULTI",IF(COUNTIFS($E$4:$E$1277,H51,$H$4:$H$1277,E51)>0,"Y","N")) -> Y | AM51: =T51*((1+Q51)^25) -> 60035.013 | BC51: GRU | BD51: =SUMIF($E$4:$E$1277,$BC51,$Z$4:$Z$1277) -> 0 | BE51: =SUMIF($E$4:$E$1277,$BC51,$AB$4:$AB$1277) -> 0 | BF51: =SUMIF($E$4:$E$1277,$BC51,$AD$4:$AD$1277) -> 0 | BG51: =SUMIF($E$4:$E$1277,$BC51,$AF$4:$AF$1277) -> 0 | BH51: =SUMIF($E$4:$E$1277,$BC51,$AH$4:$AH$1277) -> 0 | BI51: =SUMIF($E$4:$E$1277,$BC51,$AJ$4:$AJ$1277) -> 0 | BM51: Singapore | BN51: =SUMIF($F$4:$F$1277,$BM51,$Z$4:$Z$1277) -> 0 | BO51: =SUMIF($F$4:$F$1277,$BM51,$AB$4:$AB$1277) -> 189041.71 | BP51: =SUMIF($F$4:$F$1277,$BM51,$AD$4:$AD$1277) -> 766660.48 | BQ51: =SUMIF($F$4:$F$1277,$BM51,$AF$4:$AF$1277) -> 1865519.4 | BR51: =SUMIF($F$4:$F$1277,$BM51,$AH$4:$AH$1277) -> 3404534.4 | BS51: =SUMIF($F$4:$F$1277,$BM51,$AJ$4:$AJ$1277) -> 5522848.9
A52: R049 | B52: LA | C52: LATAM Airlines | D52: Passenger | E52: GRU | F52: Brazil | G52: LATAM | H52: EZE | I52: Argentina | J52: LATAM | K52: international | L52: A320neo | N52: =M52/365 -> 0 | O52: 2430 | P52: =M52*O52 -> 0 | Q52: =IFERROR(VLOOKUP(G52,SCENARIOS!$A$13:$E$18,2,0),0.025) -> 0.035 | R52: =IFERROR(VLOOKUP(L52,INPUTS!$A$107:$B$120,2,0),0.0082) -> 0.0039 | S52: =O52*R52 -> 9.477 | T52: =M52*S52 -> 0 | U52: =T52/INPUTS!$B$7*1000 -> 0 | V52: =T52*INPUTS!$B$6 -> 0 | W52: No | X52: No | Y52: =IFERROR(VLOOKUP(E52,INPUTS!$A$44:$B$103,2,0),0) -> 0 | Z52: =T52*Y52 -> 0 | AA52: =IFERROR(VLOOKUP(E52,INPUTS!$A$44:$C$103,3,0),SCENARIOS!$J$23) -> 0 | AB52: =$T52*AA52*(1+$Q52)^AB$2 -> 0 | AC52: =IFERROR(VLOOKUP($E52,INPUTS!$A$44:$G$103,4,0),SCENARIOS!$K$23) -> 0 | AD52: =$T52*AC52*(1+$Q52)^AD$2 -> 0 | AE52: =IFERROR(VLOOKUP($E52,INPUTS!$A$44:$G$103,5,0),SCENARIOS!$L$23) -> 0 | AF52: =$T52*AE52*(1+$Q52)^AF$2 -> 0 | AG52: =IFERROR(VLOOKUP($E52,INPUTS!$A$44:$G$103,6,0),SCENARIOS!$M$23) -> 0 | AH52: =$T52*AG52*(1+$Q52)^AH$2 -> 0 | AI52: =IFERROR(VLOOKUP($E52,INPUTS!$A$44:$G$103,7,0),SCENARIOS!$N$23) -> 0 | AJ52: =$T52*AI52*(1+$Q52)^AJ$2 -> 0 | AL52: =IF(H52="MULTI","MULTI",IF(COUNTIFS($E$4:$E$1277,H52,$H$4:$H$1277,E52)>0,"Y","N")) -> N | AM52: =T52*((1+Q52)^25) -> 0 | BC52: HAN | BD52: =SUMIF($E$4:$E$1277,$BC52,$Z$4:$Z$1277) -> 0 | BE52: =SUMIF($E$4:$E$1277,$BC52,$AB$4:$AB$1277) -> 0 | BF52: =SUMIF($E$4:$E$1277,$BC52,$AD$4:$AD$1277) -> 0 | BG52: =SUMIF($E$4:$E$1277,$BC52,$AF$4:$AF$1277) -> 0 | BH52: =SUMIF($E$4:$E$1277,$BC52,$AH$4:$AH$1277) -> 0 | BI52: =SUMIF($E$4:$E$1277,$BC52,$AJ$4:$AJ$1277) -> 0 | BM52: South Africa | BN52: =SUMIF($F$4:$F$1277,$BM52,$Z$4:$Z$1277) -> 0 | BO52: =SUMIF($F$4:$F$1277,$BM52,$AB$4:$AB$1277) -> 0 | BP52: =SUMIF($F$4:$F$1277,$BM52,$AD$4:$AD$1277) -> 0 | BQ52: =SUMIF($F$4:$F$1277,$BM52,$AF$4:$AF$1277) -> 0 | BR52: =SUMIF($F$4:$F$1277,$BM52,$AH$4:$AH$1277) -> 0 | BS52: =SUMIF($F$4:$F$1277,$BM52,$AJ$4:$AJ$1277) -> 0
A53: R050 | B53: LA | C53: LATAM Airlines | D53: Passenger | E53: GRU | F53: Brazil | G53: LATAM | H53: SCL | I53: Chile | J53: LATAM | K53: international | L53: A320neo | N53: =M53/365 -> 0 | O53: 2640 | P53: =M53*O53 -> 0 | Q53: =IFERROR(VLOOKUP(G53,SCENARIOS!$A$13:$E$18,2,0),0.025) -> 0.035 | R53: =IFERROR(VLOOKUP(L53,INPUTS!$A$107:$B$120,2,0),0.0082) -> 0.0039 | S53: =O53*R53 -> 10.296 | T53: =M53*S53 -> 0 | U53: =T53/INPUTS!$B$7*1000 -> 0 | V53: =T53*INPUTS!$B$6 -> 0 | W53: No | X53: No | Y53: =IFERROR(VLOOKUP(E53,INPUTS!$A$44:$B$103,2,0),0) -> 0 | Z53: =T53*Y53 -> 0 | AA53: =IFERROR(VLOOKUP(E53,INPUTS!$A$44:$C$103,3,0),SCENARIOS!$J$23) -> 0 | AB53: =$T53*AA53*(1+$Q53)^AB$2 -> 0 | AC53: =IFERROR(VLOOKUP($E53,INPUTS!$A$44:$G$103,4,0),SCENARIOS!$K$23) -> 0 | AD53: =$T53*AC53*(1+$Q53)^AD$2 -> 0 | AE53: =IFERROR(VLOOKUP($E53,INPUTS!$A$44:$G$103,5,0),SCENARIOS!$L$23) -> 0 | AF53: =$T53*AE53*(1+$Q53)^AF$2 -> 0 | AG53: =IFERROR(VLOOKUP($E53,INPUTS!$A$44:$G$103,6,0),SCENARIOS!$M$23) -> 0 | AH53: =$T53*AG53*(1+$Q53)^AH$2 -> 0 | AI53: =IFERROR(VLOOKUP($E53,INPUTS!$A$44:$G$103,7,0),SCENARIOS!$N$23) -> 0 | AJ53: =$T53*AI53*(1+$Q53)^AJ$2 -> 0 | AL53: =IF(H53="MULTI","MULTI",IF(COUNTIFS($E$4:$E$1277,H53,$H$4:$H$1277,E53)>0,"Y","N")) -> N | AM53: =T53*((1+Q53)^25) -> 0 | BC53: HEL | BD53: =SUMIF($E$4:$E$1277,$BC53,$Z$4:$Z$1277) -> 44270.503 | BE53: =SUMIF($E$4:$E$1277,$BC53,$AB$4:$AB$1277) -> 150264.03 | BF53: =SUMIF($E$4:$E$1277,$BC53,$AD$4:$AD$1277) -> 425024.9 | BG53: =SUMIF($E$4:$E$1277,$BC53,$AF$4:$AF$1277) -> 961753.33 | BH53: =SUMIF($E$4:$E$1277,$BC53,$AH$4:$AH$1277) -> 1450847.5 | BI53: =SUMIF($E$4:$E$1277,$BC53,$AJ$4:$AJ$1277) -> 2051876 | BM53: South Korea | BN53: =SUMIF($F$4:$F$1277,$BM53,$Z$4:$Z$1277) -> 0 | BO53: =SUMIF($F$4:$F$1277,$BM53,$AB$4:$AB$1277) -> 0 | BP53: =SUMIF($F$4:$F$1277,$BM53,$AD$4:$AD$1277) -> 0 | BQ53: =SUMIF($F$4:$F$1277,$BM53,$AF$4:$AF$1277) -> 0 | BR53: =SUMIF($F$4:$F$1277,$BM53,$AH$4:$AH$1277) -> 0 | BS53: =SUMIF($F$4:$F$1277,$BM53,$AJ$4:$AJ$1277) -> 0
A54: R051 | B54: ET | C54: Ethiopian Airlines | D54: Passenger | E54: ADD | F54: Ethiopia | G54: ROW | H54: LHR | I54: United Kingdom | J54: EU | K54: international | L54: B787-9 | M54: 730 | N54: =M54/365 -> 2 | O54: 6130 | P54: =M54*O54 -> 4474900 | Q54: =IFERROR(VLOOKUP(G54,SCENARIOS!$A$13:$E$18,2,0),0.025) -> 0.03 | R54: =IFERROR(VLOOKUP(L54,INPUTS!$A$107:$B$120,2,0),0.0082) -> 0.0079 | S54: =O54*R54 -> 48.427 | T54: =M54*S54 -> 35351.71 | U54: =T54/INPUTS!$B$7*1000 -> 44189638 | V54: =T54*INPUTS!$B$6 -> 111711.4 | W54: Partial | X54: Exempt-LDC | Y54: =IFERROR(VLOOKUP(E54,INPUTS!$A$44:$B$103,2,0),0) -> 0 | Z54: =T54*Y54 -> 0 | AA54: =IFERROR(VLOOKUP(E54,INPUTS!$A$44:$C$103,3,0),SCENARIOS!$J$23) -> 0 | AB54: =$T54*AA54*(1+$Q54)^AB$2 -> 0 | AC54: =IFERROR(VLOOKUP($E54,INPUTS!$A$44:$G$103,4,0),SCENARIOS!$K$23) -> 0 | AD54: =$T54*AC54*(1+$Q54)^AD$2 -> 0 | AE54: =IFERROR(VLOOKUP($E54,INPUTS!$A$44:$G$103,5,0),SCENARIOS!$L$23) -> 0 | AF54: =$T54*AE54*(1+$Q54)^AF$2 -> 0 | AG54: =IFERROR(VLOOKUP($E54,INPUTS!$A$44:$G$103,6,0),SCENARIOS!$M$23) -> 0 | AH54: =$T54*AG54*(1+$Q54)^AH$2 -> 0 | AI54: =IFERROR(VLOOKUP($E54,INPUTS!$A$44:$G$103,7,0),SCENARIOS!$N$23) -> 0 | AJ54: =$T54*AI54*(1+$Q54)^AJ$2 -> 0 | AL54: =IF(H54="MULTI","MULTI",IF(COUNTIFS($E$4:$E$1277,H54,$H$4:$H$1277,E54)>0,"Y","N")) -> N | AM54: =T54*((1+Q54)^25) -> 74018.63 | BC54: HKG | BD54: =SUMIF($E$4:$E$1277,$BC54,$Z$4:$Z$1277) -> 0 | BE54: =SUMIF($E$4:$E$1277,$BC54,$AB$4:$AB$1277) -> 0 | BF54: =SUMIF($E$4:$E$1277,$BC54,$AD$4:$AD$1277) -> 0 | BG54: =SUMIF($E$4:$E$1277,$BC54,$AF$4:$AF$1277) -> 0 | BH54: =SUMIF($E$4:$E$1277,$BC54,$AH$4:$AH$1277) -> 0 | BI54: =SUMIF($E$4:$E$1277,$BC54,$AJ$4:$AJ$1277) -> 0 | BM54: Spain | BN54: =SUMIF($F$4:$F$1277,$BM54,$Z$4:$Z$1277) -> 79999.597 | BO54: =SUMIF($F$4:$F$1277,$BM54,$AB$4:$AB$1277) -> 271536.6 | BP54: =SUMIF($F$4:$F$1277,$BM54,$AD$4:$AD$1277) -> 768046.85 | BQ54: =SUMIF($F$4:$F$1277,$BM54,$AF$4:$AF$1277) -> 1737949 | BR54: =SUMIF($F$4:$F$1277,$BM54,$AH$4:$AH$1277) -> 2621773.1 | BS54: =SUMIF($F$4:$F$1277,$BM54,$AJ$4:$AJ$1277) -> 3707869.5
A55: R052 | B55: ET | C55: Ethiopian Airlines | D55: Passenger | E55: ADD | F55: Ethiopia | G55: ROW | H55: JFK | I55: United States | J55: US | K55: international | L55: B787-9 | M55: 365 | N55: =M55/365 -> 1 | O55: 12350 | P55: =M55*O55 -> 4507750 | Q55: =IFERROR(VLOOKUP(G55,SCENARIOS!$A$13:$E$18,2,0),0.025) -> 0.03 | R55: =IFERROR(VLOOKUP(L55,INPUTS!$A$107:$B$120,2,0),0.0082) -> 0.0079 | S55: =O55*R55 -> 97.565 | T55: =M55*S55 -> 35611.225 | U55: =T55/INPUTS!$B$7*1000 -> 44514031 | V55: =T55*INPUTS!$B$6 -> 112531.47 | W55: Partial | X55: Exempt-LDC | Y55: =IFERROR(VLOOKUP(E55,INPUTS!$A$44:$B$103,2,0),0) -> 0 | Z55: =T55*Y55 -> 0 | AA55: =IFERROR(VLOOKUP(E55,INPUTS!$A$44:$C$103,3,0),SCENARIOS!$J$23) -> 0 | AB55: =$T55*AA55*(1+$Q55)^AB$2 -> 0 | AC55: =IFERROR(VLOOKUP($E55,INPUTS!$A$44:$G$103,4,0),SCENARIOS!$K$23) -> 0 | AD55: =$T55*AC55*(1+$Q55)^AD$2 -> 0 | AE55: =IFERROR(VLOOKUP($E55,INPUTS!$A$44:$G$103,5,0),SCENARIOS!$L$23) -> 0 | AF55: =$T55*AE55*(1+$Q55)^AF$2 -> 0 | AG55: =IFERROR(VLOOKUP($E55,INPUTS!$A$44:$G$103,6,0),SCENARIOS!$M$23) -> 0 | AH55: =$T55*AG55*(1+$Q55)^AH$2 -> 0 | AI55: =IFERROR(VLOOKUP($E55,INPUTS!$A$44:$G$103,7,0),SCENARIOS!$N$23) -> 0 | AJ55: =$T55*AI55*(1+$Q55)^AJ$2 -> 0 | AL55: =IF(H55="MULTI","MULTI",IF(COUNTIFS($E$4:$E$1277,H55,$H$4:$H$1277,E55)>0,"Y","N")) -> N | AM55: =T55*((1+Q55)^25) -> 74561.997 | BC55: HND | BD55: =SUMIF($E$4:$E$1277,$BC55,$Z$4:$Z$1277) -> 0 | BE55: =SUMIF($E$4:$E$1277,$BC55,$AB$4:$AB$1277) -> 37888.673 | BF55: =SUMIF($E$4:$E$1277,$BC55,$AD$4:$AD$1277) -> 69146.045 | BG55: =SUMIF($E$4:$E$1277,$BC55,$AF$4:$AF$1277) -> 168253.47 | BH55: =SUMIF($E$4:$E$1277,$BC55,$AH$4:$AH$1277) -> 272941.43 | BI55: =SUMIF($E$4:$E$1277,$BC55,$AJ$4:$AJ$1277) -> 415093.74 | BM55: Sweden | BN55: =SUMIF($F$4:$F$1277,$BM55,$Z$4:$Z$1277) -> 0 | BO55: =SUMIF($F$4:$F$1277,$BM55,$AB$4:$AB$1277) -> 0 | BP55: =SUMIF($F$4:$F$1277,$BM55,$AD$4:$AD$1277) -> 0 | BQ55: =SUMIF($F$4:$F$1277,$BM55,$AF$4:$AF$1277) -> 0 | BR55: =SUMIF($F$4:$F$1277,$BM55,$AH$4:$AH$1277) -> 0 | BS55: =SUMIF($F$4:$F$1277,$BM55,$AJ$4:$AJ$1277) -> 0
A56: R053 | B56: ET | C56: Ethiopian Airlines | D56: Passenger | E56: ADD | F56: Ethiopia | G56: ROW | H56: PEK | I56: China | J56: APAC | K56: international | L56: B787-9 | M56: 365 | N56: =M56/365 -> 1 | O56: 6740 | P56: =M56*O56 -> 2460100 | Q56: =IFERROR(VLOOKUP(G56,SCENARIOS!$A$13:$E$18,2,0),0.025) -> 0.03 | R56: =IFERROR(VLOOKUP(L56,INPUTS!$A$107:$B$120,2,0),0.0082) -> 0.0079 | S56: =O56*R56 -> 53.246 | T56: =M56*S56 -> 19434.79 | U56: =T56/INPUTS!$B$7*1000 -> 24293488 | V56: =T56*INPUTS!$B$6 -> 61413.936 | W56: No | X56: Exempt-LDC | Y56: =IFERROR(VLOOKUP(E56,INPUTS!$A$44:$B$103,2,0),0) -> 0 | Z56: =T56*Y56 -> 0 | AA56: =IFERROR(VLOOKUP(E56,INPUTS!$A$44:$C$103,3,0),SCENARIOS!$J$23) -> 0 | AB56: =$T56*AA56*(1+$Q56)^AB$2 -> 0 | AC56: =IFERROR(VLOOKUP($E56,INPUTS!$A$44:$G$103,4,0),SCENARIOS!$K$23) -> 0 | AD56: =$T56*AC56*(1+$Q56)^AD$2 -> 0 | AE56: =IFERROR(VLOOKUP($E56,INPUTS!$A$44:$G$103,5,0),SCENARIOS!$L$23) -> 0 | AF56: =$T56*AE56*(1+$Q56)^AF$2 -> 0 | AG56: =IFERROR(VLOOKUP($E56,INPUTS!$A$44:$G$103,6,0),SCENARIOS!$M$23) -> 0 | AH56: =$T56*AG56*(1+$Q56)^AH$2 -> 0 | AI56: =IFERROR(VLOOKUP($E56,INPUTS!$A$44:$G$103,7,0),SCENARIOS!$N$23) -> 0 | AJ56: =$T56*AI56*(1+$Q56)^AJ$2 -> 0 | AL56: =IF(H56="MULTI","MULTI",IF(COUNTIFS($E$4:$E$1277,H56,$H$4:$H$1277,E56)>0,"Y","N")) -> N | AM56: =T56*((1+Q56)^25) -> 40692.134 | BC56: HNL | BD56: =SUMIF($E$4:$E$1277,$BC56,$Z$4:$Z$1277) -> 0 | BE56: =SUMIF($E$4:$E$1277,$BC56,$AB$4:$AB$1277) -> 0 | BF56: =SUMIF($E$4:$E$1277,$BC56,$AD$4:$AD$1277) -> 0 | BG56: =SUMIF($E$4:$E$1277,$BC56,$AF$4:$AF$1277) -> 0 | BH56: =SUMIF($E$4:$E$1277,$BC56,$AH$4:$AH$1277) -> 0 | BI56: =SUMIF($E$4:$E$1277,$BC56,$AJ$4:$AJ$1277) -> 0 | BM56: Switzerland | BN56: =SUMIF($F$4:$F$1277,$BM56,$Z$4:$Z$1277) -> 45915.779 | BO56: =SUMIF($F$4:$F$1277,$BM56,$AB$4:$AB$1277) -> 155848.47 | BP56: =SUMIF($F$4:$F$1277,$BM56,$AD$4:$AD$1277) -> 440820.6 | BQ56: =SUMIF($F$4:$F$1277,$BM56,$AF$4:$AF$1277) -> 997496.09 | BR56: =SUMIF($F$4:$F$1277,$BM56,$AH$4:$AH$1277) -> 1504767 | BS56: =SUMIF($F$4:$F$1277,$BM56,$AJ$4:$AJ$1277) -> 2128132.2
A57: R054 | B57: TK | C57: Turkish Airlines | D57: Passenger | E57: IST | F57: Turkey | G57: ROW | H57: JFK | I57: United States | J57: US | K57: international | L57: B777-300ER | M57: 730 | N57: =M57/365 -> 2 | O57: 9400 | P57: =M57*O57 -> 6862000 | Q57: =IFERROR(VLOOKUP(G57,SCENARIOS!$A$13:$E$18,2,0),0.025) -> 0.03 | R57: =IFERROR(VLOOKUP(L57,INPUTS!$A$107:$B$120,2,0),0.0082) -> 0.0089 | S57: =O57*R57 -> 83.66 | T57: =M57*S57 -> 61071.8 | U57: =T57/INPUTS!$B$7*1000 -> 76339750 | V57: =T57*INPUTS!$B$6 -> 192986.89 | W57: Yes | X57: Yes | Y57: =IFERROR(VLOOKUP(E57,INPUTS!$A$44:$B$103,2,0),0) -> 0 | Z57: =T57*Y57 -> 0 | AA57: =IFERROR(VLOOKUP(E57,INPUTS!$A$44:$C$103,3,0),SCENARIOS!$J$23) -> 0 | AB57: =$T57*AA57*(1+$Q57)^AB$2 -> 0 | AC57: =IFERROR(VLOOKUP($E57,INPUTS!$A$44:$G$103,4,0),SCENARIOS!$K$23) -> 0 | AD57: =$T57*AC57*(1+$Q57)^AD$2 -> 0 | AE57: =IFERROR(VLOOKUP($E57,INPUTS!$A$44:$G$103,5,0),SCENARIOS!$L$23) -> 0 | AF57: =$T57*AE57*(1+$Q57)^AF$2 -> 0 | AG57: =IFERROR(VLOOKUP($E57,INPUTS!$A$44:$G$103,6,0),SCENARIOS!$M$23) -> 0 | AH57: =$T57*AG57*(1+$Q57)^AH$2 -> 0 | AI57: =IFERROR(VLOOKUP($E57,INPUTS!$A$44:$G$103,7,0),SCENARIOS!$N$23) -> 0 | AJ57: =$T57*AI57*(1+$Q57)^AJ$2 -> 0 | AL57: =IF(H57="MULTI","MULTI",IF(COUNTIFS($E$4:$E$1277,H57,$H$4:$H$1277,E57)>0,"Y","N")) -> N | AM57: =T57*((1+Q57)^25) -> 127870.79 | BC57: IAH | BD57: =SUMIF($E$4:$E$1277,$BC57,$Z$4:$Z$1277) -> 0 | BE57: =SUMIF($E$4:$E$1277,$BC57,$AB$4:$AB$1277) -> 0 | BF57: =SUMIF($E$4:$E$1277,$BC57,$AD$4:$AD$1277) -> 0 | BG57: =SUMIF($E$4:$E$1277,$BC57,$AF$4:$AF$1277) -> 0 | BH57: =SUMIF($E$4:$E$1277,$BC57,$AH$4:$AH$1277) -> 0 | BI57: =SUMIF($E$4:$E$1277,$BC57,$AJ$4:$AJ$1277) -> 0 | BM57: Taiwan | BN57: =SUMIF($F$4:$F$1277,$BM57,$Z$4:$Z$1277) -> 0 | BO57: =SUMIF($F$4:$F$1277,$BM57,$AB$4:$AB$1277) -> 0 | BP57: =SUMIF($F$4:$F$1277,$BM57,$AD$4:$AD$1277) -> 0 | BQ57: =SUMIF($F$4:$F$1277,$BM57,$AF$4:$AF$1277) -> 0 | BR57: =SUMIF($F$4:$F$1277,$BM57,$AH$4:$AH$1277) -> 0 | BS57: =SUMIF($F$4:$F$1277,$BM57,$AJ$4:$AJ$1277) -> 0
A58: R055 | B58: TK | C58: Turkish Airlines | D58: Passenger | E58: IST | F58: Turkey | G58: ROW | H58: LHR | I58: United Kingdom | J58: EU | K58: international | L58: B787-9 | M58: 1460 | N58: =M58/365 -> 4 | O58: 2860 | P58: =M58*O58 -> 4175600 | Q58: =IFERROR(VLOOKUP(G58,SCENARIOS!$A$13:$E$18,2,0),0.025) -> 0.03 | R58: =IFERROR(VLOOKUP(L58,INPUTS!$A$107:$B$120,2,0),0.0082) -> 0.0079 | S58: =O58*R58 -> 22.594 | T58: =M58*S58 -> 32987.24 | U58: =T58/INPUTS!$B$7*1000 -> 41234050 | V58: =T58*INPUTS!$B$6 -> 104239.68 | W58: Yes | X58: Yes | Y58: =IFERROR(VLOOKUP(E58,INPUTS!$A$44:$B$103,2,0),0) -> 0 | Z58: =T58*Y58 -> 0 | AA58: =IFERROR(VLOOKUP(E58,INPUTS!$A$44:$C$103,3,0),SCENARIOS!$J$23) -> 0 | AB58: =$T58*AA58*(1+$Q58)^AB$2 -> 0 | AC58: =IFERROR(VLOOKUP($E58,INPUTS!$A$44:$G$103,4,0),SCENARIOS!$K$23) -> 0 | AD58: =$T58*AC58*(1+$Q58)^AD$2 -> 0 | AE58: =IFERROR(VLOOKUP($E58,INPUTS!$A$44:$G$103,5,0),SCENARIOS!$L$23) -> 0 | AF58: =$T58*AE58*(1+$Q58)^AF$2 -> 0 | AG58: =IFERROR(VLOOKUP($E58,INPUTS!$A$44:$G$103,6,0),SCENARIOS!$M$23) -> 0 | AH58: =$T58*AG58*(1+$Q58)^AH$2 -> 0 | AI58: =IFERROR(VLOOKUP($E58,INPUTS!$A$44:$G$103,7,0),SCENARIOS!$N$23) -> 0 | AJ58: =$T58*AI58*(1+$Q58)^AJ$2 -> 0 | AL58: =IF(H58="MULTI","MULTI",IF(COUNTIFS($E$4:$E$1277,H58,$H$4:$H$1277,E58)>0,"Y","N")) -> N | AM58: =T58*((1+Q58)^25) -> 69067.955 | BC58: ICN | BD58: =SUMIF($E$4:$E$1277,$BC58,$Z$4:$Z$1277) -> 0 | BE58: =SUMIF($E$4:$E$1277,$BC58,$AB$4:$AB$1277) -> 0 | BF58: =SUMIF($E$4:$E$1277,$BC58,$AD$4:$AD$1277) -> 0 | BG58: =SUMIF($E$4:$E$1277,$BC58,$AF$4:$AF$1277) -> 0 | BH58: =SUMIF($E$4:$E$1277,$BC58,$AH$4:$AH$1277) -> 0 | BI58: =SUMIF($E$4:$E$1277,$BC58,$AJ$4:$AJ$1277) -> 0 | BM58: Thailand | BN58: =SUMIF($F$4:$F$1277,$BM58,$Z$4:$Z$1277) -> 0 | BO58: =SUMIF($F$4:$F$1277,$BM58,$AB$4:$AB$1277) -> 0 | BP58: =SUMIF($F$4:$F$1277,$BM58,$AD$4:$AD$1277) -> 0 | BQ58: =SUMIF($F$4:$F$1277,$BM58,$AF$4:$AF$1277) -> 0 | BR58: =SUMIF($F$4:$F$1277,$BM58,$AH$4:$AH$1277) -> 0 | BS58: =SUMIF($F$4:$F$1277,$BM58,$AJ$4:$AJ$1277) -> 0
A59: R056 | B59: TK | C59: Turkish Airlines | D59: Passenger | E59: IST | F59: Turkey | G59: ROW | H59: DXB | I59: UAE | J59: MENA | K59: international | L59: B737-800 | M59: 1825 | N59: =M59/365 -> 5 | O59: 3400 | P59: =M59*O59 -> 6205000 | Q59: =IFERROR(VLOOKUP(G59,SCENARIOS!$A$13:$E$18,2,0),0.025) -> 0.03 | R59: =IFERROR(VLOOKUP(L59,INPUTS!$A$107:$B$120,2,0),0.0082) -> 0.0041 | S59: =O59*R59 -> 13.94 | T59: =M59*S59 -> 25440.5 | U59: =T59/INPUTS!$B$7*1000 -> 31800625 | V59: =T59*INPUTS!$B$6 -> 80391.98 | W59: Yes | X59: Yes | Y59: =IFERROR(VLOOKUP(E59,INPUTS!$A$44:$B$103,2,0),0) -> 0 | Z59: =T59*Y59 -> 0 | AA59: =IFERROR(VLOOKUP(E59,INPUTS!$A$44:$C$103,3,0),SCENARIOS!$J$23) -> 0 | AB59: =$T59*AA59*(1+$Q59)^AB$2 -> 0 | AC59: =IFERROR(VLOOKUP($E59,INPUTS!$A$44:$G$103,4,0),SCENARIOS!$K$23) -> 0 | AD59: =$T59*AC59*(1+$Q59)^AD$2 -> 0 | AE59: =IFERROR(VLOOKUP($E59,INPUTS!$A$44:$G$103,5,0),SCENARIOS!$L$23) -> 0 | AF59: =$T59*AE59*(1+$Q59)^AF$2 -> 0 | AG59: =IFERROR(VLOOKUP($E59,INPUTS!$A$44:$G$103,6,0),SCENARIOS!$M$23) -> 0 | AH59: =$T59*AG59*(1+$Q59)^AH$2 -> 0 | AI59: =IFERROR(VLOOKUP($E59,INPUTS!$A$44:$G$103,7,0),SCENARIOS!$N$23) -> 0 | AJ59: =$T59*AI59*(1+$Q59)^AJ$2 -> 0 | AL59: =IF(H59="MULTI","MULTI",IF(COUNTIFS($E$4:$E$1277,H59,$H$4:$H$1277,E59)>0,"Y","N")) -> Y | AM59: =T59*((1+Q59)^25) -> 53266.757 | BC59: IND | BD59: =SUMIF($E$4:$E$1277,$BC59,$Z$4:$Z$1277) -> 0 | BE59: =SUMIF($E$4:$E$1277,$BC59,$AB$4:$AB$1277) -> 0 | BF59: =SUMIF($E$4:$E$1277,$BC59,$AD$4:$AD$1277) -> 0 | BG59: =SUMIF($E$4:$E$1277,$BC59,$AF$4:$AF$1277) -> 0 | BH59: =SUMIF($E$4:$E$1277,$BC59,$AH$4:$AH$1277) -> 0 | BI59: =SUMIF($E$4:$E$1277,$BC59,$AJ$4:$AJ$1277) -> 0 | BM59: Turkey | BN59: =SUMIF($F$4:$F$1277,$BM59,$Z$4:$Z$1277) -> 0 | BO59: =SUMIF($F$4:$F$1277,$BM59,$AB$4:$AB$1277) -> 0 | BP59: =SUMIF($F$4:$F$1277,$BM59,$AD$4:$AD$1277) -> 0 | BQ59: =SUMIF($F$4:$F$1277,$BM59,$AF$4:$AF$1277) -> 0 | BR59: =SUMIF($F$4:$F$1277,$BM59,$AH$4:$AH$1277) -> 0 | BS59: =SUMIF($F$4:$F$1277,$BM59,$AJ$4:$AJ$1277) -> 0
A60: R057 | BC60: IST | BD60: =SUMIF($E$4:$E$1277,$BC60,$Z$4:$Z$1277) -> 0 | BE60: =SUMIF($E$4:$E$1277,$BC60,$AB$4:$AB$1277) -> 0 | BF60: =SUMIF($E$4:$E$1277,$BC60,$AD$4:$AD$1277) -> 0 | BG60: =SUMIF($E$4:$E$1277,$BC60,$AF$4:$AF$1277) -> 0 | BH60: =SUMIF($E$4:$E$1277,$BC60,$AH$4:$AH$1277) -> 0 | BI60: =SUMIF($E$4:$E$1277,$BC60,$AJ$4:$AJ$1277) -> 0 | BM60: UAE | BN60: =SUMIF($F$4:$F$1277,$BM60,$Z$4:$Z$1277) -> 0 | BO60: =SUMIF($F$4:$F$1277,$BM60,$AB$4:$AB$1277) -> 0 | BP60: =SUMIF($F$4:$F$1277,$BM60,$AD$4:$AD$1277) -> 0 | BQ60: =SUMIF($F$4:$F$1277,$BM60,$AF$4:$AF$1277) -> 0 | BR60: =SUMIF($F$4:$F$1277,$BM60,$AH$4:$AH$1277) -> 0 | BS60: =SUMIF($F$4:$F$1277,$BM60,$AJ$4:$AJ$1277) -> 0
A61: R058 | BC61: JED | BD61: =SUMIF($E$4:$E$1277,$BC61,$Z$4:$Z$1277) -> 0 | BE61: =SUMIF($E$4:$E$1277,$BC61,$AB$4:$AB$1277) -> 0 | BF61: =SUMIF($E$4:$E$1277,$BC61,$AD$4:$AD$1277) -> 0 | BG61: =SUMIF($E$4:$E$1277,$BC61,$AF$4:$AF$1277) -> 0 | BH61: =SUMIF($E$4:$E$1277,$BC61,$AH$4:$AH$1277) -> 0 | BI61: =SUMIF($E$4:$E$1277,$BC61,$AJ$4:$AJ$1277) -> 0 | BM61: United Kingdom | BN61: =SUMIF($F$4:$F$1277,$BM61,$Z$4:$Z$1277) -> 189710.31 | BO61: =SUMIF($F$4:$F$1277,$BM61,$AB$4:$AB$1277) -> 1073199 | BP61: =SUMIF($F$4:$F$1277,$BM61,$AD$4:$AD$1277) -> 1821339.3 | BQ61: =SUMIF($F$4:$F$1277,$BM61,$AF$4:$AF$1277) -> 4121356.4 | BR61: =SUMIF($F$4:$F$1277,$BM61,$AH$4:$AH$1277) -> 6217248.6 | BS61: =SUMIF($F$4:$F$1277,$BM61,$AJ$4:$AJ$1277) -> 8792807.7
A62: R059 | BC62: JFK | BD62: =SUMIF($E$4:$E$1277,$BC62,$Z$4:$Z$1277) -> 2720.4485 | BE62: =SUMIF($E$4:$E$1277,$BC62,$AB$4:$AB$1277) -> 18021.569 | BF62: =SUMIF($E$4:$E$1277,$BC62,$AD$4:$AD$1277) -> 66324.23 | BG62: =SUMIF($E$4:$E$1277,$BC62,$AF$4:$AF$1277) -> 146454.62 | BH62: =SUMIF($E$4:$E$1277,$BC62,$AH$4:$AH$1277) -> 242546.6 | BI62: =SUMIF($E$4:$E$1277,$BC62,$AJ$4:$AJ$1277) -> 357054.72 | BM62: United States | BN62: =SUMIF($F$4:$F$1277,$BM62,$Z$4:$Z$1277) -> 22105.417 | BO62: =SUMIF($F$4:$F$1277,$BM62,$AB$4:$AB$1277) -> 146437 | BP62: =SUMIF($F$4:$F$1277,$BM62,$AD$4:$AD$1277) -> 538927.59 | BQ62: =SUMIF($F$4:$F$1277,$BM62,$AF$4:$AF$1277) -> 1190039.2 | BR62: =SUMIF($F$4:$F$1277,$BM62,$AH$4:$AH$1277) -> 1970849.2 | BS62: =SUMIF($F$4:$F$1277,$BM62,$AJ$4:$AJ$1277) -> 2901302.3
A63: R060 | B63: AF | C63: Air France | D63: Passenger | E63: CDG | F63: France | G63: EU | H63: SIN | I63: Singapore | J63: APAC | K63: international | L63: B787-9 | M63: 365 | N63: =M63/365 -> 1 | O63: 10750 | P63: =M63*O63 -> 3923750 | Q63: =IFERROR(VLOOKUP(G63,SCENARIOS!$A$13:$E$18,2,0),0.025) -> 0.025 | R63: =IFERROR(VLOOKUP(L63,INPUTS!$A$107:$B$120,2,0),0.0082) -> 0.0079 | S63: =O63*R63 -> 84.925 | T63: =M63*S63 -> 30997.625 | U63: =T63/INPUTS!$B$7*1000 -> 38747031 | V63: =T63*INPUTS!$B$6 -> 97952.495 | W63: Yes | X63: Yes | Y63: =IFERROR(VLOOKUP(E63,INPUTS!$A$44:$B$103,2,0),0) -> 0.02 | Z63: =T63*Y63 -> 619.9525 | AA63: =IFERROR(VLOOKUP(E63,INPUTS!$A$44:$C$103,3,0),SCENARIOS!$J$23) -> 0.06 | AB63: =$T63*AA63*(1+$Q63)^AB$2 -> 2104.2581 | AC63: =IFERROR(VLOOKUP($E63,INPUTS!$A$44:$G$103,4,0),SCENARIOS!$K$23) -> 0.15 | AD63: =$T63*AC63*(1+$Q63)^AD$2 -> 5951.9371 | AE63: =IFERROR(VLOOKUP($E63,INPUTS!$A$44:$G$103,5,0),SCENARIOS!$L$23) -> 0.3 | AF63: =$T63*AE63*(1+$Q63)^AF$2 -> 13468.141 | AG63: =IFERROR(VLOOKUP($E63,INPUTS!$A$44:$G$103,6,0),SCENARIOS!$M$23) -> 0.4 | AH63: =$T63*AG63*(1+$Q63)^AH$2 -> 20317.287 | AI63: =IFERROR(VLOOKUP($E63,INPUTS!$A$44:$G$103,7,0),SCENARIOS!$N$23) -> 0.5 | AJ63: =$T63*AI63*(1+$Q63)^AJ$2 -> 28733.932 | AL63: =IF(H63="MULTI","MULTI",IF(COUNTIFS($E$4:$E$1277,H63,$H$4:$H$1277,E63)>0,"Y","N")) -> Y | AM63: =T63*((1+Q63)^25) -> 57467.864 | BC63: JNB | BD63: =SUMIF($E$4:$E$1277,$BC63,$Z$4:$Z$1277) -> 0 | BE63: =SUMIF($E$4:$E$1277,$BC63,$AB$4:$AB$1277) -> 0 | BF63: =SUMIF($E$4:$E$1277,$BC63,$AD$4:$AD$1277) -> 0 | BG63: =SUMIF($E$4:$E$1277,$BC63,$AF$4:$AF$1277) -> 0 | BH63: =SUMIF($E$4:$E$1277,$BC63,$AH$4:$AH$1277) -> 0 | BI63: =SUMIF($E$4:$E$1277,$BC63,$AJ$4:$AJ$1277) -> 0 | BM63: Vietnam | BN63: =SUMIF($F$4:$F$1277,$BM63,$Z$4:$Z$1277) -> 0 | BO63: =SUMIF($F$4:$F$1277,$BM63,$AB$4:$AB$1277) -> 0 | BP63: =SUMIF($F$4:$F$1277,$BM63,$AD$4:$AD$1277) -> 0 | BQ63: =SUMIF($F$4:$F$1277,$BM63,$AF$4:$AF$1277) -> 0 | BR63: =SUMIF($F$4:$F$1277,$BM63,$AH$4:$AH$1277) -> 0 | BS63: =SUMIF($F$4:$F$1277,$BM63,$AJ$4:$AJ$1277) -> 0
A64: R061 | B64: UA | C64: United Airlines | D64: Passenger | E64: EWR | F64: United States | G64: US | H64: DOH | I64: Qatar | J64: MENA | K64: international | L64: B787-9 | M64: 365 | N64: =M64/365 -> 1 | O64: 11490 | P64: =M64*O64 -> 4193850 | Q64: =IFERROR(VLOOKUP(G64,SCENARIOS!$A$13:$E$18,2,0),0.025) -> 0.02 | R64: =IFERROR(VLOOKUP(L64,INPUTS!$A$107:$B$120,2,0),0.0082) -> 0.0079 | S64: =O64*R64 -> 90.771 | T64: =M64*S64 -> 33131.415 | U64: =T64/INPUTS!$B$7*1000 -> 41414269 | V64: =T64*INPUTS!$B$6 -> 104695.27 | W64: Yes | X64: Yes | Y64: =IFERROR(VLOOKUP(E64,INPUTS!$A$44:$B$103,2,0),0) -> 0.005 | Z64: =T64*Y64 -> 165.65707 | AA64: =IFERROR(VLOOKUP(E64,INPUTS!$A$44:$C$103,3,0),SCENARIOS!$J$23) -> 0.03 | AB64: =$T64*AA64*(1+$Q64)^AB$2 -> 1097.3928 | AC64: =IFERROR(VLOOKUP($E64,INPUTS!$A$44:$G$103,4,0),SCENARIOS!$K$23) -> 0.1 | AD64: =$T64*AC64*(1+$Q64)^AD$2 -> 4038.701 | AE64: =IFERROR(VLOOKUP($E64,INPUTS!$A$44:$G$103,5,0),SCENARIOS!$L$23) -> 0.2 | AF64: =$T64*AE64*(1+$Q64)^AF$2 -> 8918.1045 | AG64: =IFERROR(VLOOKUP($E64,INPUTS!$A$44:$G$103,6,0),SCENARIOS!$M$23) -> 0.3 | AH64: =$T64*AG64*(1+$Q64)^AH$2 -> 14769.462 | AI64: =IFERROR(VLOOKUP($E64,INPUTS!$A$44:$G$103,7,0),SCENARIOS!$N$23) -> 0.4 | AJ64: =$T64*AI64*(1+$Q64)^AJ$2 -> 21742.239 | AL64: =IF(H64="MULTI","MULTI",IF(COUNTIFS($E$4:$E$1277,H64,$H$4:$H$1277,E64)>0,"Y","N")) -> N | AM64: =T64*((1+Q64)^25) -> 54355.598 | BC64: KEF | BD64: =SUMIF($E$4:$E$1277,$BC64,$Z$4:$Z$1277) -> 0 | BE64: =SUMIF($E$4:$E$1277,$BC64,$AB$4:$AB$1277) -> 0 | BF64: =SUMIF($E$4:$E$1277,$BC64,$AD$4:$AD$1277) -> 0 | BG64: =SUMIF($E$4:$E$1277,$BC64,$AF$4:$AF$1277) -> 0 | BH64: =SUMIF($E$4:$E$1277,$BC64,$AH$4:$AH$1277) -> 0 | BI64: =SUMIF($E$4:$E$1277,$BC64,$AJ$4:$AJ$1277) -> 0 | BM64: 0
A65: R062 | B65: DL | C65: Delta Air Lines | D65: Passenger | E65: ATL | F65: United States | G65: US | H65: GRU | I65: Brazil | J65: LATAM | K65: international | L65: B787-9 | M65: 365 | N65: =M65/365 -> 1 | O65: 9650 | P65: =M65*O65 -> 3522250 | Q65: =IFERROR(VLOOKUP(G65,SCENARIOS!$A$13:$E$18,2,0),0.025) -> 0.02 | R65: =IFERROR(VLOOKUP(L65,INPUTS!$A$107:$B$120,2,0),0.0082) -> 0.0079 | S65: =O65*R65 -> 76.235 | T65: =M65*S65 -> 27825.775 | U65: =T65/INPUTS!$B$7*1000 -> 34782219 | V65: =T65*INPUTS!$B$6 -> 87929.449 | W65: Yes | X65: Yes | Y65: =IFERROR(VLOOKUP(E65,INPUTS!$A$44:$B$103,2,0),0) -> 0.005 | Z65: =T65*Y65 -> 139.12887 | AA65: =IFERROR(VLOOKUP(E65,INPUTS!$A$44:$C$103,3,0),SCENARIOS!$J$23) -> 0.03 | AB65: =$T65*AA65*(1+$Q65)^AB$2 -> 921.65712 | AC65: =IFERROR(VLOOKUP($E65,INPUTS!$A$44:$G$103,4,0),SCENARIOS!$K$23) -> 0.1 | AD65: =$T65*AC65*(1+$Q65)^AD$2 -> 3391.9464 | AE65: =IFERROR(VLOOKUP($E65,INPUTS!$A$44:$G$103,5,0),SCENARIOS!$L$23) -> 0.2 | AF65: =$T65*AE65*(1+$Q65)^AF$2 -> 7489.9659 | AG65: =IFERROR(VLOOKUP($E65,INPUTS!$A$44:$G$103,6,0),SCENARIOS!$M$23) -> 0.3 | AH65: =$T65*AG65*(1+$Q65)^AH$2 -> 12404.291 | AI65: =IFERROR(VLOOKUP($E65,INPUTS!$A$44:$G$103,7,0),SCENARIOS!$N$23) -> 0.4 | AJ65: =$T65*AI65*(1+$Q65)^AJ$2 -> 18260.453 | AL65: =IF(H65="MULTI","MULTI",IF(COUNTIFS($E$4:$E$1277,H65,$H$4:$H$1277,E65)>0,"Y","N")) -> N | AM65: =T65*((1+Q65)^25) -> 45651.133 | BC65: KUL | BD65: =SUMIF($E$4:$E$1277,$BC65,$Z$4:$Z$1277) -> 0 | BE65: =SUMIF($E$4:$E$1277,$BC65,$AB$4:$AB$1277) -> 0 | BF65: =SUMIF($E$4:$E$1277,$BC65,$AD$4:$AD$1277) -> 0 | BG65: =SUMIF($E$4:$E$1277,$BC65,$AF$4:$AF$1277) -> 0 | BH65: =SUMIF($E$4:$E$1277,$BC65,$AH$4:$AH$1277) -> 0 | BI65: =SUMIF($E$4:$E$1277,$BC65,$AJ$4:$AJ$1277) -> 0 | BM65: Total | BN65: =SUM(BN4:BN63) -> 783907.49 | BO65: =SUM(BO4:BO63) -> 4358968.6 | BP65: =SUM(BP4:BP63) -> 10698610 | BQ65: =SUM(BQ4:BQ63) -> 24713789 | BR65: =SUM(BR4:BR63) -> 39067846 | BS65: =SUM(BS4:BS63) -> 57477512
A66: R063 | B66: EK | C66: Emirates | D66: Passenger | E66: DXB | F66: UAE | G66: MENA | H66: NRT | I66: Japan | J66: APAC | K66: international | L66: A380-800 | M66: 730 | N66: =M66/365 -> 2 | O66: 7040 | P66: =M66*O66 -> 5139200 | Q66: =IFERROR(VLOOKUP(G66,SCENARIOS!$A$13:$E$18,2,0),0.025) -> 0.045 | R66: =IFERROR(VLOOKUP(L66,INPUTS!$A$107:$B$120,2,0),0.0082) -> 0.0105 | S66: =O66*R66 -> 73.92 | T66: =M66*S66 -> 53961.6 | U66: =T66/INPUTS!$B$7*1000 -> 67452000 | V66: =T66*INPUTS!$B$6 -> 170518.66 | W66: Yes | X66: Yes | Y66: =IFERROR(VLOOKUP(E66,INPUTS!$A$44:$B$103,2,0),0) -> 0 | Z66: =T66*Y66 -> 0 | AA66: =IFERROR(VLOOKUP(E66,INPUTS!$A$44:$C$103,3,0),SCENARIOS!$J$23) -> 0 | AB66: =$T66*AA66*(1+$Q66)^AB$2 -> 0 | AC66: =IFERROR(VLOOKUP($E66,INPUTS!$A$44:$G$103,4,0),SCENARIOS!$K$23) -> 0 | AD66: =$T66*AC66*(1+$Q66)^AD$2 -> 0 | AE66: =IFERROR(VLOOKUP($E66,INPUTS!$A$44:$G$103,5,0),SCENARIOS!$L$23) -> 0 | AF66: =$T66*AE66*(1+$Q66)^AF$2 -> 0 | AG66: =IFERROR(VLOOKUP($E66,INPUTS!$A$44:$G$103,6,0),SCENARIOS!$M$23) -> 0 | AH66: =$T66*AG66*(1+$Q66)^AH$2 -> 0 | AI66: =IFERROR(VLOOKUP($E66,INPUTS!$A$44:$G$103,7,0),SCENARIOS!$N$23) -> 0 | AJ66: =$T66*AI66*(1+$Q66)^AJ$2 -> 0 | AL66: =IF(H66="MULTI","MULTI",IF(COUNTIFS($E$4:$E$1277,H66,$H$4:$H$1277,E66)>0,"Y","N")) -> N | AM66: =T66*((1+Q66)^25) -> 162178.05 | BC66: KWI | BD66: =SUMIF($E$4:$E$1277,$BC66,$Z$4:$Z$1277) -> 0 | BE66: =SUMIF($E$4:$E$1277,$BC66,$AB$4:$AB$1277) -> 0 | BF66: =SUMIF($E$4:$E$1277,$BC66,$AD$4:$AD$1277) -> 0 | BG66: =SUMIF($E$4:$E$1277,$BC66,$AF$4:$AF$1277) -> 0 | BH66: =SUMIF($E$4:$E$1277,$BC66,$AH$4:$AH$1277) -> 0 | BI66: =SUMIF($E$4:$E$1277,$BC66,$AJ$4:$AJ$1277) -> 0
A67: R064 | B67: LA | C67: LATAM Airlines | D67: Passenger | E67: GRU | F67: Brazil | G67: LATAM | H67: LHR | I67: United Kingdom | J67: EU | K67: international | L67: B787-9 | M67: 365 | N67: =M67/365 -> 1 | O67: 10650 | P67: =M67*O67 -> 3887250 | Q67: =IFERROR(VLOOKUP(G67,SCENARIOS!$A$13:$E$18,2,0),0.025) -> 0.035 | R67: =IFERROR(VLOOKUP(L67,INPUTS!$A$107:$B$120,2,0),0.0082) -> 0.0079 | S67: =O67*R67 -> 84.135 | T67: =M67*S67 -> 30709.275 | U67: =T67/INPUTS!$B$7*1000 -> 38386594 | V67: =T67*INPUTS!$B$6 -> 97041.309 | W67: Yes | X67: Yes | Y67: =IFERROR(VLOOKUP(E67,INPUTS!$A$44:$B$103,2,0),0) -> 0 | Z67: =T67*Y67 -> 0 | AA67: =IFERROR(VLOOKUP(E67,INPUTS!$A$44:$C$103,3,0),SCENARIOS!$J$23) -> 0 | AB67: =$T67*AA67*(1+$Q67)^AB$2 -> 0 | AC67: =IFERROR(VLOOKUP($E67,INPUTS!$A$44:$G$103,4,0),SCENARIOS!$K$23) -> 0 | AD67: =$T67*AC67*(1+$Q67)^AD$2 -> 0 | AE67: =IFERROR(VLOOKUP($E67,INPUTS!$A$44:$G$103,5,0),SCENARIOS!$L$23) -> 0 | AF67: =$T67*AE67*(1+$Q67)^AF$2 -> 0 | AG67: =IFERROR(VLOOKUP($E67,INPUTS!$A$44:$G$103,6,0),SCENARIOS!$M$23) -> 0 | AH67: =$T67*AG67*(1+$Q67)^AH$2 -> 0 | AI67: =IFERROR(VLOOKUP($E67,INPUTS!$A$44:$G$103,7,0),SCENARIOS!$N$23) -> 0 | AJ67: =$T67*AI67*(1+$Q67)^AJ$2 -> 0 | AL67: =IF(H67="MULTI","MULTI",IF(COUNTIFS($E$4:$E$1277,H67,$H$4:$H$1277,E67)>0,"Y","N")) -> Y | AM67: =T67*((1+Q67)^25) -> 72573.54 | BC67: LAX | BD67: =SUMIF($E$4:$E$1277,$BC67,$Z$4:$Z$1277) -> 3086.0392 | BE67: =SUMIF($E$4:$E$1277,$BC67,$AB$4:$AB$1277) -> 20443.42 | BF67: =SUMIF($E$4:$E$1277,$BC67,$AD$4:$AD$1277) -> 75237.291 | BG67: =SUMIF($E$4:$E$1277,$BC67,$AF$4:$AF$1277) -> 166136.1 | BH67: =SUMIF($E$4:$E$1277,$BC67,$AH$4:$AH$1277) -> 275141.51 | BI67: =SUMIF($E$4:$E$1277,$BC67,$AJ$4:$AJ$1277) -> 405037.95
A68: R065 | B68: FX | C68: FedEx Express | D68: Cargo | E68: MEM | F68: United States | G68: US | H68: CDG | I68: France | J68: EU | K68: international | L68: B777F | M68: 365 | N68: =M68/365 -> 1 | O68: 7480 | P68: =M68*O68 -> 2730200 | Q68: =IFERROR(VLOOKUP(G68,SCENARIOS!$A$13:$E$18,2,0),0.025) -> 0.02 | R68: =IFERROR(VLOOKUP(L68,INPUTS!$A$107:$B$120,2,0),0.0082) -> 0.0082 | S68: =O68*R68 -> 61.336 | T68: =M68*S68 -> 22387.64 | U68: =T68/INPUTS!$B$7*1000 -> 27984550 | V68: =T68*INPUTS!$B$6 -> 70744.942 | W68: Yes | X68: Yes | Y68: =IFERROR(VLOOKUP(E68,INPUTS!$A$44:$B$103,2,0),0) -> 0 | Z68: =T68*Y68 -> 0 | AA68: =IFERROR(VLOOKUP(E68,INPUTS!$A$44:$C$103,3,0),SCENARIOS!$J$23) -> 0 | AB68: =$T68*AA68*(1+$Q68)^AB$2 -> 0 | AC68: =IFERROR(VLOOKUP($E68,INPUTS!$A$44:$G$103,4,0),SCENARIOS!$K$23) -> 0 | AD68: =$T68*AC68*(1+$Q68)^AD$2 -> 0 | AE68: =IFERROR(VLOOKUP($E68,INPUTS!$A$44:$G$103,5,0),SCENARIOS!$L$23) -> 0 | AF68: =$T68*AE68*(1+$Q68)^AF$2 -> 0 | AG68: =IFERROR(VLOOKUP($E68,INPUTS!$A$44:$G$103,6,0),SCENARIOS!$M$23) -> 0 | AH68: =$T68*AG68*(1+$Q68)^AH$2 -> 0 | AI68: =IFERROR(VLOOKUP($E68,INPUTS!$A$44:$G$103,7,0),SCENARIOS!$N$23) -> 0 | AJ68: =$T68*AI68*(1+$Q68)^AJ$2 -> 0 | AL68: =IF(H68="MULTI","MULTI",IF(COUNTIFS($E$4:$E$1277,H68,$H$4:$H$1277,E68)>0,"Y","N")) -> N | AM68: =T68*((1+Q68)^25) -> 36729.296 | BC68: LED | BD68: =SUMIF($E$4:$E$1277,$BC68,$Z$4:$Z$1277) -> 0 | BE68: =SUMIF($E$4:$E$1277,$BC68,$AB$4:$AB$1277) -> 0 | BF68: =SUMIF($E$4:$E$1277,$BC68,$AD$4:$AD$1277) -> 0 | BG68: =SUMIF($E$4:$E$1277,$BC68,$AF$4:$AF$1277) -> 0 | BH68: =SUMIF($E$4:$E$1277,$BC68,$AH$4:$AH$1277) -> 0 | BI68: =SUMIF($E$4:$E$1277,$BC68,$AJ$4:$AJ$1277) -> 0
A69: R066 | B69: FX | C69: FedEx Express | D69: Cargo | E69: MEM | F69: United States | G69: US | H69: NRT | I69: Japan | J69: APAC | K69: international | L69: B777F | M69: 365 | N69: =M69/365 -> 1 | O69: 11200 | P69: =M69*O69 -> 4088000 | Q69: =IFERROR(VLOOKUP(G69,SCENARIOS!$A$13:$E$18,2,0),0.025) -> 0.02 | R69: =IFERROR(VLOOKUP(L69,INPUTS!$A$107:$B$120,2,0),0.0082) -> 0.0082 | S69: =O69*R69 -> 91.84 | T69: =M69*S69 -> 33521.6 | U69: =T69/INPUTS!$B$7*1000 -> 41902000 | V69: =T69*INPUTS!$B$6 -> 105928.26 | W69: Yes | X69: Yes | Y69: =IFERROR(VLOOKUP(E69,INPUTS!$A$44:$B$103,2,0),0) -> 0 | Z69: =T69*Y69 -> 0 | AA69: =IFERROR(VLOOKUP(E69,INPUTS!$A$44:$C$103,3,0),SCENARIOS!$J$23) -> 0 | AB69: =$T69*AA69*(1+$Q69)^AB$2 -> 0 | AC69: =IFERROR(VLOOKUP($E69,INPUTS!$A$44:$G$103,4,0),SCENARIOS!$K$23) -> 0 | AD69: =$T69*AC69*(1+$Q69)^AD$2 -> 0 | AE69: =IFERROR(VLOOKUP($E69,INPUTS!$A$44:$G$103,5,0),SCENARIOS!$L$23) -> 0 | AF69: =$T69*AE69*(1+$Q69)^AF$2 -> 0 | AG69: =IFERROR(VLOOKUP($E69,INPUTS!$A$44:$G$103,6,0),SCENARIOS!$M$23) -> 0 | AH69: =$T69*AG69*(1+$Q69)^AH$2 -> 0 | AI69: =IFERROR(VLOOKUP($E69,INPUTS!$A$44:$G$103,7,0),SCENARIOS!$N$23) -> 0 | AJ69: =$T69*AI69*(1+$Q69)^AJ$2 -> 0 | AL69: =IF(H69="MULTI","MULTI",IF(COUNTIFS($E$4:$E$1277,H69,$H$4:$H$1277,E69)>0,"Y","N")) -> N | AM69: =T69*((1+Q69)^25) -> 54995.738 | BC69: LGW | BD69: =SUMIF($E$4:$E$1277,$BC69,$Z$4:$Z$1277) -> 42989.427 | BE69: =SUMIF($E$4:$E$1277,$BC69,$AB$4:$AB$1277) -> 243192.95 | BF69: =SUMIF($E$4:$E$1277,$BC69,$AD$4:$AD$1277) -> 412725.76 | BG69: =SUMIF($E$4:$E$1277,$BC69,$AF$4:$AF$1277) -> 933922.62 | BH69: =SUMIF($E$4:$E$1277,$BC69,$AH$4:$AH$1277) -> 1408863.6 | BI69: =SUMIF($E$4:$E$1277,$BC69,$AJ$4:$AJ$1277) -> 1992499.9
A70: R067 | B70: FX | C70: FedEx Express | D70: Cargo | E70: MEM | F70: United States | G70: US | H70: SIN | I70: Singapore | J70: APAC | K70: international | L70: B777F | M70: 182 | N70: =M70/365 -> 0.49863014 | O70: 14420 | P70: =M70*O70 -> 2624440 | Q70: =IFERROR(VLOOKUP(G70,SCENARIOS!$A$13:$E$18,2,0),0.025) -> 0.02 | R70: =IFERROR(VLOOKUP(L70,INPUTS!$A$107:$B$120,2,0),0.0082) -> 0.0082 | S70: =O70*R70 -> 118.244 | T70: =M70*S70 -> 21520.408 | U70: =T70/INPUTS!$B$7*1000 -> 26900510 | V70: =T70*INPUTS!$B$6 -> 68004.489 | W70: Yes | X70: Yes | Y70: =IFERROR(VLOOKUP(E70,INPUTS!$A$44:$B$103,2,0),0) -> 0 | Z70: =T70*Y70 -> 0 | AA70: =IFERROR(VLOOKUP(E70,INPUTS!$A$44:$C$103,3,0),SCENARIOS!$J$23) -> 0 | AB70: =$T70*AA70*(1+$Q70)^AB$2 -> 0 | AC70: =IFERROR(VLOOKUP($E70,INPUTS!$A$44:$G$103,4,0),SCENARIOS!$K$23) -> 0 | AD70: =$T70*AC70*(1+$Q70)^AD$2 -> 0 | AE70: =IFERROR(VLOOKUP($E70,INPUTS!$A$44:$G$103,5,0),SCENARIOS!$L$23) -> 0 | AF70: =$T70*AE70*(1+$Q70)^AF$2 -> 0 | AG70: =IFERROR(VLOOKUP($E70,INPUTS!$A$44:$G$103,6,0),SCENARIOS!$M$23) -> 0 | AH70: =$T70*AG70*(1+$Q70)^AH$2 -> 0 | AI70: =IFERROR(VLOOKUP($E70,INPUTS!$A$44:$G$103,7,0),SCENARIOS!$N$23) -> 0 | AJ70: =$T70*AI70*(1+$Q70)^AJ$2 -> 0 | AL70: =IF(H70="MULTI","MULTI",IF(COUNTIFS($E$4:$E$1277,H70,$H$4:$H$1277,E70)>0,"Y","N")) -> N | AM70: =T70*((1+Q70)^25) -> 35306.51 | BC70: LHR | BD70: =SUMIF($E$4:$E$1277,$BC70,$Z$4:$Z$1277) -> 33272.882 | BE70: =SUMIF($E$4:$E$1277,$BC70,$AB$4:$AB$1277) -> 188226.06 | BF70: =SUMIF($E$4:$E$1277,$BC70,$AD$4:$AD$1277) -> 319440.76 | BG70: =SUMIF($E$4:$E$1277,$BC70,$AF$4:$AF$1277) -> 722835.8 | BH70: =SUMIF($E$4:$E$1277,$BC70,$AH$4:$AH$1277) -> 1090429.8 | BI70: =SUMIF($E$4:$E$1277,$BC70,$AJ$4:$AJ$1277) -> 1542151.6
A71: R068 | B71: FX | C71: FedEx Express | D71: Cargo | E71: MEM | F71: United States | G71: US | H71: GRU | I71: Brazil | J71: LATAM | K71: international | L71: B777F | M71: 365 | N71: =M71/365 -> 1 | O71: 9700 | P71: =M71*O71 -> 3540500 | Q71: =IFERROR(VLOOKUP(G71,SCENARIOS!$A$13:$E$18,2,0),0.025) -> 0.02 | R71: =IFERROR(VLOOKUP(L71,INPUTS!$A$107:$B$120,2,0),0.0082) -> 0.0082 | S71: =O71*R71 -> 79.54 | T71: =M71*S71 -> 29032.1 | U71: =T71/INPUTS!$B$7*1000 -> 36290125 | V71: =T71*INPUTS!$B$6 -> 91741.436 | W71: Yes | X71: Yes | Y71: =IFERROR(VLOOKUP(E71,INPUTS!$A$44:$B$103,2,0),0) -> 0 | Z71: =T71*Y71 -> 0 | AA71: =IFERROR(VLOOKUP(E71,INPUTS!$A$44:$C$103,3,0),SCENARIOS!$J$23) -> 0 | AB71: =$T71*AA71*(1+$Q71)^AB$2 -> 0 | AC71: =IFERROR(VLOOKUP($E71,INPUTS!$A$44:$G$103,4,0),SCENARIOS!$K$23) -> 0 | AD71: =$T71*AC71*(1+$Q71)^AD$2 -> 0 | AE71: =IFERROR(VLOOKUP($E71,INPUTS!$A$44:$G$103,5,0),SCENARIOS!$L$23) -> 0 | AF71: =$T71*AE71*(1+$Q71)^AF$2 -> 0 | AG71: =IFERROR(VLOOKUP($E71,INPUTS!$A$44:$G$103,6,0),SCENARIOS!$M$23) -> 0 | AH71: =$T71*AG71*(1+$Q71)^AH$2 -> 0 | AI71: =IFERROR(VLOOKUP($E71,INPUTS!$A$44:$G$103,7,0),SCENARIOS!$N$23) -> 0 | AJ71: =$T71*AI71*(1+$Q71)^AJ$2 -> 0 | AL71: =IF(H71="MULTI","MULTI",IF(COUNTIFS($E$4:$E$1277,H71,$H$4:$H$1277,E71)>0,"Y","N")) -> N | AM71: =T71*((1+Q71)^25) -> 47630.237 | BC71: LIM | BD71: =SUMIF($E$4:$E$1277,$BC71,$Z$4:$Z$1277) -> 0 | BE71: =SUMIF($E$4:$E$1277,$BC71,$AB$4:$AB$1277) -> 0 | BF71: =SUMIF($E$4:$E$1277,$BC71,$AD$4:$AD$1277) -> 0 | BG71: =SUMIF($E$4:$E$1277,$BC71,$AF$4:$AF$1277) -> 0 | BH71: =SUMIF($E$4:$E$1277,$BC71,$AH$4:$AH$1277) -> 0 | BI71: =SUMIF($E$4:$E$1277,$BC71,$AJ$4:$AJ$1277) -> 0
A72: R069 | B72: FX | C72: FedEx Express | D72: Cargo | E72: MEM | F72: United States | G72: US | H72: DXB | I72: UAE | J72: MENA | K72: international | L72: B777F | M72: 365 | N72: =M72/365 -> 1 | O72: 12030 | P72: =M72*O72 -> 4390950 | Q72: =IFERROR(VLOOKUP(G72,SCENARIOS!$A$13:$E$18,2,0),0.025) -> 0.02 | R72: =IFERROR(VLOOKUP(L72,INPUTS!$A$107:$B$120,2,0),0.0082) -> 0.0082 | S72: =O72*R72 -> 98.646 | T72: =M72*S72 -> 36005.79 | U72: =T72/INPUTS!$B$7*1000 -> 45007238 | V72: =T72*INPUTS!$B$6 -> 113778.3 | W72: Yes | X72: Yes | Y72: =IFERROR(VLOOKUP(E72,INPUTS!$A$44:$B$103,2,0),0) -> 0 | Z72: =T72*Y72 -> 0 | AA72: =IFERROR(VLOOKUP(E72,INPUTS!$A$44:$C$103,3,0),SCENARIOS!$J$23) -> 0 | AB72: =$T72*AA72*(1+$Q72)^AB$2 -> 0 | AC72: =IFERROR(VLOOKUP($E72,INPUTS!$A$44:$G$103,4,0),SCENARIOS!$K$23) -> 0 | AD72: =$T72*AC72*(1+$Q72)^AD$2 -> 0 | AE72: =IFERROR(VLOOKUP($E72,INPUTS!$A$44:$G$103,5,0),SCENARIOS!$L$23) -> 0 | AF72: =$T72*AE72*(1+$Q72)^AF$2 -> 0 | AG72: =IFERROR(VLOOKUP($E72,INPUTS!$A$44:$G$103,6,0),SCENARIOS!$M$23) -> 0 | AH72: =$T72*AG72*(1+$Q72)^AH$2 -> 0 | AI72: =IFERROR(VLOOKUP($E72,INPUTS!$A$44:$G$103,7,0),SCENARIOS!$N$23) -> 0 | AJ72: =$T72*AI72*(1+$Q72)^AJ$2 -> 0 | AL72: =IF(H72="MULTI","MULTI",IF(COUNTIFS($E$4:$E$1277,H72,$H$4:$H$1277,E72)>0,"Y","N")) -> N | AM72: =T72*((1+Q72)^25) -> 59071.315 | BC72: LIS | BD72: =SUMIF($E$4:$E$1277,$BC72,$Z$4:$Z$1277) -> 51612.63 | BE72: =SUMIF($E$4:$E$1277,$BC72,$AB$4:$AB$1277) -> 175184.86 | BF72: =SUMIF($E$4:$E$1277,$BC72,$AD$4:$AD$1277) -> 495513.98 | BG72: =SUMIF($E$4:$E$1277,$BC72,$AF$4:$AF$1277) -> 1121257.2 | BH72: =SUMIF($E$4:$E$1277,$BC72,$AH$4:$AH$1277) -> 1691466.1 | BI72: =SUMIF($E$4:$E$1277,$BC72,$AJ$4:$AJ$1277) -> 2392173.3
A73: R070 | B73: FX | C73: FedEx Express | D73: Cargo | E73: ANC | F73: United States | G73: US | H73: NRT | I73: Japan | J73: APAC | K73: international | L73: B747-8F | M73: 730 | N73: =M73/365 -> 2 | O73: 5650 | P73: =M73*O73 -> 4124500 | Q73: =IFERROR(VLOOKUP(G73,SCENARIOS!$A$13:$E$18,2,0),0.025) -> 0.02 | R73: =IFERROR(VLOOKUP(L73,INPUTS!$A$107:$B$120,2,0),0.0082) -> 0.0096 | S73: =O73*R73 -> 54.24 | T73: =M73*S73 -> 39595.2 | U73: =T73/INPUTS!$B$7*1000 -> 49494000 | V73: =T73*INPUTS!$B$6 -> 125120.83 | W73: Yes | X73: Yes | Y73: =IFERROR(VLOOKUP(E73,INPUTS!$A$44:$B$103,2,0),0) -> 0.005 | Z73: =T73*Y73 -> 197.976 | AA73: =IFERROR(VLOOKUP(E73,INPUTS!$A$44:$C$103,3,0),SCENARIOS!$J$23) -> 0.03 | AB73: =$T73*AA73*(1+$Q73)^AB$2 -> 1311.489 | AC73: =IFERROR(VLOOKUP($E73,INPUTS!$A$44:$G$103,4,0),SCENARIOS!$K$23) -> 0.1 | AD73: =$T73*AC73*(1+$Q73)^AD$2 -> 4826.6328 | AE73: =IFERROR(VLOOKUP($E73,INPUTS!$A$44:$G$103,5,0),SCENARIOS!$L$23) -> 0.2 | AF73: =$T73*AE73*(1+$Q73)^AF$2 -> 10657.985 | AG73: =IFERROR(VLOOKUP($E73,INPUTS!$A$44:$G$103,6,0),SCENARIOS!$M$23) -> 0.3 | AH73: =$T73*AG73*(1+$Q73)^AH$2 -> 17650.915 | AI73: =IFERROR(VLOOKUP($E73,INPUTS!$A$44:$G$103,7,0),SCENARIOS!$N$23) -> 0.4 | AJ73: =$T73*AI73*(1+$Q73)^AJ$2 -> 25984.049 | AL73: =IF(H73="MULTI","MULTI",IF(COUNTIFS($E$4:$E$1277,H73,$H$4:$H$1277,E73)>0,"Y","N")) -> N | AM73: =T73*((1+Q73)^25) -> 64960.122 | BC73: LTN | BD73: =SUMIF($E$4:$E$1277,$BC73,$Z$4:$Z$1277) -> 48240 | BE73: =SUMIF($E$4:$E$1277,$BC73,$AB$4:$AB$1277) -> 272895.66 | BF73: =SUMIF($E$4:$E$1277,$BC73,$AD$4:$AD$1277) -> 463134.59 | BG73: =SUMIF($E$4:$E$1277,$BC73,$AF$4:$AF$1277) -> 1047988.6 | BH73: =SUMIF($E$4:$E$1277,$BC73,$AH$4:$AH$1277) -> 1580937.1 | BI73: =SUMIF($E$4:$E$1277,$BC73,$AJ$4:$AJ$1277) -> 2235856.6
A74: R071 | B74: FX | C74: FedEx Express | D74: Cargo | E74: IND | F74: United States | G74: US | H74: CGN | I74: Germany | J74: EU | K74: international | L74: B777F | M74: 365 | N74: =M74/365 -> 1 | O74: 7580 | P74: =M74*O74 -> 2766700 | Q74: =IFERROR(VLOOKUP(G74,SCENARIOS!$A$13:$E$18,2,0),0.025) -> 0.02 | R74: =IFERROR(VLOOKUP(L74,INPUTS!$A$107:$B$120,2,0),0.0082) -> 0.0082 | S74: =O74*R74 -> 62.156 | T74: =M74*S74 -> 22686.94 | U74: =T74/INPUTS!$B$7*1000 -> 28358675 | V74: =T74*INPUTS!$B$6 -> 71690.73 | W74: Yes | X74: Yes | Y74: =IFERROR(VLOOKUP(E74,INPUTS!$A$44:$B$103,2,0),0) -> 0 | Z74: =T74*Y74 -> 0 | AA74: =IFERROR(VLOOKUP(E74,INPUTS!$A$44:$C$103,3,0),SCENARIOS!$J$23) -> 0 | AB74: =$T74*AA74*(1+$Q74)^AB$2 -> 0 | AC74: =IFERROR(VLOOKUP($E74,INPUTS!$A$44:$G$103,4,0),SCENARIOS!$K$23) -> 0 | AD74: =$T74*AC74*(1+$Q74)^AD$2 -> 0 | AE74: =IFERROR(VLOOKUP($E74,INPUTS!$A$44:$G$103,5,0),SCENARIOS!$L$23) -> 0 | AF74: =$T74*AE74*(1+$Q74)^AF$2 -> 0 | AG74: =IFERROR(VLOOKUP($E74,INPUTS!$A$44:$G$103,6,0),SCENARIOS!$M$23) -> 0 | AH74: =$T74*AG74*(1+$Q74)^AH$2 -> 0 | AI74: =IFERROR(VLOOKUP($E74,INPUTS!$A$44:$G$103,7,0),SCENARIOS!$N$23) -> 0 | AJ74: =$T74*AI74*(1+$Q74)^AJ$2 -> 0 | AL74: =IF(H74="MULTI","MULTI",IF(COUNTIFS($E$4:$E$1277,H74,$H$4:$H$1277,E74)>0,"Y","N")) -> N | AM74: =T74*((1+Q74)^25) -> 37220.33 | BC74: LUX | BD74: =SUMIF($E$4:$E$1277,$BC74,$Z$4:$Z$1277) -> 0 | BE74: =SUMIF($E$4:$E$1277,$BC74,$AB$4:$AB$1277) -> 0 | BF74: =SUMIF($E$4:$E$1277,$BC74,$AD$4:$AD$1277) -> 0 | BG74: =SUMIF($E$4:$E$1277,$BC74,$AF$4:$AF$1277) -> 0 | BH74: =SUMIF($E$4:$E$1277,$BC74,$AH$4:$AH$1277) -> 0 | BI74: =SUMIF($E$4:$E$1277,$BC74,$AJ$4:$AJ$1277) -> 0
A75: R072 | B75: 5X | C75: UPS Airlines | D75: Cargo | E75: SDF | F75: United States | G75: US | H75: CGN | I75: Germany | J75: EU | K75: international | L75: B747-8F | M75: 365 | N75: =M75/365 -> 1 | O75: 7390 | P75: =M75*O75 -> 2697350 | Q75: =IFERROR(VLOOKUP(G75,SCENARIOS!$A$13:$E$18,2,0),0.025) -> 0.02 | R75: =IFERROR(VLOOKUP(L75,INPUTS!$A$107:$B$120,2,0),0.0082) -> 0.0096 | S75: =O75*R75 -> 70.944 | T75: =M75*S75 -> 25894.56 | U75: =T75/INPUTS!$B$7*1000 -> 32368200 | V75: =T75*INPUTS!$B$6 -> 81826.81 | W75: Yes | X75: Yes | Y75: =IFERROR(VLOOKUP(E75,INPUTS!$A$44:$B$103,2,0),0) -> 0.005 | Z75: =T75*Y75 -> 129.4728 | AA75: =IFERROR(VLOOKUP(E75,INPUTS!$A$44:$C$103,3,0),SCENARIOS!$J$23) -> 0.03 | AB75: =$T75*AA75*(1+$Q75)^AB$2 -> 857.6906 | AC75: =IFERROR(VLOOKUP($E75,INPUTS!$A$44:$G$103,4,0),SCENARIOS!$K$23) -> 0.1 | AD75: =$T75*AC75*(1+$Q75)^AD$2 -> 3156.5324 | AE75: =IFERROR(VLOOKUP($E75,INPUTS!$A$44:$G$103,5,0),SCENARIOS!$L$23) -> 0.2 | AF75: =$T75*AE75*(1+$Q75)^AF$2 -> 6970.1337 | AG75: =IFERROR(VLOOKUP($E75,INPUTS!$A$44:$G$103,6,0),SCENARIOS!$M$23) -> 0.3 | AH75: =$T75*AG75*(1+$Q75)^AH$2 -> 11543.386 | AI75: =IFERROR(VLOOKUP($E75,INPUTS!$A$44:$G$103,7,0),SCENARIOS!$N$23) -> 0.4 | AJ75: =$T75*AI75*(1+$Q75)^AJ$2 -> 16993.108 | AL75: =IF(H75="MULTI","MULTI",IF(COUNTIFS($E$4:$E$1277,H75,$H$4:$H$1277,E75)>0,"Y","N")) -> N | AM75: =T75*((1+Q75)^25) -> 42482.77 | BC75: MAD | BD75: =SUMIF($E$4:$E$1277,$BC75,$Z$4:$Z$1277) -> 52008.566 | BE75: =SUMIF($E$4:$E$1277,$BC75,$AB$4:$AB$1277) -> 176528.75 | BF75: =SUMIF($E$4:$E$1277,$BC75,$AD$4:$AD$1277) -> 499315.21 | BG75: =SUMIF($E$4:$E$1277,$BC75,$AF$4:$AF$1277) -> 1129858.7 | BH75: =SUMIF($E$4:$E$1277,$BC75,$AH$4:$AH$1277) -> 1704441.8 | BI75: =SUMIF($E$4:$E$1277,$BC75,$AJ$4:$AJ$1277) -> 2410524.3
A76: R073 | B76: 5X | C76: UPS Airlines | D76: Cargo | E76: SDF | F76: United States | G76: US | H76: HKG | I76: Hong Kong | J76: APAC | K76: international | L76: B747-8F | M76: 365 | N76: =M76/365 -> 1 | O76: 14200 | P76: =M76*O76 -> 5183000 | Q76: =IFERROR(VLOOKUP(G76,SCENARIOS!$A$13:$E$18,2,0),0.025) -> 0.02 | R76: =IFERROR(VLOOKUP(L76,INPUTS!$A$107:$B$120,2,0),0.0082) -> 0.0096 | S76: =O76*R76 -> 136.32 | T76: =M76*S76 -> 49756.8 | U76: =T76/INPUTS!$B$7*1000 -> 62196000 | V76: =T76*INPUTS!$B$6 -> 157231.49 | W76: Yes | X76: Yes | Y76: =IFERROR(VLOOKUP(E76,INPUTS!$A$44:$B$103,2,0),0) -> 0.005 | Z76: =T76*Y76 -> 248.784 | AA76: =IFERROR(VLOOKUP(E76,INPUTS!$A$44:$C$103,3,0),SCENARIOS!$J$23) -> 0.03 | AB76: =$T76*AA76*(1+$Q76)^AB$2 -> 1648.0658 | AC76: =IFERROR(VLOOKUP($E76,INPUTS!$A$44:$G$103,4,0),SCENARIOS!$K$23) -> 0.1 | AD76: =$T76*AC76*(1+$Q76)^AD$2 -> 6065.3262 | AE76: =IFERROR(VLOOKUP($E76,INPUTS!$A$44:$G$103,5,0),SCENARIOS!$L$23) -> 0.2 | AF76: =$T76*AE76*(1+$Q76)^AF$2 -> 13393.22 | AG76: =IFERROR(VLOOKUP($E76,INPUTS!$A$44:$G$103,6,0),SCENARIOS!$M$23) -> 0.3 | AH76: =$T76*AG76*(1+$Q76)^AH$2 -> 22180.796 | AI76: =IFERROR(VLOOKUP($E76,INPUTS!$A$44:$G$103,7,0),SCENARIOS!$N$23) -> 0.4 | AJ76: =$T76*AI76*(1+$Q76)^AJ$2 -> 32652.522 | AL76: =IF(H76="MULTI","MULTI",IF(COUNTIFS($E$4:$E$1277,H76,$H$4:$H$1277,E76)>0,"Y","N")) -> N | AM76: =T76*((1+Q76)^25) -> 81631.304 | BC76: MCT | BD76: =SUMIF($E$4:$E$1277,$BC76,$Z$4:$Z$1277) -> 0 | BE76: =SUMIF($E$4:$E$1277,$BC76,$AB$4:$AB$1277) -> 0 | BF76: =SUMIF($E$4:$E$1277,$BC76,$AD$4:$AD$1277) -> 0 | BG76: =SUMIF($E$4:$E$1277,$BC76,$AF$4:$AF$1277) -> 0 | BH76: =SUMIF($E$4:$E$1277,$BC76,$AH$4:$AH$1277) -> 0 | BI76: =SUMIF($E$4:$E$1277,$BC76,$AJ$4:$AJ$1277) -> 0
A77: R074 | B77: 5X | C77: UPS Airlines | D77: Cargo | E77: SDF | F77: United States | G77: US | H77: NRT | I77: Japan | J77: APAC | K77: international | L77: B747-8F | M77: 365 | N77: =M77/365 -> 1 | O77: 11100 | P77: =M77*O77 -> 4051500 | Q77: =IFERROR(VLOOKUP(G77,SCENARIOS!$A$13:$E$18,2,0),0.025) -> 0.02 | R77: =IFERROR(VLOOKUP(L77,INPUTS!$A$107:$B$120,2,0),0.0082) -> 0.0096 | S77: =O77*R77 -> 106.56 | T77: =M77*S77 -> 38894.4 | U77: =T77/INPUTS!$B$7*1000 -> 48618000 | V77: =T77*INPUTS!$B$6 -> 122906.3 | W77: Yes | X77: Yes | Y77: =IFERROR(VLOOKUP(E77,INPUTS!$A$44:$B$103,2,0),0) -> 0.005 | Z77: =T77*Y77 -> 194.472 | AA77: =IFERROR(VLOOKUP(E77,INPUTS!$A$44:$C$103,3,0),SCENARIOS!$J$23) -> 0.03 | AB77: =$T77*AA77*(1+$Q77)^AB$2 -> 1288.2768 | AC77: =IFERROR(VLOOKUP($E77,INPUTS!$A$44:$G$103,4,0),SCENARIOS!$K$23) -> 0.1 | AD77: =$T77*AC77*(1+$Q77)^AD$2 -> 4741.2057 | AE77: =IFERROR(VLOOKUP($E77,INPUTS!$A$44:$G$103,5,0),SCENARIOS!$L$23) -> 0.2 | AF77: =$T77*AE77*(1+$Q77)^AF$2 -> 10469.348 | AG77: =IFERROR(VLOOKUP($E77,INPUTS!$A$44:$G$103,6,0),SCENARIOS!$M$23) -> 0.3 | AH77: =$T77*AG77*(1+$Q77)^AH$2 -> 17338.51 | AI77: =IFERROR(VLOOKUP($E77,INPUTS!$A$44:$G$103,7,0),SCENARIOS!$N$23) -> 0.4 | AJ77: =$T77*AI77*(1+$Q77)^AJ$2 -> 25524.154 | AL77: =IF(H77="MULTI","MULTI",IF(COUNTIFS($E$4:$E$1277,H77,$H$4:$H$1277,E77)>0,"Y","N")) -> N | AM77: =T77*((1+Q77)^25) -> 63810.386 | BC77: MEL | BD77: =SUMIF($E$4:$E$1277,$BC77,$Z$4:$Z$1277) -> 0 | BE77: =SUMIF($E$4:$E$1277,$BC77,$AB$4:$AB$1277) -> 237031.32 | BF77: =SUMIF($E$4:$E$1277,$BC77,$AD$4:$AD$1277) -> 576769.68 | BG77: =SUMIF($E$4:$E$1277,$BC77,$AF$4:$AF$1277) -> 1403457 | BH77: =SUMIF($E$4:$E$1277,$BC77,$AH$4:$AH$1277) -> 2561280.1 | BI77: =SUMIF($E$4:$E$1277,$BC77,$AJ$4:$AJ$1277) -> 4154918.4
... A93: R090 | B93: TKC | C93: Turkish Cargo | D93: Cargo | E93: IST | F93: Turkey | G93: ROW | H93: PVG | I93: China | J93: APAC | K93: international | L93: B777F | M93: 365 | N93: =M93/365 -> 1 | O93: 7500 | P93: =M93*O93 -> 2737500 | Q93: =IFERROR(VLOOKUP(G93,SCENARIOS!$A$13:$E$18,2,0),0.025) -> 0.03 | R93: =IFERROR(VLOOKUP(L93,INPUTS!$A$107:$B$120,2,0),0.0082) -> 0.0082 | S93: =O93*R93 -> 61.5 | T93: =M93*S93 -> 22447.5 | U93: =T93/INPUTS!$B$7*1000 -> 28059375 | V93: =T93*INPUTS!$B$6 -> 70934.1 | W93: No | X93: Yes | Y93: =IFERROR(VLOOKUP(E93,INPUTS!$A$44:$B$103,2,0),0) -> 0 | Z93: =T93*Y93 -> 0 | AA93: =IFERROR(VLOOKUP(E93,INPUTS!$A$44:$C$103,3,0),SCENARIOS!$J$23) -> 0 | AB93: =$T93*AA93*(1+$Q93)^AB$2 -> 0 | AC93: =IFERROR(VLOOKUP($E93,INPUTS!$A$44:$G$103,4,0),SCENARIOS!$K$23) -> 0 | AD93: =$T93*AC93*(1+$Q93)^AD$2 -> 0 | AE93: =IFERROR(VLOOKUP($E93,INPUTS!$A$44:$G$103,5,0),SCENARIOS!$L$23) -> 0 | AF93: =$T93*AE93*(1+$Q93)^AF$2 -> 0 | AG93: =IFERROR(VLOOKUP($E93,INPUTS!$A$44:$G$103,6,0),SCENARIOS!$M$23) -> 0 | AH93: =$T93*AG93*(1+$Q93)^AH$2 -> 0 | AI93: =IFERROR(VLOOKUP($E93,INPUTS!$A$44:$G$103,7,0),SCENARIOS!$N$23) -> 0 | AJ93: =$T93*AI93*(1+$Q93)^AJ$2 -> 0 | AL93: =IF(H93="MULTI","MULTI",IF(COUNTIFS($E$4:$E$1277,H93,$H$4:$H$1277,E93)>0,"Y","N")) -> N | AM93: =T93*((1+Q93)^25) -> 47000.08 | BC93: PTY | BD93: =SUMIF($E$4:$E$1277,$BC93,$Z$4:$Z$1277) -> 0 | BE93: =SUMIF($E$4:$E$1277,$BC93,$AB$4:$AB$1277) -> 0 | BF93: =SUMIF($E$4:$E$1277,$BC93,$AD$4:$AD$1277) -> 0 | BG93: =SUMIF($E$4:$E$1277,$BC93,$AF$4:$AF$1277) -> 0 | BH93: =SUMIF($E$4:$E$1277,$BC93,$AH$4:$AH$1277) -> 0 | BI93: =SUMIF($E$4:$E$1277,$BC93,$AJ$4:$AJ$1277) -> 0
A94: R091 | BC94: PVG | BD94: =SUMIF($E$4:$E$1277,$BC94,$Z$4:$Z$1277) -> 0 | BE94: =SUMIF($E$4:$E$1277,$BC94,$AB$4:$AB$1277) -> 0 | BF94: =SUMIF($E$4:$E$1277,$BC94,$AD$4:$AD$1277) -> 0 | BG94: =SUMIF($E$4:$E$1277,$BC94,$AF$4:$AF$1277) -> 0 | BH94: =SUMIF($E$4:$E$1277,$BC94,$AH$4:$AH$1277) -> 0 | BI94: =SUMIF($E$4:$E$1277,$BC94,$AJ$4:$AJ$1277) -> 0
A95: R092 | BC95: RIX | BD95: =SUMIF($E$4:$E$1277,$BC95,$Z$4:$Z$1277) -> 0 | BE95: =SUMIF($E$4:$E$1277,$BC95,$AB$4:$AB$1277) -> 0 | BF95: =SUMIF($E$4:$E$1277,$BC95,$AD$4:$AD$1277) -> 0 | BG95: =SUMIF($E$4:$E$1277,$BC95,$AF$4:$AF$1277) -> 0 | BH95: =SUMIF($E$4:$E$1277,$BC95,$AH$4:$AH$1277) -> 0 | BI95: =SUMIF($E$4:$E$1277,$BC95,$AJ$4:$AJ$1277) -> 0
A96: R093 | BC96: RUH | BD96: =SUMIF($E$4:$E$1277,$BC96,$Z$4:$Z$1277) -> 0 | BE96: =SUMIF($E$4:$E$1277,$BC96,$AB$4:$AB$1277) -> 0 | BF96: =SUMIF($E$4:$E$1277,$BC96,$AD$4:$AD$1277) -> 0 | BG96: =SUMIF($E$4:$E$1277,$BC96,$AF$4:$AF$1277) -> 0 | BH96: =SUMIF($E$4:$E$1277,$BC96,$AH$4:$AH$1277) -> 0 | BI96: =SUMIF($E$4:$E$1277,$BC96,$AJ$4:$AJ$1277) -> 0
A97: R094 | B97: K4 | C97: Kalitta Air | D97: Cargo | E97: YIP | F97: United States | G97: US | H97: ICN | I97: South Korea | J97: APAC | K97: international | L97: B747-8F | M97: 365 | N97: =M97/365 -> 1 | O97: 10700 | P97: =M97*O97 -> 3905500 | Q97: =IFERROR(VLOOKUP(G97,SCENARIOS!$A$13:$E$18,2,0),0.025) -> 0.02 | R97: =IFERROR(VLOOKUP(L97,INPUTS!$A$107:$B$120,2,0),0.0082) -> 0.0096 | S97: =O97*R97 -> 102.72 | T97: =M97*S97 -> 37492.8 | U97: =T97/INPUTS!$B$7*1000 -> 46866000 | V97: =T97*INPUTS!$B$6 -> 118477.25 | W97: Yes | X97: Yes | Y97: =IFERROR(VLOOKUP(E97,INPUTS!$A$44:$B$103,2,0),0) -> 0 | Z97: =T97*Y97 -> 0 | AA97: =IFERROR(VLOOKUP(E97,INPUTS!$A$44:$C$103,3,0),SCENARIOS!$J$23) -> 0 | AB97: =$T97*AA97*(1+$Q97)^AB$2 -> 0 | AC97: =IFERROR(VLOOKUP($E97,INPUTS!$A$44:$G$103,4,0),SCENARIOS!$K$23) -> 0 | AD97: =$T97*AC97*(1+$Q97)^AD$2 -> 0 | AE97: =IFERROR(VLOOKUP($E97,INPUTS!$A$44:$G$103,5,0),SCENARIOS!$L$23) -> 0 | AF97: =$T97*AE97*(1+$Q97)^AF$2 -> 0 | AG97: =IFERROR(VLOOKUP($E97,INPUTS!$A$44:$G$103,6,0),SCENARIOS!$M$23) -> 0 | AH97: =$T97*AG97*(1+$Q97)^AH$2 -> 0 | AI97: =IFERROR(VLOOKUP($E97,INPUTS!$A$44:$G$103,7,0),SCENARIOS!$N$23) -> 0 | AJ97: =$T97*AI97*(1+$Q97)^AJ$2 -> 0 | AL97: =IF(H97="MULTI","MULTI",IF(COUNTIFS($E$4:$E$1277,H97,$H$4:$H$1277,E97)>0,"Y","N")) -> N | AM97: =T97*((1+Q97)^25) -> 61510.912 | BC97: SAW | BD97: =SUMIF($E$4:$E$1277,$BC97,$Z$4:$Z$1277) -> 0 | BE97: =SUMIF($E$4:$E$1277,$BC97,$AB$4:$AB$1277) -> 0 | BF97: =SUMIF($E$4:$E$1277,$BC97,$AD$4:$AD$1277) -> 0 | BG97: =SUMIF($E$4:$E$1277,$BC97,$AF$4:$AF$1277) -> 0 | BH97: =SUMIF($E$4:$E$1277,$BC97,$AH$4:$AH$1277) -> 0 | BI97: =SUMIF($E$4:$E$1277,$BC97,$AJ$4:$AJ$1277) -> 0
A98: R095 | B98: K4 | C98: Kalitta Air | D98: Cargo | E98: YIP | F98: United States | G98: US | H98: NRT | I98: Japan | J98: APAC | K98: international | L98: B747-8F | M98: 365 | N98: =M98/365 -> 1 | O98: 10500 | P98: =M98*O98 -> 3832500 | Q98: =IFERROR(VLOOKUP(G98,SCENARIOS!$A$13:$E$18,2,0),0.025) -> 0.02 | R98: =IFERROR(VLOOKUP(L98,INPUTS!$A$107:$B$120,2,0),0.0082) -> 0.0096 | S98: =O98*R98 -> 100.8 | T98: =M98*S98 -> 36792 | U98: =T98/INPUTS!$B$7*1000 -> 45990000 | V98: =T98*INPUTS!$B$6 -> 116262.72 | W98: Yes | X98: Yes | Y98: =IFERROR(VLOOKUP(E98,INPUTS!$A$44:$B$103,2,0),0) -> 0 | Z98: =T98*Y98 -> 0 | AA98: =IFERROR(VLOOKUP(E98,INPUTS!$A$44:$C$103,3,0),SCENARIOS!$J$23) -> 0 | AB98: =$T98*AA98*(1+$Q98)^AB$2 -> 0 | AC98: =IFERROR(VLOOKUP($E98,INPUTS!$A$44:$G$103,4,0),SCENARIOS!$K$23) -> 0 | AD98: =$T98*AC98*(1+$Q98)^AD$2 -> 0 | AE98: =IFERROR(VLOOKUP($E98,INPUTS!$A$44:$G$103,5,0),SCENARIOS!$L$23) -> 0 | AF98: =$T98*AE98*(1+$Q98)^AF$2 -> 0 | AG98: =IFERROR(VLOOKUP($E98,INPUTS!$A$44:$G$103,6,0),SCENARIOS!$M$23) -> 0 | AH98: =$T98*AG98*(1+$Q98)^AH$2 -> 0 | AI98: =IFERROR(VLOOKUP($E98,INPUTS!$A$44:$G$103,7,0),SCENARIOS!$N$23) -> 0 | AJ98: =$T98*AI98*(1+$Q98)^AJ$2 -> 0 | AL98: =IF(H98="MULTI","MULTI",IF(COUNTIFS($E$4:$E$1277,H98,$H$4:$H$1277,E98)>0,"Y","N")) -> N | AM98: =T98*((1+Q98)^25) -> 60361.176 | BC98: SCL | BD98: =SUMIF($E$4:$E$1277,$BC98,$Z$4:$Z$1277) -> 0 | BE98: =SUMIF($E$4:$E$1277,$BC98,$AB$4:$AB$1277) -> 0 | BF98: =SUMIF($E$4:$E$1277,$BC98,$AD$4:$AD$1277) -> 0 | BG98: =SUMIF($E$4:$E$1277,$BC98,$AF$4:$AF$1277) -> 0 | BH98: =SUMIF($E$4:$E$1277,$BC98,$AH$4:$AH$1277) -> 0 | BI98: =SUMIF($E$4:$E$1277,$BC98,$AJ$4:$AJ$1277) -> 0
A99: R096 | B99: ABR | C99: ASL Aviation Holdings | D99: Cargo | E99: DUB | F99: Ireland | G99: EU | H99: CDG | I99: France | J99: EU | K99: international | L99: B737-800 | M99: 730 | N99: =M99/365 -> 2 | O99: 780 | P99: =M99*O99 -> 569400 | Q99: =IFERROR(VLOOKUP(G99,SCENARIOS!$A$13:$E$18,2,0),0.025) -> 0.025 | R99: =IFERROR(VLOOKUP(L99,INPUTS!$A$107:$B$120,2,0),0.0082) -> 0.0041 | S99: =O99*R99 -> 3.198 | T99: =M99*S99 -> 2334.54 | U99: =T99/INPUTS!$B$7*1000 -> 2918175 | V99: =T99*INPUTS!$B$6 -> 7377.1464 | W99: Yes | X99: Yes | Y99: =IFERROR(VLOOKUP(E99,INPUTS!$A$44:$B$103,2,0),0) -> 0.02 | Z99: =T99*Y99 -> 46.6908 | AA99: =IFERROR(VLOOKUP(E99,INPUTS!$A$44:$C$103,3,0),SCENARIOS!$J$23) -> 0.06 | AB99: =$T99*AA99*(1+$Q99)^AB$2 -> 158.47906 | AC99: =IFERROR(VLOOKUP($E99,INPUTS!$A$44:$G$103,4,0),SCENARIOS!$K$23) -> 0.15 | AD99: =$T99*AC99*(1+$Q99)^AD$2 -> 448.26129 | AE99: =IFERROR(VLOOKUP($E99,INPUTS!$A$44:$G$103,5,0),SCENARIOS!$L$23) -> 0.3 | AF99: =$T99*AE99*(1+$Q99)^AF$2 -> 1014.333 | AG99: =IFERROR(VLOOKUP($E99,INPUTS!$A$44:$G$103,6,0),SCENARIOS!$M$23) -> 0.4 | AH99: =$T99*AG99*(1+$Q99)^AH$2 -> 1530.1662 | AI99: =IFERROR(VLOOKUP($E99,INPUTS!$A$44:$G$103,7,0),SCENARIOS!$N$23) -> 0.5 | AJ99: =$T99*AI99*(1+$Q99)^AJ$2 -> 2164.0533 | AL99: =IF(H99="MULTI","MULTI",IF(COUNTIFS($E$4:$E$1277,H99,$H$4:$H$1277,E99)>0,"Y","N")) -> N | AM99: =T99*((1+Q99)^25) -> 4328.1067 | BC99: SDF | BD99: =SUMIF($E$4:$E$1277,$BC99,$Z$4:$Z$1277) -> 714.252 | BE99: =SUMIF($E$4:$E$1277,$BC99,$AB$4:$AB$1277) -> 4731.5515 | BF99: =SUMIF($E$4:$E$1277,$BC99,$AD$4:$AD$1277) -> 17413.384 | BG99: =SUMIF($E$4:$E$1277,$BC99,$AF$4:$AF$1277) -> 38451.566 | BH99: =SUMIF($E$4:$E$1277,$BC99,$AH$4:$AH$1277) -> 63680.454 | BI99: =SUMIF($E$4:$E$1277,$BC99,$AJ$4:$AJ$1277) -> 93744.489
A100: R097 | B100: ABR | C100: ASL Aviation Holdings | D100: Cargo | E100: DUB | F100: Ireland | G100: EU | H100: CGN | I100: Germany | J100: EU | K100: international | L100: B737-800 | M100: 730 | N100: =M100/365 -> 2 | O100: 1000 | P100: =M100*O100 -> 730000 | Q100: =IFERROR(VLOOKUP(G100,SCENARIOS!$A$13:$E$18,2,0),0.025) -> 0.025 | R100: =IFERROR(VLOOKUP(L100,INPUTS!$A$107:$B$120,2,0),0.0082) -> 0.0041 | S100: =O100*R100 -> 4.1 | T100: =M100*S100 -> 2993 | U100: =T100/INPUTS!$B$7*1000 -> 3741250 | V100: =T100*INPUTS!$B$6 -> 9457.88 | W100: Yes | X100: Yes | Y100: =IFERROR(VLOOKUP(E100,INPUTS!$A$44:$B$103,2,0),0) -> 0.02 | Z100: =T100*Y100 -> 59.86 | AA100: =IFERROR(VLOOKUP(E100,INPUTS!$A$44:$C$103,3,0),SCENARIOS!$J$23) -> 0.06 | AB100: =$T100*AA100*(1+$Q100)^AB$2 -> 203.17829 | AC100: =IFERROR(VLOOKUP($E100,INPUTS!$A$44:$G$103,4,0),SCENARIOS!$K$23) -> 0.15 | AD100: =$T100*AC100*(1+$Q100)^AD$2 -> 574.69396 | AE100: =IFERROR(VLOOKUP($E100,INPUTS!$A$44:$G$103,5,0),SCENARIOS!$L$23) -> 0.3 | AF100: =$T100*AE100*(1+$Q100)^AF$2 -> 1300.4269 | AG100: =IFERROR(VLOOKUP($E100,INPUTS!$A$44:$G$103,6,0),SCENARIOS!$M$23) -> 0.4 | AH100: =$T100*AG100*(1+$Q100)^AH$2 -> 1961.7516 | AI100: =IFERROR(VLOOKUP($E100,INPUTS!$A$44:$G$103,7,0),SCENARIOS!$N$23) -> 0.5 | AJ100: =$T100*AI100*(1+$Q100)^AJ$2 -> 2774.4273 | AL100: =IF(H100="MULTI","MULTI",IF(COUNTIFS($E$4:$E$1277,H100,$H$4:$H$1277,E100)>0,"Y","N")) -> N | AM100: =T100*((1+Q100)^25) -> 5548.8547 | BC100: SEA | BD100: =SUMIF($E$4:$E$1277,$BC100,$Z$4:$Z$1277) -> 898.9475 | BE100: =SUMIF($E$4:$E$1277,$BC100,$AB$4:$AB$1277) -> 5955.0641 | BF100: =SUMIF($E$4:$E$1277,$BC100,$AD$4:$AD$1277) -> 21916.24 | BG100: =SUMIF($E$4:$E$1277,$BC100,$AF$4:$AF$1277) -> 48394.599 | BH100: =SUMIF($E$4:$E$1277,$BC100,$AH$4:$AH$1277) -> 80147.322 | BI100: =SUMIF($E$4:$E$1277,$BC100,$AJ$4:$AJ$1277) -> 117985.49
A101: R098 | B101: ABR | C101: ASL Aviation Holdings | D101: Cargo | E101: DUB | F101: Ireland | G101: EU | H101: LHR | I101: United Kingdom | J101: EU | K101: international | L101: B757F | M101: 1095 | N101: =M101/365 -> 3 | O101: 440 | P101: =M101*O101 -> 481800 | Q101: =IFERROR(VLOOKUP(G101,SCENARIOS!$A$13:$E$18,2,0),0.025) -> 0.025 | R101: =IFERROR(VLOOKUP(L101,INPUTS!$A$107:$B$120,2,0),0.0082) -> 0.0046 | S101: =O101*R101 -> 2.024 | T101: =M101*S101 -> 2216.28 | U101: =T101/INPUTS!$B$7*1000 -> 2770350 | V101: =T101*INPUTS!$B$6 -> 7003.4448 | W101: Yes | X101: Yes | Y101: =IFERROR(VLOOKUP(E101,INPUTS!$A$44:$B$103,2,0),0) -> 0.02 | Z101: =T101*Y101 -> 44.3256 | AA101: =IFERROR(VLOOKUP(E101,INPUTS!$A$44:$C$103,3,0),SCENARIOS!$J$23) -> 0.06 | AB101: =$T101*AA101*(1+$Q101)^AB$2 -> 150.45104 | AC101: =IFERROR(VLOOKUP($E101,INPUTS!$A$44:$G$103,4,0),SCENARIOS!$K$23) -> 0.15 | AD101: =$T101*AC101*(1+$Q101)^AD$2 -> 425.55387 | AE101: =IFERROR(VLOOKUP($E101,INPUTS!$A$44:$G$103,5,0),SCENARIOS!$L$23) -> 0.3 | AF101: =$T101*AE101*(1+$Q101)^AF$2 -> 962.95028 | AG101: =IFERROR(VLOOKUP($E101,INPUTS!$A$44:$G$103,6,0),SCENARIOS!$M$23) -> 0.4 | AH101: =$T101*AG101*(1+$Q101)^AH$2 -> 1452.6531 | AI101: =IFERROR(VLOOKUP($E101,INPUTS!$A$44:$G$103,7,0),SCENARIOS!$N$23) -> 0.5 | AJ101: =$T101*AI101*(1+$Q101)^AJ$2 -> 2054.4296 | AL101: =IF(H101="MULTI","MULTI",IF(COUNTIFS($E$4:$E$1277,H101,$H$4:$H$1277,E101)>0,"Y","N")) -> N | AM101: =T101*((1+Q101)^25) -> 4108.8592 | BC101: SFO | BD101: =SUMIF($E$4:$E$1277,$BC101,$Z$4:$Z$1277) -> 1262.1857 | BE101: =SUMIF($E$4:$E$1277,$BC101,$AB$4:$AB$1277) -> 8361.33 | BF101: =SUMIF($E$4:$E$1277,$BC101,$AD$4:$AD$1277) -> 30771.947 | BG101: =SUMIF($E$4:$E$1277,$BC101,$AF$4:$AF$1277) -> 67949.431 | BH101: =SUMIF($E$4:$E$1277,$BC101,$AH$4:$AH$1277) -> 112532.49 | BI101: =SUMIF($E$4:$E$1277,$BC101,$AJ$4:$AJ$1277) -> 165659.95
A102: R099 | B102: LHC | C102: Lufthansa Cargo | D102: Cargo | E102: FRA | F102: Germany | G102: EU | H102: PVG | I102: China | J102: APAC | K102: international | L102: B777F | M102: 365 | N102: =M102/365 -> 1 | O102: 9200 | P102: =M102*O102 -> 3358000 | Q102: =IFERROR(VLOOKUP(G102,SCENARIOS!$A$13:$E$18,2,0),0.025) -> 0.025 | R102: =IFERROR(VLOOKUP(L102,INPUTS!$A$107:$B$120,2,0),0.0082) -> 0.0082 | S102: =O102*R102 -> 75.44 | T102: =M102*S102 -> 27535.6 | U102: =T102/INPUTS!$B$7*1000 -> 34419500 | V102: =T102*INPUTS!$B$6 -> 87012.496 | W102: Yes | X102: Yes | Y102: =IFERROR(VLOOKUP(E102,INPUTS!$A$44:$B$103,2,0),0) -> 0.02 | Z102: =T102*Y102 -> 550.712 | AA102: =IFERROR(VLOOKUP(E102,INPUTS!$A$44:$C$103,3,0),SCENARIOS!$J$23) -> 0.06 | AB102: =$T102*AA102*(1+$Q102)^AB$2 -> 1869.2402 | AC102: =IFERROR(VLOOKUP($E102,INPUTS!$A$44:$G$103,4,0),SCENARIOS!$K$23) -> 0.15 | AD102: =$T102*AC102*(1+$Q102)^AD$2 -> 5287.1844 | AE102: =IFERROR(VLOOKUP($E102,INPUTS!$A$44:$G$103,5,0),SCENARIOS!$L$23) -> 0.3 | AF102: =$T102*AE102*(1+$Q102)^AF$2 -> 11963.928 | AG102: =IFERROR(VLOOKUP($E102,INPUTS!$A$44:$G$103,6,0),SCENARIOS!$M$23) -> 0.4 | AH102: =$T102*AG102*(1+$Q102)^AH$2 -> 18048.115 | AI102: =IFERROR(VLOOKUP($E102,INPUTS!$A$44:$G$103,7,0),SCENARIOS!$N$23) -> 0.5 | AJ102: =$T102*AI102*(1+$Q102)^AJ$2 -> 25524.732 | AL102: =IF(H102="MULTI","MULTI",IF(COUNTIFS($E$4:$E$1277,H102,$H$4:$H$1277,E102)>0,"Y","N")) -> N | AM102: =T102*((1+Q102)^25) -> 51049.463 | BC102: SGN | BD102: =SUMIF($E$4:$E$1277,$BC102,$Z$4:$Z$1277) -> 0 | BE102: =SUMIF($E$4:$E$1277,$BC102,$AB$4:$AB$1277) -> 0 | BF102: =SUMIF($E$4:$E$1277,$BC102,$AD$4:$AD$1277) -> 0 | BG102: =SUMIF($E$4:$E$1277,$BC102,$AF$4:$AF$1277) -> 0 | BH102: =SUMIF($E$4:$E$1277,$BC102,$AH$4:$AH$1277) -> 0 | BI102: =SUMIF($E$4:$E$1277,$BC102,$AJ$4:$AJ$1277) -> 0
A103: R100 | B103: LHC | C103: Lufthansa Cargo | D103: Cargo | E103: FRA | F103: Germany | G103: EU | H103: NRT | I103: Japan | J103: APAC | K103: international | L103: B777F | M103: 365 | N103: =M103/365 -> 1 | O103: 9350 | P103: =M103*O103 -> 3412750 | Q103: =IFERROR(VLOOKUP(G103,SCENARIOS!$A$13:$E$18,2,0),0.025) -> 0.025 | R103: =IFERROR(VLOOKUP(L103,INPUTS!$A$107:$B$120,2,0),0.0082) -> 0.0082 | S103: =O103*R103 -> 76.67 | T103: =M103*S103 -> 27984.55 | U103: =T103/INPUTS!$B$7*1000 -> 34980688 | V103: =T103*INPUTS!$B$6 -> 88431.178 | W103: Yes | X103: Yes | Y103: =IFERROR(VLOOKUP(E103,INPUTS!$A$44:$B$103,2,0),0) -> 0.02 | Z103: =T103*Y103 -> 559.691 | AA103: =IFERROR(VLOOKUP(E103,INPUTS!$A$44:$C$103,3,0),SCENARIOS!$J$23) -> 0.06 | AB103: =$T103*AA103*(1+$Q103)^AB$2 -> 1899.717 | AC103: =IFERROR(VLOOKUP($E103,INPUTS!$A$44:$G$103,4,0),SCENARIOS!$K$23) -> 0.15 | AD103: =$T103*AC103*(1+$Q103)^AD$2 -> 5373.3885 | AE103: =IFERROR(VLOOKUP($E103,INPUTS!$A$44:$G$103,5,0),SCENARIOS!$L$23) -> 0.3 | AF103: =$T103*AE103*(1+$Q103)^AF$2 -> 12158.992 | AG103: =IFERROR(VLOOKUP($E103,INPUTS!$A$44:$G$103,6,0),SCENARIOS!$M$23) -> 0.4 | AH103: =$T103*AG103*(1+$Q103)^AH$2 -> 18342.377 | AI103: =IFERROR(VLOOKUP($E103,INPUTS!$A$44:$G$103,7,0),SCENARIOS!$N$23) -> 0.5 | AJ103: =$T103*AI103*(1+$Q103)^AJ$2 -> 25940.896 | AL103: =IF(H103="MULTI","MULTI",IF(COUNTIFS($E$4:$E$1277,H103,$H$4:$H$1277,E103)>0,"Y","N")) -> Y | AM103: =T103*((1+Q103)^25) -> 51881.791 | BC103: SHJ | BD103: =SUMIF($E$4:$E$1277,$BC103,$Z$4:$Z$1277) -> 0 | BE103: =SUMIF($E$4:$E$1277,$BC103,$AB$4:$AB$1277) -> 0 | BF103: =SUMIF($E$4:$E$1277,$BC103,$AD$4:$AD$1277) -> 0 | BG103: =SUMIF($E$4:$E$1277,$BC103,$AF$4:$AF$1277) -> 0 | BH103: =SUMIF($E$4:$E$1277,$BC103,$AH$4:$AH$1277) -> 0 | BI103: =SUMIF($E$4:$E$1277,$BC103,$AJ$4:$AJ$1277) -> 0
A104: R101 | B104: LHC | C104: Lufthansa Cargo | D104: Cargo | E104: FRA | F104: Germany | G104: EU | H104: JFK | I104: United States | J104: US | K104: international | L104: B777F | M104: 730 | N104: =M104/365 -> 2 | O104: 6200 | P104: =M104*O104 -> 4526000 | Q104: =IFERROR(VLOOKUP(G104,SCENARIOS!$A$13:$E$18,2,0),0.025) -> 0.025 | R104: =IFERROR(VLOOKUP(L104,INPUTS!$A$107:$B$120,2,0),0.0082) -> 0.0082 | S104: =O104*R104 -> 50.84 | T104: =M104*S104 -> 37113.2 | U104: =T104/INPUTS!$B$7*1000 -> 46391500 | V104: =T104*INPUTS!$B$6 -> 117277.71 | W104: Yes | X104: Yes | Y104: =IFERROR(VLOOKUP(E104,INPUTS!$A$44:$B$103,2,0),0) -> 0.02 | Z104: =T104*Y104 -> 742.264 | AA104: =IFERROR(VLOOKUP(E104,INPUTS!$A$44:$C$103,3,0),SCENARIOS!$J$23) -> 0.06 | AB104: =$T104*AA104*(1+$Q104)^AB$2 -> 2519.4108 | AC104: =IFERROR(VLOOKUP($E104,INPUTS!$A$44:$G$103,4,0),SCENARIOS!$K$23) -> 0.15 | AD104: =$T104*AC104*(1+$Q104)^AD$2 -> 7126.2051 | AE104: =IFERROR(VLOOKUP($E104,INPUTS!$A$44:$G$103,5,0),SCENARIOS!$L$23) -> 0.3 | AF104: =$T104*AE104*(1+$Q104)^AF$2 -> 16125.294 | AG104: =IFERROR(VLOOKUP($E104,INPUTS!$A$44:$G$103,6,0),SCENARIOS!$M$23) -> 0.4 | AH104: =$T104*AG104*(1+$Q104)^AH$2 -> 24325.72 | AI104: =IFERROR(VLOOKUP($E104,INPUTS!$A$44:$G$103,7,0),SCENARIOS!$N$23) -> 0.5 | AJ104: =$T104*AI104*(1+$Q104)^AJ$2 -> 34402.899 | AL104: =IF(H104="MULTI","MULTI",IF(COUNTIFS($E$4:$E$1277,H104,$H$4:$H$1277,E104)>0,"Y","N")) -> N | AM104: =T104*((1+Q104)^25) -> 68805.798 | BC104: SIN | BD104: =SUMIF($E$4:$E$1277,$BC104,$Z$4:$Z$1277) -> 0 | BE104: =SUMIF($E$4:$E$1277,$BC104,$AB$4:$AB$1277) -> 189041.71 | BF104: =SUMIF($E$4:$E$1277,$BC104,$AD$4:$AD$1277) -> 766660.48 | BG104: =SUMIF($E$4:$E$1277,$BC104,$AF$4:$AF$1277) -> 1865519.4 | BH104: =SUMIF($E$4:$E$1277,$BC104,$AH$4:$AH$1277) -> 3404534.4 | BI104: =SUMIF($E$4:$E$1277,$BC104,$AJ$4:$AJ$1277) -> 5522848.9
A105: R102 | B105: QRC | C105: Qatar Airways Cargo | D105: Cargo | E105: DOH | F105: Qatar | G105: MENA | H105: FRA | I105: Germany | J105: EU | K105: international | L105: B777F | M105: 730 | N105: =M105/365 -> 2 | O105: 4850 | P105: =M105*O105 -> 3540500 | Q105: =IFERROR(VLOOKUP(G105,SCENARIOS!$A$13:$E$18,2,0),0.025) -> 0.045 | R105: =IFERROR(VLOOKUP(L105,INPUTS!$A$107:$B$120,2,0),0.0082) -> 0.0082 | S105: =O105*R105 -> 39.77 | T105: =M105*S105 -> 29032.1 | U105: =T105/INPUTS!$B$7*1000 -> 36290125 | V105: =T105*INPUTS!$B$6 -> 91741.436 | W105: Yes | X105: Yes | Y105: =IFERROR(VLOOKUP(E105,INPUTS!$A$44:$B$103,2,0),0) -> 0 | Z105: =T105*Y105 -> 0 | AA105: =IFERROR(VLOOKUP(E105,INPUTS!$A$44:$C$103,3,0),SCENARIOS!$J$23) -> 0 | AB105: =$T105*AA105*(1+$Q105)^AB$2 -> 0 | AC105: =IFERROR(VLOOKUP($E105,INPUTS!$A$44:$G$103,4,0),SCENARIOS!$K$23) -> 0 | AD105: =$T105*AC105*(1+$Q105)^AD$2 -> 0 | AE105: =IFERROR(VLOOKUP($E105,INPUTS!$A$44:$G$103,5,0),SCENARIOS!$L$23) -> 0 | AF105: =$T105*AE105*(1+$Q105)^AF$2 -> 0 | AG105: =IFERROR(VLOOKUP($E105,INPUTS!$A$44:$G$103,6,0),SCENARIOS!$M$23) -> 0 | AH105: =$T105*AG105*(1+$Q105)^AH$2 -> 0 | AI105: =IFERROR(VLOOKUP($E105,INPUTS!$A$44:$G$103,7,0),SCENARIOS!$N$23) -> 0 | AJ105: =$T105*AI105*(1+$Q105)^AJ$2 -> 0 | AL105: =IF(H105="MULTI","MULTI",IF(COUNTIFS($E$4:$E$1277,H105,$H$4:$H$1277,E105)>0,"Y","N")) -> Y | AM105: =T105*((1+Q105)^25) -> 87254.074 | BC105: STN | BD105: =SUMIF($E$4:$E$1277,$BC105,$Z$4:$Z$1277) -> 65208 | BE105: =SUMIF($E$4:$E$1277,$BC105,$AB$4:$AB$1277) -> 368884.33 | BF105: =SUMIF($E$4:$E$1277,$BC105,$AD$4:$AD$1277) -> 626038.15 | BG105: =SUMIF($E$4:$E$1277,$BC105,$AF$4:$AF$1277) -> 1416609.4 | BH105: =SUMIF($E$4:$E$1277,$BC105,$AH$4:$AH$1277) -> 2137018 | BI105: =SUMIF($E$4:$E$1277,$BC105,$AJ$4:$AJ$1277) -> 3022299.7
A106: R103 | B106: QRC | C106: Qatar Airways Cargo | D106: Cargo | E106: DOH | F106: Qatar | G106: MENA | H106: PVG | I106: China | J106: APAC | K106: international | L106: B777F | M106: 365 | N106: =M106/365 -> 1 | O106: 6300 | P106: =M106*O106 -> 2299500 | Q106: =IFERROR(VLOOKUP(G106,SCENARIOS!$A$13:$E$18,2,0),0.025) -> 0.045 | R106: =IFERROR(VLOOKUP(L106,INPUTS!$A$107:$B$120,2,0),0.0082) -> 0.0082 | S106: =O106*R106 -> 51.66 | T106: =M106*S106 -> 18855.9 | U106: =T106/INPUTS!$B$7*1000 -> 23569875 | V106: =T106*INPUTS!$B$6 -> 59584.644 | W106: Yes | X106: Yes | Y106: =IFERROR(VLOOKUP(E106,INPUTS!$A$44:$B$103,2,0),0) -> 0 | Z106: =T106*Y106 -> 0 | AA106: =IFERROR(VLOOKUP(E106,INPUTS!$A$44:$C$103,3,0),SCENARIOS!$J$23) -> 0 | AB106: =$T106*AA106*(1+$Q106)^AB$2 -> 0 | AC106: =IFERROR(VLOOKUP($E106,INPUTS!$A$44:$G$103,4,0),SCENARIOS!$K$23) -> 0 | AD106: =$T106*AC106*(1+$Q106)^AD$2 -> 0 | AE106: =IFERROR(VLOOKUP($E106,INPUTS!$A$44:$G$103,5,0),SCENARIOS!$L$23) -> 0 | AF106: =$T106*AE106*(1+$Q106)^AF$2 -> 0 | AG106: =IFERROR(VLOOKUP($E106,INPUTS!$A$44:$G$103,6,0),SCENARIOS!$M$23) -> 0 | AH106: =$T106*AG106*(1+$Q106)^AH$2 -> 0 | AI106: =IFERROR(VLOOKUP($E106,INPUTS!$A$44:$G$103,7,0),SCENARIOS!$N$23) -> 0 | AJ106: =$T106*AI106*(1+$Q106)^AJ$2 -> 0 | AL106: =IF(H106="MULTI","MULTI",IF(COUNTIFS($E$4:$E$1277,H106,$H$4:$H$1277,E106)>0,"Y","N")) -> N | AM106: =T106*((1+Q106)^25) -> 56670.172 | BC106: SVO | BD106: =SUMIF($E$4:$E$1277,$BC106,$Z$4:$Z$1277) -> 0 | BE106: =SUMIF($E$4:$E$1277,$BC106,$AB$4:$AB$1277) -> 0 | BF106: =SUMIF($E$4:$E$1277,$BC106,$AD$4:$AD$1277) -> 0 | BG106: =SUMIF($E$4:$E$1277,$BC106,$AF$4:$AF$1277) -> 0 | BH106: =SUMIF($E$4:$E$1277,$BC106,$AH$4:$AH$1277) -> 0 | BI106: =SUMIF($E$4:$E$1277,$BC106,$AJ$4:$AJ$1277) -> 0
A107: R104 | B107: QRC | C107: Qatar Airways Cargo | D107: Cargo | E107: DOH | F107: Qatar | G107: MENA | H107: JFK | I107: United States | J107: US | K107: international | L107: B777F | M107: 365 | N107: =M107/365 -> 1 | O107: 11000 | P107: =M107*O107 -> 4015000 | Q107: =IFERROR(VLOOKUP(G107,SCENARIOS!$A$13:$E$18,2,0),0.025) -> 0.045 | R107: =IFERROR(VLOOKUP(L107,INPUTS!$A$107:$B$120,2,0),0.0082) -> 0.0082 | S107: =O107*R107 -> 90.2 | T107: =M107*S107 -> 32923 | U107: =T107/INPUTS!$B$7*1000 -> 41153750 | V107: =T107*INPUTS!$B$6 -> 104036.68 | W107: Yes | X107: Yes | Y107: =IFERROR(VLOOKUP(E107,INPUTS!$A$44:$B$103,2,0),0) -> 0 | Z107: =T107*Y107 -> 0 | AA107: =IFERROR(VLOOKUP(E107,INPUTS!$A$44:$C$103,3,0),SCENARIOS!$J$23) -> 0 | AB107: =$T107*AA107*(1+$Q107)^AB$2 -> 0 | AC107: =IFERROR(VLOOKUP($E107,INPUTS!$A$44:$G$103,4,0),SCENARIOS!$K$23) -> 0 | AD107: =$T107*AC107*(1+$Q107)^AD$2 -> 0 | AE107: =IFERROR(VLOOKUP($E107,INPUTS!$A$44:$G$103,5,0),SCENARIOS!$L$23) -> 0 | AF107: =$T107*AE107*(1+$Q107)^AF$2 -> 0 | AG107: =IFERROR(VLOOKUP($E107,INPUTS!$A$44:$G$103,6,0),SCENARIOS!$M$23) -> 0 | AH107: =$T107*AG107*(1+$Q107)^AH$2 -> 0 | AI107: =IFERROR(VLOOKUP($E107,INPUTS!$A$44:$G$103,7,0),SCENARIOS!$N$23) -> 0 | AJ107: =$T107*AI107*(1+$Q107)^AJ$2 -> 0 | AL107: =IF(H107="MULTI","MULTI",IF(COUNTIFS($E$4:$E$1277,H107,$H$4:$H$1277,E107)>0,"Y","N")) -> N | AM107: =T107*((1+Q107)^25) -> 98947.919 | BC107: SVX | BD107: =SUMIF($E$4:$E$1277,$BC107,$Z$4:$Z$1277) -> 0 | BE107: =SUMIF($E$4:$E$1277,$BC107,$AB$4:$AB$1277) -> 0 | BF107: =SUMIF($E$4:$E$1277,$BC107,$AD$4:$AD$1277) -> 0 | BG107: =SUMIF($E$4:$E$1277,$BC107,$AF$4:$AF$1277) -> 0 | BH107: =SUMIF($E$4:$E$1277,$BC107,$AH$4:$AH$1277) -> 0 | BI107: =SUMIF($E$4:$E$1277,$BC107,$AJ$4:$AJ$1277) -> 0
